Workbook

Sheet Тест кейсы API
A1: Модуль | B1: ID | C1: Приоритет | D1: Название тест кейса | E1: Описание | F1: Предусловия | G1: Шаги воспроизведения | H1: ОР | I1: Скринкаст/скриншот | J1: Ссылка на БР | K1: Статус проверки | L1: Комментарии
A2: whom_we_helped | B2: API_w_w_hlpd_1 | C2: Высокий | D2: Успешное получение списка опубликованных завершенных запросов при запросе на эндпоинт whom_we_helped/ | E2: Проверить, что по умолчанию эндпоинт возвращает успешный ответ с корректной структурой данных и пагинацией | F2: 1.Открыто приложение Postman 2.Ввести адрес тестового стенда: pl.rassokha.pro:8000/api/v1 3.API доступен и авторизация не требуется для GET-запроса | G2: 1. Создать GET запрос на эндпоинт whom_we_helped/ 2. Отправить запрос | H2: Ошибки в структуре ответа нет "Ответ приходит без ошибок 200 ок { "count": integer, "next": "string($uri)", "previous": "string($uri)", "results": [ { "images": "string($uri)", "text": "string" } ] } | K2: Passed
A3: whom_we_helped | B3: API_w_w_hlpd_2 | C3: Высокий | D3: Корректная работа пагинации - переход по страницам при запросе на эндпоинт whom_we_helped/ | E3: Проверить, что параметр page корректно разделяет результаты на страницы | F3: 1.Открыто приложение Postman 2.Открыт тестовый стенд: pl.rassokha.pro:8000/api/v1 3.API доступен и авторизация не требуется для GET-запроса | G3: 1. Создать GET запрос на эндпоинт whom_we_helped/ 2. Во вкладке params вставить key: page 3. Во вкладке params вставить value: integer, где номер страницы не превышает существующие количество страниц 4. Отправить запрос | H3: Ошибки в структуре ответа нет "Ответ приходит без ошибок 200 ок { "count": integer, "next": "string($uri)", "previous": "string($uri)", "results": [ { "images": "string($uri)", "text": "string" } ] } | K3: Passed
A4: whom_we_helped | B4: API_w_w_hlpd_3 | C4: Высокий | D4: Проверка ответа при отсутствии данных(пустой параметр)при запросе на эндпоинт whom_we_helped/ | E4: Проверить поведение API припустом вводе | F4: 1.Открыто приложение Postman 2.Открыт тестовый стенд: pl.rassokha.pro:8000/api/v1 3.API доступен и авторизация не требуется для GET-запроса | G4: 1. Создать GET запрос на эндпоинт whom_we_helped/ 2. Во вкладке params вставить key: page 3.Отправить запрос | H4: Ошибки в структуре ответа нет "Ответ приходит без ошибок 200 ок { "count": integer, "next": "string($uri)", "previous": "string($uri)", "results": [ { "images": "string($uri)", "text": "string" } ] } | K4: Passed
A5: whom_we_helped | B5: API_w_w_hlpd_4 | C5: Высокий | D5: Проверка запроса с неверным HTTP-методом OPTIONS при запросе на эндпоинт whom_we_helped/ | E5: Отправить запрос с методом OPTIONS https://pl.rassokha.pro:8000/api/v1/whom_we_helped/ | F5: 1.Открыто приложение Postman 2.Открыт тестовый стенд: pl.rassokha.pro:8000/api/v1 3.API доступен и авторизация не требуется для OPTIONS-запроса | G5: 1. Создать OPTIONS запрос на эндпоинт whom_we_helped/ 2. Отправить запрос | H5: 405 Method Not Allowed { "detail": "Метод \"OPTIONS\" не разрешен." } | K5: Skipped
A6: whom_we_helped | B6: API_w_w_hlpd_5 | C6: Высокий | D6: Получение отчета со всеми заполненными полями при запросе на эндпоинт whom_we_helped/ | E6: Проверить, что в ответе присутствуют посты, у которых заполнены все обязательные и необязательные поля (например, id, image_url, title, description,minLength), и их значения соответствуют ожидаемым типам данных | F6: 1.Открыто приложение Postman 2.Открыт тестовый стенд: pl.rassokha.pro:8000/api/v1 3.API доступен и авторизация не требуется для GET-запроса | G6: 1. Создать GET запрос на эндпоинт whom_we_helped/ 2. Отправить запрос | H6: Ошибки в структуре ответа нет "Ответ приходит без ошибок 200 ок | K6: Skipped
A7: whom_we_helped | B7: API_w_w_hlpd_6 | C7: Высокий | D7: Получение поста только с описанием (без фотографии) при запросе на эндпоинт whom_we_helped/ | E7: Проверить, как система обрабатывает пост, у которого есть текстовое описание, но отсутствует фотография | F7: 1.Открыто приложение Postman 2.Открыт тестовый стенд: pl.rassokha.pro:8000/api/v1 3.API доступен и авторизация не требуется для GET-запроса | G7: 1. Создать GET запрос на эндпоинт whom_we_helped/ 2. Отправить запрос | H7: Ошибки в структуре ответа нет "Ответ приходит без ошибок 200 ок | K7: Skipped
A8: whom_we_helped | B8: API_w_w_hlpd_7 | C8: Высокий | D8: Получение поста с описанием на иностранном языке при запросе на эндпоинт whom_we_helped/ | E8: Проверить, что отчеты, содержащие в описании символы иностранных языков (например, English, 中文), корректно отображаются в ответе API без искажений (проблем с кодировкой). | F8: 1.Открыто приложение Postman 2.Открыт тестовый стенд: pl.rassokha.pro:8000/api/v1 3.API доступен и авторизация не требуется для GET-запроса | G8: 1. Создать GET запрос на эндпоинт whom_we_helped/ 2.Отправить запрос | H8: Ошибки в структуре ответа нет "Ответ приходит без ошибок 200 ок | K8: Skipped
A9: whom_we_helped | B9: API_w_w_hlpd_8 | C9: Высокий | D9: Проверка структуры данных одного поста при запросе на эндпоинт whom_we_helped/ | E9: Проверить, что каждый элемент в массиве содержит ожидаемый набор полей | F9: 1.Открыто приложение Postman 2.Открыт тестовый стенд: pl.rassokha.pro:8000/api/v1 3.API доступен и авторизация не требуется для GET-запроса | G9: 1. Создать GET запрос на эндпоинт whom_we_helped/ 2.Отправить запрос | H9: Ошибки в структуре ответа нет "Ответ приходит без ошибок 200 ок | K9: Skipped
A10: whom_we_helped | B10: API_w_w_hlpd_9 | C10: Высокий | D10: Проверка значения по умолчания для параметра page при запросе на эндпоинт whom_we_helped/ | E10: Убедиться, что запросы /api/v1/whom_we_helped/ и /api/v1/whom_we_helped/?page=1 возвращают идентичный результат | F10: 1.Открыто приложение Postman 2.Открыт тестовый стенд: pl.rassokha.pro:8000/api/v1 3.API доступен и авторизация не требуется для GET-запроса | G10: 1. Отправить GET /api/v1/whom_we_helped/ 2. Отправить GET /api/v1/whom_we_helped/?page=1 3. Сравнить ответы | H10: Ошибки в структуре ответа нет "Ответ приходит без ошибок 200 ок { "count": integer, "next": "string($uri)", "previous": "string($uri)", "results": [ { "images": "string($uri)", "text": "string" } ] } | K10: Blocked
A11: whom_we_helped | B11: API_w_w_hlpd_10 | C11: Высокий | D11: Проверка запроса с буквенным типом параметра page при запросе на эндпоинт whom_we_helped/ | E11: Отправить запрос с параметром page, имеющим буквенное значение (например, page=abc). | F11: 1.Открыто приложение Postman 2.Открыт тестовый стенд: pl.rassokha.pro:8000/api/v1 3.API доступен и авторизация не требуется для GET-запроса | G11: 1. Создать GET запрос на эндпоинт whom_we_helped/ 2. Во вкладке params вставить key: page 3. Во вкладке params вставить value: abc 2.Отправить запрос | H11: 404 Not Found Body ответа: { "detail": "Неправильная страница" } | K11: Skipped
A12: whom_we_helped | B12: API_w_w_hlpd_11 | C12: Высокий | D12: Обработка запроса с отрицательным значением параметра page при запросе на эндпоинт whom_we_helped/ | E12: Отправить запрос с page=-1 | F12: 1.Открыто приложение Postman 2.Открыт тестовый стенд: pl.rassokha.pro:8000/api/v1 3.API доступен и авторизация не требуется для GET-запроса | G12: 1. Создать GET запрос на эндпоинт whom_we_helped/ 2. Во вкладке params вставить key: page 3. Во вкладке params вставить value: -1 2.Отправить запрос | H12: 404 Not Found Body ответа: { "detail": "Неправильная страница" } | K12: Passed
A13: whom_we_helped | B13: API_w_w_hlpd_12 | C13: Высокий | D13: Проверка обработки запроса со спецсимволами при запросе на эндпоинт whom_we_helped/ | E13: Отправить запрос с page=+2 | F13: 1.Открыто приложение Postman 2.Открыт тестовый стенд: pl.rassokha.pro:8000/api/v1 3.API доступен и авторизация не требуется для GET-запроса | G13: 1. Создать GET запрос на эндпоинт whom_we_helped/ 2. Во вкладке params вставить key: page 3. Во вкладке params вставить value: +2 2.Отправить запрос | H13: 404 Not Found Body ответа: { "detail": "Неправильная страница" } | K13: Skipped
... A64: they_need_help_too | B64: API_they_nd_hlp_2 | C64: Средний | D64: Получение списка семей которым нужна помощь неверным HTTP-методом | E64: Отправить запрос с методом POST https://pl.rassokha.pro:8000/api/v1/they_need_help_too/ | F64: 1.Открыто приложение Postman 2.Открыт тестовый стенд: pl.rassokha.pro:8000/api/v1 3.API доступен и авторизация не требуется для POST-запроса | G64: 1. Создать POST запрос на эндпоинт they_need_help_too/ 2. Отправить запрос | H64: 405 Method Not Allowed { "detail": "Метод \"POST\" не разрешен." } | K64: Passed
A65: they_need_help_too | B65: API_they_nd_hlp_3 | C65: Средний | D65: Успешное получение существующей семьи которой нужна помощь | E65: Отправить запрос с методом GET https://pl.rassokha.pro:8000/api/v1/they_need_help_too/ | F65: 1. Открыто приложение Postman 2. Используется тестовый стенд pl.rassokha.pro:8000/api/v1 3.API доступен и авторизация не требуется для GET-запроса | G65: 1. Создать GET запрос на эндпоинт they_need_help_too/{id}/ где {id} - существующий идентификатор семьи 2.Отправить запрос | H65: Возвращается код 200 OK Тело ответа: [ { "id": integer, "family_name": "string", "image": "string($uri)" } ] | I65: they_need_help_too_bg1.png | J65: QA_Pomogi_2_39_Тестовая документация | K65: Blocked
A66: team_member | B66: API_tm_mmbr_1 | C66: Средний | D66: Успешное получение списка членов команды | E66: Отправить запрос с методом GET https://pl.rassokha.pro:8000/api/v1/team_member/ | F66: 1. Открыто приложение Postman 2. Используется тестовый стенд pl.rassokha.pro:8000/api/v1 3.API доступен и авторизация не требуется для GET-запроса | G66: 1. Создать GET запрос на эндпоинт team_member/ 2.Отправить запрос | H66: Возвращается код 200 OK [ { "name": "string", "member_title": "string", "photo": "string($uri)" } ] | K66: Passed
A67: team_member | B67: API_tm_mmbr_2 | C67: Средний | D67: Получение списка членов команды недопустимым HTTP-методом | E67: Отправить запрос с методом POST https://pl.rassokha.pro:8000/api/v1/team_member/ | F67: 1.Открыто приложение Postman 2.Открыт тестовый стенд: pl.rassokha.pro:8000/api/v1 3.API доступен и авторизация не требуется для POST-запроса | G67: 1. Создать POST запрос на эндпоинт team_member/ 2. Отправить запрос | H67: 405 Method Not Allowed { "detail": "Метод \"POST\" не разрешен." } | K67: Passed
A68: team_member | B68: API_tm_mmbr_3 | C68: Средний | D68: Успешное получение существующего члена команды | E68: Отправить запрос с методом GET https://pl.rassokha.pro:8000/api/v1/team_member/{id}/ | F68: 1. Открыто приложение Postman 2. Используется тестовый стенд pl.rassokha.pro:8000/api/v1 3.API доступен и авторизация не требуется для GET-запроса | G68: 1. Создать GET запрос на эндпоинт team_member/{id}/ где {id} - существующий идентификатор члена команды 2.Отправить запрос | H68: Возвращается код 200 OK [ { "name": "string", "member_title": "string", "photo": "string($uri)" } ] | K68: Passed
A69: team_member | B69: API_tm_mmbr_4 | C69: Средний | D69: Попытка получения несуществующего члена команды | E69: Отправить запрос с методом GET https://pl.rassokha.pro:8000/api/v1/team_member/{id}/ | F69: 1. Открыто приложение Postman 2. Используется тестовый стенд pl.rassokha.pro:8000/api/v1 3. Убедиться, что челена команды {id} НЕ существует | G69: 1. Создать GET запрос на эндпоинт team_member/{id}/ 2.Отправить запрос | H69: Возвращается код 404 Not Found Тело ответа: { "detail": "No TeamMember matches the given query." } | K69: Passed
A70: team_member | B70: API_tm_mmbr_5 | C70: Средний | D70: Попытка получения члена команды с нечисловым ID | E70: Отправить запрос с методом GET https://pl.rassokha.pro:8000/api/v1/team_member/{id}/ | F70: 1. Открыто приложение Postman 2. Используется тестовый стенд pl.rassokha.pro:8000/api/v1 3.API доступен и авторизация не требуется для GET-запроса | G70: 1. Создать GET запрос на эндпоинт team_member/abc 2.Отправить запрос | H70: Возвращается код 404 Not Found Тело ответа: { "detail": "Страница не найдена." } | K70: Passed
A71: team_member | B71: API_tm_mmbr_6 | C71: Средний | D71: Получение существующего члена команды недопустимым HTTP-методом | E71: Отправить запрос с методом POST https://pl.rassokha.pro:8000/api/v1/team_member/{id}/ | F71: 1.Открыто приложение Postman 2.Открыт тестовый стенд: pl.rassokha.pro:8000/api/v1 3.API доступен и авторизация не требуется для POST-запроса | G71: 1. Создать POST запрос на эндпоинт team_member/{id}/ где {id} - существующий идентификатор члена команды 2.Отправить запрос | H71: 405 Method Not Allowed { "detail": "Метод \"POST\" не разрешен." } | K71: Passed
A72: social_links | B72: API_scl_lnks_1 | C72: Средний | D72: Успешное получение списка существующих социальных ссылок | E72: Отправить запрос с методом GET https://pl.rassokha.pro:8000/api/v1/social_links/ | F72: 1. Открыто приложение Postman 2. Используется тестовый стенд pl.rassokha.pro:8000/api/v1 3.API доступен и авторизация не требуется для GET-запроса | G72: 1. Создать GET запрос на эндпоинт social_links/ 2.Отправить запрос | H72: Возвращается код 200 OK Тело ответа: [ { "label": "string", "link": "string($uri)", "icon": "string", "slug": "string" } ] | K72: Passed
A73: social_links | B73: API_scl_lnks_2 | C73: Средний | D73: Получение списка существующих социальных ссылок неверным HTTP-методом | E73: Отправить запрос с методом POST https://pl.rassokha.pro:8000/api/v1/social_links/ | F73: 1.Открыто приложение Postman 2.Открыт тестовый стенд: pl.rassokha.pro:8000/api/v1 3.API доступен и авторизация не требуется для POST-запроса | G73: 1. Создать POST запрос на эндпоинт social_links/ 2.Отправить запрос | H73: Возвращается код 405 Method Not Allowed { "detail": "Метод \"POST\" не разрешен." } | K73: Passed
A74: social_links | B74: API_scl_lnks_3 | C74: Средний | D74: Успешное получение существующей социальной ссылки | E74: Отправить запрос с методом GET https://pl.rassokha.pro:8000/api/v1/social_links/{slug}/ | F74: 1. Открыто приложение Postman 2. Используется тестовый стенд pl.rassokha.pro:8000/api/v1 3.API доступен и авторизация не требуется для GET-запроса | G74: 1. Создать GET запрос на эндпоинт social_links/{slug}/ где {slug} - существующая социальная ссылка 2.Отправить запрос | H74: Возвращается код 200 OK Тело ответа: [ { "label": "string", "link": "string($uri)", "icon": "string", "slug": "string" } ] | K74: Passed
A75: social_links | B75: API_scl_lnks_4 | C75: Средний | D75: Попытка получение не существующей социальной ссылки | E75: Отправить запрос с методом GET https://pl.rassokha.pro:8000/api/v1/social_links/{slug}/ | F75: 1. Открыто приложение Postman 2. Используется тестовый стенд pl.rassokha.pro:8000/api/v1 3.Убедиться, что социальной ссылки {slug} НЕ существует | G75: 1. Создать GET запрос на эндпоинт social_links/{slug}/ 2.Отправить запрос | H75: Возвращается код 404 Not Found Тело ответа: { "detail": "No SocialLink matches the given query." } | K75: Passed
A76: social_links | B76: API_scl_lnks_5 | C76: Средний | D76: Попытка получения социальной ссылки c нестрочным SLUG | E76: Отправить запрос с методом GET https://pl.rassokha.pro:8000/api/v1/social_links/{slug}/ | F76: 1. Открыто приложение Postman 2. Используется тестовый стенд pl.rassokha.pro:8000/api/v1 3.API доступен и авторизация не требуется для GET-запроса | G76: 1. Создать GET запрос на эндпоинт social_links/12/ 2.Отправить запрос | H76: Возвращается код 404 Not Found Тело ответа: { "detail": "No SocialLink matches the given query." } | K76: Passed
A77: social_links | B77: API_scl_lnks_6 | C77: Средний | D77: Получение существующей социальной ссылки неверным HTTP-методом | E77: Отправить запрос с методом POST https://pl.rassokha.pro:8000/api/v1/social_links/{slug}/ | F77: 1. Открыто приложение Postman 2. Используется тестовый стенд pl.rassokha.pro:8000/api/v1 3.API доступен и авторизация не требуется для POST-запроса | G77: 1. Создать POST запрос на эндпоинт social_links/{slug}/ 2.Отправить запрос | H77: 405 Method Not Allowed { "detail": "Метод \"POST\" не разрешен." } | K77: Passed
... A80: family_applications_list | B80: API_fml_pplctns_lst_3 | C80: Высокий | D80: Получение списка заявок и списка городов заявок: с указанием неверного метода | E80: Отправить запрос с методом POST https://pl.rassokha.pro:8000/api/v1/family_applications_list/ | F80: 1. Открыто приложение Postman 2. Используется тестовый стенд pl.rassokha.pro:8000/api/v1 3.API доступен и авторизация не требуется для POST-запроса | G80: 1. Создать POST запрос на эндпоинт /family_applications_list/ 2. Во вкладке Params ввести: key: "limit", value: 5 key: "offset", value: 5 3. Отправить запрос | H80: 405 Method Not Allowed { "detail": "Метод \"POST\" не разрешен." } | K80: Passed
A81: family_applications_list | B81: API_fml_pplctns_lst_4 | C81: Высокий | D81: Получение списка заявок и списка городов заявок: параметры = "string" | E81: Отправить запрос с методом GET https://pl.rassokha.pro:8000/api/v1/family_applications_list/ | F81: 1. Открыто приложение Postman 2. Используется тестовый стенд pl.rassokha.pro:8000/api/v1 3.API доступен и авторизация не требуется для GET-запроса | G81: 1. Создать GET запрос на эндпоинт /family_applications_list/ 2. Во вкладке Params ввести: key: "limit", value: "12" key: "offset", value: "12" 3. Отправить запрос | H81: 400 Bad Request | I81: API_fml_pplctns_lst_2.png | J81: QA_Pomogi_2_39_Тестовая документация | K81: Failed
A82: family_applications_list | B82: API_fml_pplctns_lst_5 | C82: Высокий | D82: Получение списка заявок и списка городов заявок: параметры = null | E82: Отправить запрос с методом GET https://pl.rassokha.pro:8000/api/v1/family_applications_list/ | F82: 1. Открыто приложение Postman 2. Используется тестовый стенд pl.rassokha.pro:8000/api/v1 3.API доступен и авторизация не требуется для GET-запроса | G82: 1. Создать GET запрос на эндпоинт /family_applications_list/ 2. Во вкладке Params ввести: key: "limit", value: null key: "offset", value: null 3. Отправить запрос | H82: 200 Ок { "count": integer, "next": "string($uri)", "previous": "string($uri)", "results": [ { "id": integer, "city": "string", "full_name": "string", "status": "string" } ] } | K82: Passed
A83: family_applications_list | B83: API_fml_pplctns_lst_6 | C83: Высокий | D83: Получение списка заявок и списка городов заявок: параметры = дробь | E83: Отправить запрос с методом GET https://pl.rassokha.pro:8000/api/v1/family_applications_list/ | F83: 1. Открыто приложение Postman 2. Используется тестовый стенд pl.rassokha.pro:8000/api/v1 3.API доступен и авторизация не требуется для GET-запроса | G83: 1. Создать GET запрос на эндпоинт /family_applications_list/ 2. Во вкладке Params ввести: key: "limit", value: 2.2 key: "offset", value: 2.2 3. Отправить запрос | H83: 400 Bad Request | I83: API_fml_pplctns_lst_1.png | J83: QA_Pomogi_2_39_Тестовая документация | K83: Failed
A84: family_applications_list | B84: API_fml_pplctns_lst_7 | C84: Высокий | D84: Получение списка заявок и списка городов заявок: с передачей параметра "limit" со значением, превышающим количество созданных заявок | E84: Отправить запрос с методом GET https://pl.rassokha.pro:8000/api/v1/family_applications_list/ | F84: 1. Открыто приложение Postman 2. Используется тестовый стенд pl.rassokha.pro:8000/api/v1 3.API доступен и авторизация не требуется для GET-запроса | G84: 1. Создать GET запрос на эндпоинт /family_applications_list/ 2. Во вкладке Params ввести: key: "limit", value: integer (где integer - целое число, превышающее количество созданных заявок) 3. Отправить запрос | H84: Список = количеству созданных заявок без каких-либо добавлений 200 Ок { "count": integer, "next": "string($uri)", "previous": "string($uri)", "results": [ { "id": integer, "city": "string", "full_name": "string", "status": "string" } ] } | K84: Passed
A85: family_applications_list | B85: API_fml_pplctns_lst_8 | C85: Высокий | D85: Получение списка заявок и списка городов заявок: с передачей параметра "offset" со значением, превышающим количество созданных заявок | E85: Отправить запрос с методом GET https://pl.rassokha.pro:8000/api/v1/family_applications_list/ | F85: 1. Открыто приложение Postman 2. Используется тестовый стенд pl.rassokha.pro:8000/api/v1 3.API доступен и авторизация не требуется для GET-запроса | G85: 1. Создать GET запрос на эндпоинт /family_applications_list/ 2. Во вкладке Params ввести: key: "offset", value: integer (где integer - целое число, превышающее количество созданных заявок) 3. Отправить запрос | H85: 200 Ок { "count": integer, "next": "null, "previous": "string($uri)", "results": [] } | K85: Passed
A86: family_applications_list | B86: API_fml_pplctns_lst_9 | C86: Высокий | D86: Получение списка городов заявок | E86: Отправить запрос с методом GET https://pl.rassokha.pro:8000/api/v1/family_applications_list/cities/ | F86: 1. Открыто приложение Postman 2. Используется тестовый стенд pl.rassokha.pro:8000/api/v1 3.API доступен и авторизация не требуется для GET-запроса | G86: 1.Создать GET запрос на эндпоинт /family_applications_list/cities/ 2. Отправить запрос | H86: список городов, указанных при регистрации заявки на оказание помощи в алфавитном порядке 200 ОК [ "string", "string" ] | I86: API_fml_pplctns_lst_bg_3.png | J86: QA_Pomogi_2_39_Тестовая документация | K86: Passed
A87: family_applications_list | B87: API_fml_pplctns_lst_10 | C87: Высокий | D87: Получение списка городов заявок: с передачей параметров | E87: Отправить запрос с методом GET https://pl.rassokha.pro:8000/api/v1/family_applications_list/cities/ | F87: 1. Открыто приложение Postman 2. Используется тестовый стенд pl.rassokha.pro:8000/api/v1 3.API доступен и авторизация не требуется для GET-запроса | G87: 1. Создать GET запрос на эндпоинт /family_applications_list/cities/ 2. Во вкладке Params ввести: key: "limit", value: 5 key: "offset", value: 5 3. Отправить запрос | H87: список из 5 городов в алфавитном порядке, начиная в шестого по порядку (указанные при регистрации заявки на оказание помощи) 200 ОК [ "string", "string" ] | J87: QA_Pomogi_2_39_Тестовая документация | K87: Blocked
A88: family_applications_list | B88: API_fml_pplctns_lst_11 | C88: Высокий | D88: Получение списка городов заявок: с указанием неверного метода | E88: Отправить запрос с методом POST https://pl.rassokha.pro:8000/api/v1/family_applications_list/cities/ | F88: 1. Открыто приложение Postman 2. Используется тестовый стенд pl.rassokha.pro:8000/api/v1 3.API доступен и авторизация не требуется для POST-запроса | G88: 1.Создать POST запрос на эндпоинт /family_applications_list/cities/ 2. Отправить запрос | H88: 405 Method Not Allowed { "detail": "Метод \"POST\" не разрешен." } | K88: Passed
A89: family_applications_list | B89: API_fml_pplctns_lst_12 | C89: Высокий | D89: Получение списка городов заявок после заведения нового города | E89: Отправить запрос с методом GET https://pl.rassokha.pro:8000/api/v1/family_applications_list/cities/ | F89: 1) Base URL: pl.rassokha.pro:8000/api/v1 2) Создать заявку с городом, которого еще не было в базе: Отправить POST на эндпоинт /application_family/ С телом Json { "first_name": "string", "last_name": "string", "middle_name": "string", "phone": "string", "email": "string($email)", "city": "string", "district": "string", "address": "string", "situation": "string", "accept_confidential_policy": true } где "first_name", "last_name", "middle_name", "city" : поле должно начинаться с буквы и содержать кириллицу, пробел, тире, количество символов от 1 до 200 "phone" : формат ввода номера: <+79104366339>, минимальное количнство символов 1. "email": латиница от 1 до 254 символов "district" : поле может содержать кириллицу, пробел, дефис, от 1 до 200 символов "address": поле может содержать кириллицу, цифры, -, /, запятую, точку, пробел, от 1 до 500 символов "situation": кириллица от 1 до 4000 символов | G89: 1.Создать GET запрос на эндпоинт /family_applications_list/cities/ 2. Отправить запрос | H89: в списке городов есть город из новой заявки 200 ОК [ "string", "string" ] | K89: Passed
A90: family_applications_list | B90: API_fml_pplctns_lst_13 | C90: Высокий | D90: Получение информации о зарегистрированной заявке на получение помощи | E90: Отправить запрос с методом GET https://pl.rassokha.pro:8000/api/v1/family_applications_list/{id}/ | F90: 1. Открыто приложение Postman 2. Используется тестовый стенд pl.rassokha.pro:8000/api/v1 3.API доступен и авторизация не требуется для GET-запроса | G90: Отправить GET запрос на эндпоинт /family_applications_list/{id}/ где {id} = integer, соответствует id зарегистрированной заявке | H90: 200 ОК { "id": integer, "city": "string", "full_name": "string", "status": "string" } id соответствует запрашиваемому id | K90: Passed
A91: family_applications_list | B91: API_fml_pplctns_lst_14 | C91: Высокий | D91: Получение информации о несуществующей заявке на получение помощи | E91: Отправить запрос с методом GET https://pl.rassokha.pro:8000/api/v1/family_applications_list/{id}/ | F91: 1. Открыто приложение Postman 2. Используется тестовый стенд pl.rassokha.pro:8000/api/v1 3.API доступен и авторизация не требуется для GET-запроса | G91: Отправить GET запрос на эндпоинт /family_applications_list/{id}/ где {id} = integer, число превышающее значение ранее зарегистрированных заявок | H91: 404 Not Found { "detail": "No FamilyApplication matches the given query." } | K91: Passed
A92: family_applications_list | B92: API_fml_pplctns_lst_15 | C92: Высокий | D92: Получение информации о зарегистрированной заявке на получение помощи: при передаче id="string" | E92: Отправить запрос с методом GET https://pl.rassokha.pro:8000/api/v1/family_applications_list/{id}/ | F92: 1. Открыто приложение Postman 2. Используется тестовый стенд pl.rassokha.pro:8000/api/v1 3.API доступен и авторизация не требуется для GET-запроса | G92: Отправить GET запрос на эндпоинт /family_applications_list/"id"/ где id = integer, соответствует id зарегистрированной заявке | H92: 404 Not Found { "detail": "Страница не найдена." } | K92: Passed
A93: family_applications_list | B93: API_fml_pplctns_lst_19 | C93: Высокий | D93: Получение информации о зарегистрированной заявке на получение помощи: при передаче иного метода | E93: Отправить запрос с методом POST https://pl.rassokha.pro:8000/api/v1/family_applications_list/{id}/ | F93: 1. Открыто приложение Postman 2. Используется тестовый стенд pl.rassokha.pro:8000/api/v1 3.API доступен и авторизация не требуется для POST-запроса | G93: Отправить POST запрос на эндпоинт /family_applications_list/2/ | H93: 405 Method Not Allowed { "detail": "Метод \"POST\" не разрешен." } | K93: Passed
A94: question_application | B94: API_qstn_pplctn_1 | C94: Высокий | D94: Создание POST -запроса на эндпоинт /question_application/ | E94: Проверка успешного создания заявки с данными из документации swagger | F94: 1.Открыто приложение Postman 2.Ввести адрес тестового стенда: pl.rassokha.pro:8000/api/v1 3.API доступен и авторизация не требуется для POST-запроса | G94: 1. Создать POST запрос на эндпоинт /question_application/ 2.Ввести в body { "first_name": "string", "last_name": "string", "middle_name": "string", "phone": "string", "email": "string($email)", "city": "string", "question": "string", "accept_confidential_policy": true } 3. Выбрать формат json 4. Отправить запрос | H94: Возвращается код 201 «Created» { "first_name": "string", "last_name": "string", "middle_name": "string", "phone": "string", "email": "string($email)", "city": "string", "question": "string", "accept_confidential_policy": true } | K94: Passed
A95: question_application | B95: API_qstn_pplctn_2 | C95: Средний | D95: Попытка создания запроса без обязательного поля first_name при создании POST -запроса на эндпоинт /question_application/ | E95: Проверка обработки отсутствия обязательного поля first_name | F95: 1.Открыто приложение Postman 2.Ввести адрес тестового стенда: pl.rassokha.pro:8000/api/v1 3.API доступен и авторизация не требуется для POST-запроса | G95: 1. Создать POST запрос на эндпоинт /question_application/ 2.Ввести в body { "last_name": "string", "middle_name": "string", "phone": "string", "email": "string($email)", "city": "string", "question": "string", "accept_confidential_policy": true } 3. Выбрать формат json 4. Отправить запрос | H95: 400 Bad Request { "first_name": [ "Обязательное поле." ] } | K95: Passed
A96: question_application | B96: API_qstn_pplctn_3 | C96: Средний | D96: Попытка создания запроса без обязательного поля last_name при создании POST -запроса на эндпоинт /question_application/ | E96: Проверка обработки отсутствия обязательного поля last_name | F96: 1.Открыто приложение Postman 2.Ввести адрес тестового стенда: pl.rassokha.pro:8000/api/v1 3.API доступен и авторизация не требуется для POST-запроса | G96: 1. Создать POST запрос на эндпоинт /question_application/ 2.Ввести в body { "first_name": "string", "middle_name": "string", "phone": "string", "email": "string($email)", "city": "string", "question": "string", "accept_confidential_policy": true } 3. Выбрать формат json 4. Отправить запрос | H96: 400 Bad Request { "last_name": [ "Обязательное поле." ] } | K96: Passed
A97: question_application | B97: API_qstn_pplctn_4 | C97: Средний | D97: Попытка создания запроса без обязательного поля middle_name при создании POST -запроса на эндпоинт /question_application/ | E97: Проверка обработки отсутствия обязательного поля middle_name | F97: 1.Открыто приложение Postman 2.Ввести адрес тестового стенда: pl.rassokha.pro:8000/api/v1 3.API доступен и авторизация не требуется для POST-запроса | G97: 1. Создать POST запрос на эндпоинт /question_application/ 2.Ввести в body { "first_name": "string", "last_name": "string", "phone": "string", "email": "string($email)", "city": "string", "question": "string", "accept_confidential_policy": true } 3. Выбрать формат json 4. Отправить запрос | H97: 400 Bad Request { "middle_name": [ "Обязательное поле." ] } | K97: Passed
A98: question_application | B98: API_qstn_pplctn_5 | C98: Средний | D98: Попытка создания запроса без обязательного поля phone при создании POST -запроса на эндпоинт /question_application/ | E98: Проверка обработки отсутствия обязательного поля phone | F98: 1.Открыто приложение Postman 2.Ввести адрес тестового стенда: pl.rassokha.pro:8000/api/v1 3.API доступен и авторизация не требуется для POST-запроса | G98: 1. Создать POST запрос на эндпоинт /question_application/ 2.Ввести в body { "first_name": "string", "last_name": "string", "middle_name": "string", "email": "string($email)", "city": "string", "question": "string", "accept_confidential_policy": true } 3. Выбрать формат json 4. Отправить запрос | H98: 400 Bad Request { "phone": [ "Обязательное поле." ] } | K98: Passed
A99: question_application | B99: API_qstn_pplctn_6 | C99: Средний | D99: Попытка создания запроса без обязательного поля email при создании POST -запроса на эндпоинт /question_application/ | E99: Проверка обработки отсутствия обязательного поля email | F99: 1.Открыто приложение Postman 2.Ввести адрес тестового стенда: pl.rassokha.pro:8000/api/v1 3.API доступен и авторизация не требуется для POST-запроса | G99: 1. Создать POST запрос на эндпоинт /question_application/ 2.Ввести в body { "first_name": "string", "last_name": "string", "middle_name": "string", "phone": "string", "city": "string", "question": "string", "accept_confidential_policy": true } 3. Выбрать формат json 4. Отправить запрос | H99: 400 Bad Request { "email": [ "Обязательное поле." ] } | K99: Passed
... A102: question_application | B102: API_qstn_pplctn_9 | C102: Средний | D102: Попытка создания запроса без accept_confidential_policy при создании POST -запроса на эндпоинт /question_application/ | E102: Проверка обработки отсутствия обязательного поля accept_confidential_policy | F102: 1.Открыто приложение Postman 2.Ввести адрес тестового стенда: pl.rassokha.pro:8000/api/v1 3.API доступен и авторизация не требуется для POST-запроса | G102: 1. Создать POST запрос на эндпоинт /question_application/ 2.Ввести в body { "first_name": "string", "last_name": "string", "middle_name": "string", "phone": "string", "email": "string($email)", "city": "string", "question": "string" } 3. Выбрать формат json 4. Отправить запрос | H102: 400 Bad Request { "accept_confidential_policy": [ "Обязательное поле." ] } | K102: Passed
A103: question_application | B103: API_qstn_pplctn_10 | C103: Средний | D103: Попытка отправки запроса с пустой строкой в поле first_name при создании POST -запроса на эндпоинт /question_application/ | F103: 1.Открыто приложение Postman 2.Ввести адрес тестового стенда: pl.rassokha.pro:8000/api/v1 3.API доступен и авторизация не требуется для POST-запроса | G103: 1. Создать POST запрос на эндпоинт /question_application/ 2.Ввести в body { "first_name": "", "last_name": "string", "middle_name": "string", "phone": "string", "email": "string($email)", "city": "string", "question": "string", "accept_confidential_policy": true } 3. Выбрать формат json 4. Отправить запрос | H103: 400 Bad Request { "first_name": [ "Это поле не может быть пустым." ] } | K103: Passed
A104: question_application | B104: API_qstn_pplctn_11 | C104: Средний | D104: Попытка отправки запроса с пустой строкой в поле last_name при создании POST -запроса на эндпоинт /question_application/ | F104: 1.Открыто приложение Postman 2.Ввести адрес тестового стенда: pl.rassokha.pro:8000/api/v1 3.API доступен и авторизация не требуется для POST-запроса | G104: 1. Создать POST запрос на эндпоинт /question_application/ 2.Ввести в body { "first_name": "string", "last_name": "", "middle_name": "string", "phone": "string", "email": "string($email)", "city": "string", "question": "string", "accept_confidential_policy": true } 3. Выбрать формат json 4. Отправить запрос | H104: 400 Bad Request { "last_name": [ "Это поле не может быть пустым." ] } | K104: Passed
A105: question_application | B105: API_qstn_pplctn_12 | C105: Средний | D105: Попытка отправки запроса с пустой строкой в поле middle_name при создании POST -запроса на эндпоинт /question_application/ | F105: 1.Открыто приложение Postman 2.Ввести адрес тестового стенда: pl.rassokha.pro:8000/api/v1 3.API доступен и авторизация не требуется для POST-запроса | G105: 1. Создать POST запрос на эндпоинт /question_application/ 2.Ввести в body { "first_name": "string", "last_name": "string", "middle_name": "", "phone": "string", "email": "string($email)", "city": "string", "question": "string", "accept_confidential_policy": true } 3. Выбрать формат json 4. Отправить запрос | H105: 400 Bad Request { "middle_name": [ "Это поле не может быть пустым." ] } | K105: Passed
A106: question_application | B106: API_qstn_pplctn_13 | C106: Средний | D106: Попытка отправки запроса с пустой строкой в поле phone при создании POST -запроса на эндпоинт /question_application/ | F106: 1.Открыто приложение Postman 2.Ввести адрес тестового стенда: pl.rassokha.pro:8000/api/v1 3.API доступен и авторизация не требуется для POST-запроса | G106: 1. Создать POST запрос на эндпоинт /question_application/ 2.Ввести в body { "first_name": "string", "last_name": "string", "middle_name": "string", "phone": "", "email": "string($email)", "city": "string", "question": "string", "accept_confidential_policy": true } 3. Выбрать формат json 4. Отправить запрос | H106: 400 Bad Request { "phone": [ "Это поле не может быть пустым." ] } | K106: Passed
A107: question_application | B107: API_qstn_pplctn_14 | C107: Средний | D107: Попытка отправки запроса с пустой строкой в поле email при создании POST -запроса на эндпоинт /question_application/ | F107: 1.Открыто приложение Postman 2.Ввести адрес тестового стенда: pl.rassokha.pro:8000/api/v1 3.API доступен и авторизация не требуется для POST-запроса | G107: 1. Создать POST запрос на эндпоинт /question_application/ 2.Ввести в body { "first_name": "string", "last_name": "string", "middle_name": "string", "phone": "string", "email": "", "city": "string", "question": "string", "accept_confidential_policy": true } 3. Выбрать формат json 4. Отправить запрос | H107: 400 Bad Request { "email": [ "Это поле не может быть пустым." ] } | K107: Passed
A108: question_application | B108: API_qstn_pplctn_15 | C108: Средний | D108: Попытка отправки запроса с пустой строкой в поле city при создании POST -запроса на эндпоинт /question_application/ | F108: 1.Открыто приложение Postman 2.Ввести адрес тестового стенда: pl.rassokha.pro:8000/api/v1 3.API доступен и авторизация не требуется для POST-запроса | G108: 1. Создать POST запрос на эндпоинт /question_application/ 2.Ввести в body { "first_name": "string", "last_name": "string", "middle_name": "string", "phone": "string", "email": "string($email)", "city": "", "question": "string", "accept_confidential_policy": true } 3. Выбрать формат json 4. Отправить запрос | H108: 400 Bad Request { "city": [ "Это поле не может быть пустым." ] } | K108: Passed
A109: question_application | B109: API_qstn_pplctn_16 | C109: Средний | D109: Попытка отправки запроса с пустой строкой в поле question при создании POST -запроса на эндпоинт /question_application/ | F109: 1.Открыто приложение Postman 2.Ввести адрес тестового стенда: pl.rassokha.pro:8000/api/v1 3.API доступен и авторизация не требуется для POST-запроса | G109: 1. Создать POST запрос на эндпоинт /question_application/ 2.Ввести в body { "first_name": "string", "last_name": "string", "middle_name": "string", "phone": "string", "email": "string($email)", "city": "string", "question": "", "accept_confidential_policy": true } 3. Выбрать формат json 4. Отправить запрос | H109: 400 Bad Request { "question": [ "Это поле не может быть пустым." ] } | K109: Passed
A110: question_application | B110: API_qstn_pplctn_17 | C110: Средний | D110: Попытка создания запроса без принятия политики конфиденциальности accept_confidential_policy при создании POST -запроса на эндпоинт /question_application/ | F110: 1.Открыто приложение Postman 2.Ввести адрес тестового стенда: pl.rassokha.pro:8000/api/v1 3.API доступен и авторизация не требуется для POST-запроса | G110: 1. Создать POST запрос на эндпоинт /question_application/ 2.Ввести в body { "first_name": "string", "last_name": "string", "middle_name": "string", "phone": "string", "email": "string($email)", "city": "string", "question": "string", "accept_confidential_policy": false } 3. Выбрать формат json 4. Отправить запрос | H110: 400 Bad Request { "accept_confidential_policy": [ "Вы должны принять политику конфиденциальности." ] } | K110: Passed
A111: question_application | B111: API_qstn_pplctn_18 | C111: Средний | D111: Проверка запроса с неверным HTTP-методом GET при запросе на эндпоинт /question_application/ | F111: 1.Открыто приложение Postman 2.Ввести адрес тестового стенда: pl.rassokha.pro:8000/api/v1 3.API доступен и авторизация не требуется для GET-запроса | G111: 1. Создать POST запрос на эндпоинт /question_application/ 2.Ввести в body { "first_name": "string", "last_name": "string", "middle_name": "string", "phone": "string", "email": "string($email)", "city": "string", "question": "string", "accept_confidential_policy": true } 3. Выбрать формат json 4. Отправить запрос | H111: 405 Method Not Allowed { "detail": "Метод \"GET\" не разрешен." } | K111: Passed
A112: question_application | B112: API_qstn_pplctn_19 | C112: Средний | D112: Проверка запроса с неверным HTTP-методом PUT при запросе на эндпоинт /question_application/ | F112: 1.Открыто приложение Postman 2.Ввести адрес тестового стенда: pl.rassokha.pro:8000/api/v1 3.API доступен и авторизация не требуется для PUT-запроса | G112: 1. Создать POST запрос на эндпоинт /question_application/ 2.Ввести в body { "first_name": "string", "last_name": "string", "middle_name": "string", "phone": "string", "email": "string($email)", "city": "string", "question": "string", "accept_confidential_policy": true } 3. Выбрать формат json 4. Отправить запрос | H112: 405 Method Not Allowed { "detail": "Метод \"PUT\" не разрешен." } | K112: Passed
A113: question_application | B113: API_qstn_pplctn_20 | C113: Средний | D113: Проверка запроса с неверным HTTP-методом PATCH при запросе на эндпоинт /question_application/ | F113: 1.Открыто приложение Postman 2.Ввести адрес тестового стенда: pl.rassokha.pro:8000/api/v1 3.API доступен и авторизация не требуется для PATCH-запроса | G113: 1. Создать POST запрос на эндпоинт /question_application/ 2.Ввести в body { "first_name": "string", "last_name": "string", "middle_name": "string", "phone": "string", "email": "string($email)", "city": "string", "question": "string", "accept_confidential_policy": true } 3. Выбрать формат json 4. Отправить запрос | H113: 405 Method Not Allowed { "detail": "Метод \"PATCH\" не разрешен." } | K113: Passed
A114: question_application | B114: API_qstn_pplctn_21 | C114: Средний | D114: Проверка запроса с неверным HTTP-методом DELETE при запросе на эндпоинт /question_application/ | F114: 1.Открыто приложение Postman 2.Ввести адрес тестового стенда: pl.rassokha.pro:8000/api/v1 3.API доступен и авторизация не требуется для DELETE-запроса | G114: 1. Создать POST запрос на эндпоинт /question_application/ 2.Ввести в body { "first_name": "string", "last_name": "string", "middle_name": "string", "phone": "string", "email": "string($email)", "city": "string", "question": "string", "accept_confidential_policy": true } 3. Выбрать формат json 4. Отправить запрос | H114: 405 Method Not Allowed { "detail": "Метод \"DELETE\" не разрешен." } | K114: Passed
... A121: question_application | B121: API_qstn_pplctn_28 | C121: Средний | D121: Проверка валидации формата email при вводе эмодзи ❤️ при запросе на эндпоинт /question_application/ | F121: 1.Открыто приложение Postman 2.Ввести адрес тестового стенда: pl.rassokha.pro:8000/api/v1 3.API доступен и авторизация не требуется для POST-запроса | G121: 1. Создать POST запрос на эндпоинт /question_application/ 2.Ввести в body { "first_name": "string", "last_name": "string", "middle_name": "string", "phone": "string", "email": "string($email)", "city": "string", "question": "string", "accept_confidential_policy": true } 3. Выбрать формат json 4. Отправить запрос | H121: 201 Created { "first_name": "string", "last_name": "string", "middle_name": "string", "phone": "string", "email": "string($email)", "city": "string", "question": "string", "accept_confidential_policy": true } | K121: Passed
A122: faq | B122: API_fq_1 | C122: Средний | D122: Успешное получение списка часто задаваемые вопросы | E122: Отправить запрос с методом GET https://pl.rassokha.pro:8000/api/v1/faq/ | F122: 1. Открыто приложение Postman 2. Используется тестовый стенд pl.rassokha.pro:8000/api/v1 3.API доступен и авторизация не требуется для GET-запроса | G122: 1. Создать GET запрос на эндпоинт faq/ 2.Отправить запрос | H122: Возвращается код 200 OK Тело ответа: [ { "id": integer, "slug": "string", "question": "string", "answer": "string" } ] | K122: Passed
A123: faq | B123: API_fq_2 | C123: Средний | D123: Получение списка часто задаваемые вопросы неверным HTTP-методом | E123: Отправить запрос с методом POST https://pl.rassokha.pro:8000/api/v1/faq/ | F123: 1. Открыто приложение Postman 2. Используется тестовый стенд pl.rassokha.pro:8000/api/v1 3.API доступен и авторизация не требуется для POST-запроса | G123: 1. Создать POST запрос на эндпоинт faq/ 2.Отправить запрос | H123: 405 Method Not Allowed { "detail": "Метод \"POST\" не разрешен." } | K123: Passed
A124: faq | B124: API_fq_3 | C124: Средний | D124: Успешное получение существующего часто задаваемого вопроса | E124: Отправить запрос с методом GET https://pl.rassokha.pro:8000/api/v1/faq/{id}/ | F124: 1. Открыто приложение Postman 2. Используется тестовый стенд pl.rassokha.pro:8000/api/v1 3.API доступен и авторизация не требуется для GET-запроса | G124: 1. Создать GET запрос на эндпоинт faq/{id}/ где {id} - существующий часто задаваемый вопрос 2.Отправить запрос | H124: Возвращается код 200 OK Тело ответа: [ { "id": integer, "slug": "string", "question": "string", "answer": "string" } ] | K124: Passed
A125: faq | B125: API_fq_4 | C125: Средний | D125: Получение не существующего часто задаваемого вопроса | E125: Отправить запрос с методом GET https://pl.rassokha.pro:8000/api/v1/faq/{id}/ | F125: 1. Открыто приложение Postman 2. Используется тестовый стенд pl.rassokha.pro:8000/api/v1 3. Убедиться, что часто задаваемого вопроса {id} НЕ существует | G125: 1. Создать GET запрос на эндпоинт faq/{id}/ 2.Отправить запрос | H125: Возвращается код 404 Not Found Тело ответа: { "detail": "No FrequentQuestion matches the given query." } | K125: Passed
A126: faq | B126: API_fq_5 | C126: Средний | D126: Попытка получения часто задаваемого вопроса с нечисловым ID | E126: Отправить запрос с методом GET https://pl.rassokha.pro:8000/api/v1/faq/{id}/ | F126: 1. Открыто приложение Postman 2. Используется тестовый стенд pl.rassokha.pro:8000/api/v1 3.API доступен и авторизация не требуется для GET-запроса | G126: 1. Создать GET запрос на эндпоинт faq/abc/ 2.Отправить запрос | H126: Возвращается код 404 Not Found Тело ответа: { "detail": "Страница не найдена." } | K126: Passed
A127: faq | B127: API_fq_6 | C127: Средний | D127: Попытка получения существующего часто задаваемого вопроса неверным HTTP-методом | E127: Отправить запрос с методом POST https://pl.rassokha.pro:8000/api/v1/faq/{id}/ | F127: 1. Открыто приложение Postman 2. Используется тестовый стенд pl.rassokha.pro:8000/api/v1 3.API доступен и авторизация не требуется для PSOT-запроса | G127: 1. Создать POST запрос на эндпоинт faq/{id}/ 2.Отправить запрос | H127: 405 Method Not Allowed { "detail": "Метод \"POST\" не разрешен." } | K127: Passed
A128: contacts | B128: API_cntcts_1 | C128: Средний | D128: Успешное получение списка контактов | E128: Отправить запрос с методом GET https://pl.rassokha.pro:8000/api/v1/contacts/ | F128: 1. Открыто приложение Postman 2. Используется тестовый стенд pl.rassokha.pro:8000/api/v1 3.API доступен и авторизация не требуется для GET-запроса | G128: 1. Создать GET запрос на эндпоинт contacts/ 2.Отправить запрос | H128: Возвращается код 200 OK Тело ответа: [ { "contact_type": "string", "title": "string", "details": ["value1", "value2"] } ] | K128: Passed
A129: contacts | B129: API_cntcts_2 | C129: Средний | D129: Попытка получение списка контактов неверным HTTP-методом | E129: Отправить запрос с методом POST https://pl.rassokha.pro:8000/api/v1/contacts/ | F129: 1. Открыто приложение Postman 2. Используется тестовый стенд pl.rassokha.pro:8000/api/v1 3.API доступен и авторизация не требуется для PSOT-запроса | G129: 1. Создать POST запрос на эндпоинт contacts/ 2.Отправить запрос | H129: 405 Method Not Allowed { "detail": "Метод \"POST\" не разрешен." } | K129: Passed
A130: contacts | B130: API_cntcts_3 | C130: Средний | D130: Успешное получение существующего типа контакта | E130: Отправить запрос с методом GET https://pl.rassokha.pro:8000/api/v1/contacts/type/{contact_type}/ | F130: 1. Открыто приложение Postman 2. Используется тестовый стенд pl.rassokha.pro:8000/api/v1 3.API доступен и авторизация не требуется для GET-запроса | G130: 1. Создать GET запрос на эндпоинт contacts/type/{contact_type}/ где {contact_type} - существующий тип контакт 2.Отправить запрос | H130: Возвращается код 200 OK Тело ответа: [ { "contact_type": "string", "title": "string", "details": ["value1", "value2"] } ] | K130: Passed
A131: contacts | B131: API_cntcts_4 | C131: Средний | D131: Попытка получение не существующего типа контакта | E131: Отправить запрос с методом GET https://pl.rassokha.pro:8000/api/v1/contacts/type/{contact_type}/ | F131: 1. Открыто приложение Postman 2. Используется тестовый стенд pl.rassokha.pro:8000/api/v1 3.Убедиться, что социальной ссылки {contact_type} НЕ существует | G131: 1. Создать GET запрос на эндпоинт contacts/type/{contact_type}/ 2.Отправить запрос | H131: Возвращается код 404 Not Found Тело ответа: { "detail": "Контакты не найдены." } | K131: Passed
A132: contacts | B132: API_cntcts_5 | C132: Средний | D132: Попытка получения типа контакта c нестрочным contact_type | E132: Отправить запрос с методом GET https://pl.rassokha.pro:8000/api/v1/contacts/type/{contact_type}/ | F132: 1. Открыто приложение Postman 2. Используется тестовый стенд pl.rassokha.pro:8000/api/v1 3.API доступен и авторизация не требуется для GET-запроса | G132: 1. Создать GET запрос на эндпоинт contacts/type/123/ 2.Отправить запрос | H132: Возвращается код 404 Not Found Тело ответа: { "detail": "Контакты не найдены." } | K132: Passed
A133: contacts | B133: API_cntcts_6 | C133: Средний | D133: Попытка получение существующего типа контакта неверным HTTP-методом | E133: Отправить запрос с методом POST https://pl.rassokha.pro:8000/api/v1contacts/type/{contact_type}/ | F133: 1. Открыто приложение Postman 2. Используется тестовый стенд pl.rassokha.pro:8000/api/v1 3.API доступен и авторизация не требуется для PSOT-запроса | G133: 1. Создать POST запрос на эндпоинт contacts/type/{contact_type}/ где {contact_type} - существующий тип контакт 2.Отправить запрос | H133: 405 Method Not Allowed { "detail": "Метод \"POST\" не разрешен." } | K133: Passed
... A152: org_requisites | B152: API_rqsts_8 | C152: Средний | D152: Попытка получения существующих реквизитов неверным HTTP-методом | E152: Отправить запрос с методом POST https://pl.rassokha.pro:8000/api/v1/org_requisites/{id}/ | F152: 1. Открыто приложение Postman 2. Используется тестовый стенд pl.rassokha.pro:8000/api/v1 3.API доступен и авторизация не требуется для POST-запроса | G152: 1. Создать POST запрос на эндпоинт org_requisites/{id}/ Где {id} - существующие реквезиты 2.Отправить запрос | H152: 405 Method Not Allowed { "detail": "Метод \"POST\" не разрешен." } | K152: Passed
A153: donation | B153: API_dntn_1 | C153: Высокий | D153: Попытка отправки валидного запроса о создании нового платежа | F153: 1. Открыто приложение Postman 2. Используется тестовый стенд pl.rassokha.pro:8000/api/v1 | G153: 1. Создать POST запрос на эндпоинт /donation/ 2. В тело запроса вставить: { "id": "string", "created_at": "string", "amount": { "additionalProp1": "string", "additionalProp2": "string", "additionalProp3": "string" }, "metadata": { "additionalProp1": "string", "additionalProp2": "string", "additionalProp3": "string" }, "status": "pending", "description": "string", "value": "string($decimal)", "family_request": [ 0 ], "first_name": "string", "payment_method": "string" } 3.Отправить запрос | H153: Возвращается код 200 Created Возвращаются заголовки: { "Vary": "Accept, Cookie", "Allow": "POST, OPTIONS", "X-Frame-Options": "SAMEORIGIN", "Content-Length": "0", "X-Content-Type-Options": "nosniff", "Referrer-Policy": "same-origin", "Cross-Origin-Opener-Policy": "same-origin" } | K153: Failed
A154: donation | B154: API_dntn_2 | C154: Средний | D154: Попытка передачи integer вместо string в поле "id" | F154: 1. Открыто приложение Postman 2. Используется тестовый стенд pl.rassokha.pro:8000/api/v1 | G154: 1. Создать POST запрос на эндпоинт /donation/ 2. В тело запроса вставить: { "id": 1, "created_at": "string", "amount": { "additionalProp1": "string", "additionalProp2": "string", "additionalProp3": "string" }, "metadata": { "additionalProp1": "string", "additionalProp2": "string", "additionalProp3": "string" }, "status": "pending", "description": "string", "value": "string($decimal)", "family_request": [ 0 ], "first_name": "string", "payment_method": "string" } 3.Отправить запрос | H154: Возвращается код 400 Bad Request | K154: Blocked
A155: donation | B155: API_dntn_3 | C155: Средний | D155: Попытка передачи пустой строки в поле "id" | F155: 1. Открыто приложение Postman 2. Используется тестовый стенд pl.rassokha.pro:8000/api/v1 | G155: 1. Создать POST запрос на эндпоинт /donation/ 2. В тело запроса вставить: { "id": "", "created_at": "string", "amount": { "additionalProp1": "string", "additionalProp2": "string", "additionalProp3": "string" }, "metadata": { "additionalProp1": "string", "additionalProp2": "string", "additionalProp3": "string" }, "status": "pending", "description": "string", "value": "string($decimal)", "family_request": [ 0 ], "first_name": "string", "payment_method": "string" } 3.Отправить запрос | H155: Возвращается код 400 Bad Request | K155: Blocked
A156: donation | B156: API_dntn_4 | C156: Средний | D156: Попытка передачи integer вместо string в поле "created_at" | F156: 1. Открыто приложение Postman 2. Используется тестовый стенд pl.rassokha.pro:8000/api/v1 | G156: 1. Создать POST запрос на эндпоинт /donation/ 2. В тело запроса вставить: { "id": "string", "created_at": 1, "amount": { "additionalProp1": "string", "additionalProp2": "string", "additionalProp3": "string" }, "metadata": { "additionalProp1": "string", "additionalProp2": "string", "additionalProp3": "string" }, "status": "pending", "description": "string", "value": "string($decimal)", "family_request": [ 0 ], "first_name": "string", "payment_method": "string" } 3.Отправить запрос | H156: Возвращается код 400 Bad Request | K156: Blocked
A157: donation | B157: API_dntn_5 | C157: Средний | D157: Попытка передачи пустой строки в поле "created_at" | F157: 1. Открыто приложение Postman 2. Используется тестовый стенд pl.rassokha.pro:8000/api/v1 | G157: 1. Создать POST запрос на эндпоинт /donation/ 2. В тело запроса вставить: { "id": "string", "created_at": "", "amount": { "additionalProp1": "string", "additionalProp2": "string", "additionalProp3": "string" }, "metadata": { "additionalProp1": "string", "additionalProp2": "string", "additionalProp3": "string" }, "status": "pending", "description": "string", "value": "string($decimal)", "family_request": [ 0 ], "first_name": "string", "payment_method": "string" } 3.Отправить запрос | H157: Возвращается код 400 Bad Request | K157: Blocked
A158: donation | B158: API_dntn_6 | C158: Средний | D158: Попытка передачи integer вместо string в поле "status" | F158: 1. Открыто приложение Postman 2. Используется тестовый стенд pl.rassokha.pro:8000/api/v1 | G158: 1. Создать POST запрос на эндпоинт /donation/ 2. В тело запроса вставить: { "id": "string", "created_at": "", "amount": { "additionalProp1": "string", "additionalProp2": "string", "additionalProp3": "string" }, "metadata": { "additionalProp1": "string", "additionalProp2": "string", "additionalProp3": "string" }, "status": 1, "description": "string", "value": "string($decimal)", "family_request": [ 0 ], "first_name": "string", "payment_method": "string" } 3.Отправить запрос | H158: Возвращается код 400 Bad Request | K158: Blocked
A159: donation | B159: API_dntn_7 | C159: Средний | D159: Попытка передачи пустой строки в поле "status" | F159: 1. Открыто приложение Postman 2. Используется тестовый стенд pl.rassokha.pro:8000/api/v1 | G159: 1. Создать POST запрос на эндпоинт /donation/ 2. В тело запроса вставить: { "id": "string", "created_at": "", "amount": { "additionalProp1": "string", "additionalProp2": "string", "additionalProp3": "string" }, "metadata": { "additionalProp1": "string", "additionalProp2": "string", "additionalProp3": "string" }, "status": "", "description": "string", "value": "string($decimal)", "family_request": [ 0 ], "first_name": "string", "payment_method": "string" } 3.Отправить запрос | H159: Возвращается код 400 Bad Request | K159: Blocked
A160: donation | B160: API_dntn_8 | C160: Средний | D160: Попытка передачи integer вместо string в поле "description" | F160: 1. Открыто приложение Postman 2. Используется тестовый стенд pl.rassokha.pro:8000/api/v1 | G160: 1. Создать POST запрос на эндпоинт /donation/ 2. В тело запроса вставить: { "id": "string", "created_at": "string", "amount": { "additionalProp1": "string", "additionalProp2": "string", "additionalProp3": "string" }, "metadata": { "additionalProp1": "string", "additionalProp2": "string", "additionalProp3": "string" }, "status": "pending", "description": 1, "value": "string($decimal)", "family_request": [ 0 ], "first_name": "string", "payment_method": "string" } 3.Отправить запрос | H160: Возвращается код 400 Bad Request | K160: Blocked
A161: donation | B161: API_dntn_9 | C161: Средний | D161: Попытка передачи пустой строки в поле "description" | F161: 1. Открыто приложение Postman 2. Используется тестовый стенд pl.rassokha.pro:8000/api/v1 | G161: 1. Создать POST запрос на эндпоинт /donation/ 2. В тело запроса вставить: { "id": "string", "created_at": "string", "amount": { "additionalProp1": "string", "additionalProp2": "string", "additionalProp3": "string" }, "metadata": { "additionalProp1": "string", "additionalProp2": "string", "additionalProp3": "string" }, "status": "pending", "description": "", "value": "string($decimal)", "family_request": [ 0 ], "first_name": "string", "payment_method": "string" } 3.Отправить запрос | H161: Возвращается код 400 Bad Request | K161: Blocked
A162: donation | B162: API_dntn_10 | C162: Средний | D162: Попытка передачи integer вместо string в поле "value" | F162: 1. Открыто приложение Postman 2. Используется тестовый стенд pl.rassokha.pro:8000/api/v1 | G162: 1. Создать POST запрос на эндпоинт /donation/ 2. В тело запроса вставить: { "id": "string", "created_at": "string", "amount": { "additionalProp1": "string", "additionalProp2": "string", "additionalProp3": "string" }, "metadata": { "additionalProp1": "string", "additionalProp2": "string", "additionalProp3": "string" }, "status": "pending", "description": "string", "value": 1, "family_request": [ 0 ], "first_name": "string", "payment_method": "string" } 3.Отправить запрос | H162: Возвращается код 400 Bad Request | K162: Blocked
A163: donation | B163: API_dntn_11 | C163: Средний | D163: Попытка передачи пустой строки в поле "value" | F163: 1. Открыто приложение Postman 2. Используется тестовый стенд pl.rassokha.pro:8000/api/v1 | G163: 1. Создать POST запрос на эндпоинт /donation/ 2. В тело запроса вставить: { "id": "string", "created_at": "string", "amount": { "additionalProp1": "string", "additionalProp2": "string", "additionalProp3": "string" }, "metadata": { "additionalProp1": "string", "additionalProp2": "string", "additionalProp3": "string" }, "status": "pending", "description": "string", "value": "", "family_request": [ 0 ], "first_name": "string", "payment_method": "string" } 3.Отправить запрос | H163: Возвращается код 400 Bad Request | K163: Blocked
A164: donation | B164: API_dntn_12 | C164: Средний | D164: Проверка идемпотентности запроса с одним и тем же ID в теле | E164: Проверить поведение системы если отправить несколько запросов с одинаковым ID платежа | F164: 1. Открыто приложение Postman 2. Используется тестовый стенд pl.rassokha.pro:8000/api/v1 | G164: 1. Создать POST запрос на эндпоинт /donation/ 2. В тело запроса вставить: { "id": {id сущ. платежа}, "created_at": "string", "amount": { "additionalProp1": "string", "additionalProp2": "string", "additionalProp3": "string" }, "metadata": { "additionalProp1": "string", "additionalProp2": "string", "additionalProp3": "string" }, "status": "pending", "description": "string", "value": "string($decimal)", "family_request": [ 0 ], "first_name": "string", "payment_method": "string" } , где {id сущ. платежа} - идентификатор существующего платежа 3.Отправить запрос | H164: См. комментарий | K164: Blocked
A165: donation_list | B165: API_dontn_lst_1 | C165: Высокий | D165: Успешное получение списка донатов | F165: 1. Открыто приложение Postman 2. Используется тестовый стенд pl.rassokha.pro:8000/api/v1 | G165: 1. Отправить GET запрос на эндпоинт /donation_list/ | H165: Возвращается код 200 OK Тело ответа: [ { "payment_method": "string", "first_name": "string", "value": "string" }, { "payment_method": "string", "first_name": "string", "value": "string" } ] | K165: Passed
A166: donation_list | B166: API_dontn_lst_2 | C166: Высокий | D166: Попытка получения списка донатов неверным HTTP-методом | F166: 1. Открыто приложение Postman 2. Используется тестовый стенд pl.rassokha.pro:8000/api/v1 | G166: 1. Отправить POST запрос на эндпоинт /donation_list/ | H166: 405 Method Not Allowed { "detail": "Метод \"POST\" не разрешен." } | K166: Passed
A167: about_image | B167: API_bt_img_1 | C167: Высокий | D167: Отправка валидного запроса получения списка изображений | F167: 1. Открыто приложение Postman 2. Используется тестовый стенд pl.rassokha.pro:8000/api/v1 | G167: 1. Отправить GET запрос на эндпоинт /about_image/ | H167: Возвращается код 200 OK Тело ответа: [ { "id": integer, "image": "string($url)", "title": "string" } ] | K167: Passed
A168: about_image | B168: API_bt_img_2 | C168: Высокий | D168: Отправка валидного запроса получения конкретного изображения | F168: 1. Открыто приложение Postman 2. Используется тестовый стенд pl.rassokha.pro:8000/api/v1 | G168: 1. Отправить GET запрос на эндпоинт /about_image/{id}/, где {id} - идентификатор существующего изображения | H168: Возвращается код 200 OK Тело ответа: { "id": integer, "image": "string($url)", "title": "string" } | K168: Passed
A169: support_us_gallery | B169: API_spprt_gllrl_1 | C169: Средний | D169: Успешное получение списка 'Нас поддерживают' | E169: Отправить запрос с методом GET https://pl.rassokha.pro:8000/api/v1/support_us_gallery/ | F169: 1. Открыто приложение Postman 2. Используется тестовый стенд pl.rassokha.pro:8000/api/v1 3.API доступен и авторизация не требуется для GET-запроса | G169: 1. Создать GET запрос на эндпоинт support_us_gallery/ 2.Отправить запрос | H169: Возвращается код 200 OK Тело ответа: [ { "id": integer, "title": "string", "images": [ { "id": integer, "image_file": "string($url)", "link": "string($url)", "title": "string" } ] } ] | K169: Passed
A170: support_us_gallery | B170: API_spprt_gllrl_2 | C170: Средний | D170: Попытка получения списка 'Нас поддерживают' неверным HTTP-методом | E170: Отправить запрос с методом POST https://pl.rassokha.pro:8000/api/v1/support_us_gallery/ | F170: 1. Открыто приложение Postman 2. Используется тестовый стенд pl.rassokha.pro:8000/api/v1 3.API доступен и авторизация не требуется для POST-запроса | G170: 1. Создать POST запрос на эндпоинт support_us_gallery/ 2.Отправить запрос | H170: 405 Method Not Allowed { "detail": "Метод \"POST\" не разрешен." } | K170: Passed
A171: support_us_gallery | B171: API_spprt_gllrl_3 | C171: Средний | D171: Успешное получение существующего списка 'Нас поддерживают' | E171: Отправить запрос с методом GET https://pl.rassokha.pro:8000/api/v1/support_us_gallery/{id}/ | F171: 1. Открыто приложение Postman 2. Используется тестовый стенд pl.rassokha.pro:8000/api/v1 3.API доступен и авторизация не требуется для GET-запроса | G171: 1. Создать GET запрос на эндпоинт support_us_gallery/{id}/ где {id} - существующий список поддерживающих 2.Отправить запрос | H171: Возвращается код 200 OK Тело ответа: { "id": integer, "title": "string", "images": [ { "id": integer, "image_file": "string($url)", "link": "string($url)", "title": "string" } ] } | K171: Passed
A172: support_us_gallery | B172: API_spprt_gllrl_4 | C172: Средний | D172: Попытка получения не существующего списка 'Нас поддерживают' | E172: Отправить запрос с методом GET https://pl.rassokha.pro:8000/api/v1/support_us_gallery/{id}/ | F172: 1. Открыто приложение Postman 2. Используется тестовый стенд pl.rassokha.pro:8000/api/v1 3.API доступен и авторизация не требуется для GET-запроса 4. Убедиться, что списока поддерживающих {id} НЕ существует | G172: 1. Создать GET запрос на эндпоинт support_us_gallery/{id}/ 2.Отправить запрос | H172: Возвращается код 404 Not Found { "detail": "No Gallery matches the given query." } | K172: Passed
A173: support_us_gallery | B173: API_spprt_gllrl_5 | C173: Средний | D173: Попытка получения списка 'Нас поддерживают' с не числовым id | E173: Отправить запрос с методом GET https://pl.rassokha.pro:8000/api/v1/support_us_gallery/{id}/ | F173: 1. Открыто приложение Postman 2. Используется тестовый стенд pl.rassokha.pro:8000/api/v1 3.API доступен и авторизация не требуется для GET-запроса | G173: 1. Создать GET запрос на эндпоинт support_us_gallery/abc/ 2.Отправить запрос | H173: Возвращается код 404 Not Found Тело ответа: { "detail": "Страница не найдена." } | K173: Passed
A174: support_us_gallery | B174: API_spprt_gllrl_6 | C174: Средний | D174: Попытка получения существующего списка 'Нас поддерживают' неверным HTTP-методом | E174: Отправить запрос с методом POST https://pl.rassokha.pro:8000/api/v1/support_us_gallery/{id}/ | F174: 1. Открыто приложение Postman 2. Используется тестовый стенд pl.rassokha.pro:8000/api/v1 3.API доступен и авторизация не требуется для GET-запроса | G174: 1. Создать GET запрос на эндпоинт support_us_gallery/{id}/ где {id} - существующий список поддерживающих 2.Отправить запрос | H174: 405 Method Not Allowed { "detail": "Метод \"POST\" не разрешен." } | K174: Passed
A175: support_us_gallery | B175: API_spprt_gllrl_7 | C175: Средний | D175: Корректная работа пагинации - уменьшение лимита при запросе на эндпоинт support_us_gallery/{id}/images/ | E175: Проверить, что параметр limit корректно уменьшает количество картинок | F175: 1. Открыто приложение Postman 2. Используется тестовый стенд pl.rassokha.pro:8000/api/v1 3.API доступен и авторизация не требуется для GET-запроса | G175: 1. Создать GET запрос на эндпоинт support_us_gallery/{id}/images/ 2. Во вкладке params вставить key: limit 3. Во вкладке params вставить value: integer, где число на 1 меньше чем существующее количество картинок 4. Отправить запрос | H175: Возвращается код 200 OK Тело ответа: { "count": integer, "next": "string($url)", "previous": string($url), "results": [ { "id": integer, "image_file": "string($url)", "link": "string($url)", "title": "string" } ] } | K175: Passed
A176: support_us_gallery | B176: API_spprt_gllrl_8 | C176: Средний | D176: Корректная работа пагинации - cмещение при запросе на эндпоинт support_us_gallery/{id}/images/ | E176: Проверить, что параметр offset корректно пропускает количество картинок | F176: 1. Открыто приложение Postman 2. Используется тестовый стенд pl.rassokha.pro:8000/api/v1 3.API доступен и авторизация не требуется для GET-запроса | G176: 1. Создать GET запрос на эндпоинт support_us_gallery/{id}/images/ 2. Во вкладке params вставить key: offset 3. Во вкладке params вставить value: integer, где число уменьшает (пропускает) существующее количество картинок 4. Отправить запрос | H176: Возвращается код 200 OK Тело ответа: { "count": integer, "next": "string($url)", "previous": string($url), "results": [ { "id": integer, "image_file": "string($url)", "link": "string($url)", "title": "string" } ] } | K176: Passed
A177: support_us_gallery | B177: API_spprt_gllrl_9 | C177: Средний | D177: Проверка работы пагинации при запросе support_us_gallery/{id}/images/ неверным HTTP-методом | E177: Отправить запрос с методом POST https://pl.rassokha.pro:8000/api/v1/support_us_gallery/{id}/images/ | F177: 1. Открыто приложение Postman 2. Используется тестовый стенд pl.rassokha.pro:8000/api/v1 3.API доступен и авторизация не требуется для POST-запроса | G177: 1. Создать POST запрос на эндпоинт support_us_gallery/{id}/images/ 2. Во вкладке params вставить key: offset 3. Во вкладке params вставить value: integer, где число уменьшает (пропускает) существующее количество картинок 4. Отправить запрос | H177: 405 Method Not Allowed { "detail": "Метод \"POST\" не разрешен." } | K177: Passed
A178: photoreport | B178: API_phtrprt_1 | C178: Средний | D178: Успешное получение завершенных сборов | E178: Отправить запрос с методом GET https://pl.rassokha.pro:8000/api/v1/photoreport/ | F178: 1. Открыто приложение Postman 2. Используется тестовый стенд pl.rassokha.pro:8000/api/v1 3.API доступен и авторизация не требуется для GET-запроса | G178: 1. Создать GET запрос на эндпоинт photoreport/ 2.Отправить запрос | H178: Возвращается код 200 OK Тело ответа: [ { "images": "string", "text": "string" } ] | K178: Passed
...

Sheet Баг-репорты swagger
A1: ID | B1: Severity | C1: Priority | D1: Название бага | E1: Описание | F1: Предусловия | G1: Шаги воспроизведения | H1: ОР | I1: ФР | J1: Скринкаст/скриншот | K1: Окружение | L1: Комментарий | M1: Автор
A2: whm_w_hlpd_bg_swg_1 | B2: Стандартный | C2: Высокий | D2: Ошибка при буквенном значении page при запросе на эндпоинт whom_we_helped/ | E2: Отправить запрос с параметром page, имеющим буквенное значение (например, page=abc). | F2: 1.Открыто приложение Postman 2.Ввести адрес тестового стенда: pl.rassokha.pro:8000/api/v1 3.API доступен и авторизация не требуется для GET-запроса | G2: 1. Создать GET запрос на эндпоинт whom_we_helped/ 2. Во вкладке params вставить key: page 3. Во вкладке params вставить value: abc 2.Отправить запрос | H2: 404 Not Found Body ответа: { "detail": "Неправильная страница" } | I2: 404 Not Found Body ответа: { "detail": "Неправильная страница" } | K2: Postman | L2: Баг в документации swagger | M2: Ибрагимова Юлия
A3: whm_w_hlpd_bg_swg_2 | B3: Стандартный | C3: Высокий | D3: Ошибка при спецсимволах в параметре page при запросе на эндпоинт whom_we_helped/ | E3: Отправить запрос с page=+2 | F3: 1.Открыто приложение Postman 2.Ввести адрес тестового стенда: pl.rassokha.pro:8000/api/v1 3.API доступен и авторизация не требуется для GET-запроса | G3: 1. Создать GET запрос на эндпоинт whom_we_helped/ 2. Во вкладке params вставить key: page 3. Во вкладке params вставить value: +2 2.Отправить запрос | H3: 404 Not Found Body ответа: { "detail": "Неправильная страница" } | I3: 404 Not Found Body ответа: { "detail": "Неправильная страница" } | K3: Postman | L3: Баг в документации swagger | M3: Ибрагимова Юлия
A4: whm_w_hlpd_bg_3 | B4: Стандартный | C4: Высокий | D4: Не описан метод OPTIONS при запросе на эндпоинт whom_we_helped/ | E4: Отправить запрос с методом OPTIONS https://pl.rassokha.pro:8000/api/v1/whom_we_helped/ | F4: 1.Открыто приложение Postman 2.Ввести адрес тестового стенда: pl.rassokha.pro:8000/api/v1 3.API доступен и авторизация не требуется для GET-запроса | G4: 1. Создать OPTIONS запрос на эндпоинт whom_we_helped/ 2. Отправить запрос | H4: 405 Method Not Allowed { "detail": "Метод \"OPTIONS\" не разрешен." } | I4: 405 Method Not Allowed { "detail": "Метод \"OPTIONS\" не разрешен." } | K4: Postman | L4: Серая зона, ошибка не описана в документации API | M4: Ибрагимова Юлия
A5: whm_w_hlpd_bg_4 | B5: Высокий | C5: Высокий | D5: Не прописаны в документации API обязательные поля в ответе при запросе на эндпоинт whom_we_helped/ | E5: Проверить, что в ответе присутствуют посты, у которых заполнены все обязательные и необязательные поля (например, id, image_url, title, description,minLength), и их значения соответствуют ожидаемым типам данных | F5: 1.Открыто приложение Postman 2.Ввести адрес тестового стенда: pl.rassokha.pro:8000/api/v1 3.API доступен и авторизация не требуется для GET-запроса | G5: 1. Создать GET запрос на эндпоинт whom_we_helped/ 2. Отправить запрос | H5: Ошибки в структуре ответа нет "Ответ приходит без ошибок 200 ок | I5: Ошибки в структуре ответа нет "Ответ приходит без ошибок 200 ок | K5: Postman | L5: Серая зона, обязательные поля не описаны в документации API | M5: Ибрагимова Юлия
A6: whm_w_hlpd_bg_5 | B6: Высокий | C6: Высокий | D6: Ошибка при обработке записей без изображений при запросе на эндпоинт whom_we_helped/ | E6: Проверить, как система обрабатывает пост, у которого есть текстовое описание, но отсутствует фотография | F6: 1.Открыто приложение Postman 2.Ввести адрес тестового стенда: pl.rassokha.pro:8000/api/v1 3.API доступен и авторизация не требуется для GET-запроса | G6: 1. Создать GET запрос на эндпоинт whom_we_helped/ 2. Отправить запрос | H6: Ошибки в структуре ответа нет "Ответ приходит без ошибок 200 ок | I6: Ответ приходит без ошибок 200 ок | K6: Postman | L6: Серая зона в документации API. На странице "получить помощь" https://pl.rassokha.pro:3001/get-help фотография не является обязательным требованием, поэтому возможность запросить помощь без фотографии должна быть возможной, однако в документации этот момент не прописан | M6: Ибрагимова Юлия
A7: whm_w_hlpd_bg_6 | B7: Высокий | C7: Высокий | D7: Проблемы с кодировкой Unicode символов при запросе на эндпоинт whom_we_helped/ | E7: Проверить, что отчеты, содержащие в описании символы иностранных языков (например, English, 中文), корректно отображаются в ответе API без искажений (проблем с кодировкой). | F7: 1.Открыто приложение Postman 2.Ввести адрес тестового стенда: pl.rassokha.pro:8000/api/v1 3.API доступен и авторизация не требуется для GET-запроса | G7: 1. Создать GET запрос на эндпоинт whom_we_helped/ 2.Отправить запрос | H7: Ошибки в структуре ответа нет "Ответ приходит без ошибок 200 ок | I7: Ошибки в структуре ответа нет "Ответ приходит без ошибок 200 ок | K7: Postman | L7: Серая зона, обязательные поля не описаны в документации API и в документации swagger | M7: Ибрагимова Юлия
A8: whm_w_hlpd_bg_7 | B8: Стандартный | C8: Высокий | D8: Нарушена структура данных элементов results при запросе на эндпоинт whom_we_helped/ | E8: Проверить, что каждый элемент в массиве содержит ожидаемый набор полей | F8: 1.Открыто приложение Postman 2.Ввести адрес тестового стенда: pl.rassokha.pro:8000/api/v1 3.API доступен и авторизация не требуется для GET-запроса | G8: 1. Создать GET запрос на эндпоинт whom_we_helped/ 2.Отправить запрос | H8: Ошибки в структуре ответа нет Ответ приходит без ошибок 200 ок | I8: Ответ приходит без ошибок 200 ок | K8: Postman | L8: Серая зона, обязательные поля не описаны в документации API | M8: Ибрагимова Юлия
A9: whm_w_hlpd_bg_8 | B9: Блокирующий | C9: Высокий | D9: Несоответствие результатов для page=1 и запроса без page при запросе на эндпоинт whom_we_helped/ | E9: Убедиться, что запросы /api/v1/whom_we_helped/ и /api/v1/whom_we_helped/?page=1 возвращают идентичный результат | F9: "1.Открыто приложение Postman 2.Ввести адрес тестового стенда: pl.rassokha.pro:8000/api/v1 3.API доступен и авторизация не требуется для GET-запроса" | G9: 1. Отправить GET /api/v1/whom_we_helped/ 2. Отправить GET /api/v1/whom_we_helped/?page=1 3. Сравнить ответы | H9: Ошибки в структуре ответа нет "Ответ приходит без ошибок 200 ок | I9: Ответ приходит без ошибок 200 ок { "current_page": 1, "total_objects": 0, "next_page": null, "previous_page": null, "result": [] } | K9: Postman | L9: Невозможно проверить,поскольку в тестовой документации ничего об этом не сказано. Неизвестна идея разработчика, первая страница = 0 или 1 | M9: Ибрагимова Юлия
K10: Postman | L10: Description не передает запрос | M10: Ибрагимова Юлия
A11: whm_w_hlpd_bg_10 | B11: Высокий | C11: Высокий | D11: Ошибка 404 при несуществующих параметрах при запросе на эндпоинт whom_we_helped/ | E11: Отправить запрос с параметром, который не описан в API (например, ?unsupported_param=value) | F11: 1.Открыто приложение Postman 2.Ввести адрес тестового стенда: pl.rassokha.pro:8000/api/v1 3.API доступен и авторизация не требуется для GET-запроса | G11: 1. Создать GET запрос на эндпоинт whom_we_helped/ 2. Во вкладке params вставить key: page 3. Во вкладке params вставить value: ?unsupported_param 2.Отправить запрос | H11: 404 Not Found Body ответа: { "detail": "Неправильная страница" } | I11: 404 Not Found Body ответа: { "detail": "Неправильная страница" } | K11: Postman | L11: Серая зона нет описаня в документации API | M11: Ибрагимова Юлия
A12: API_qstn_pplctn_bg_1 | B12: Стандартный | C12: Низкий | D12: Отрицательный ответ 405 Method Not Allowed не прописан в в документации swagger при попытке проверки запроса с неверным HTTP-методом GET при запросе на эндпоинт /question_application/ | F12: 1.Открыто приложение Postman 2.Ввести адрес тестового стенда: pl.rassokha.pro:8000/api/v1 3.API доступен и авторизация не требуется для GET-запроса | G12: 1. Создать GET-запрос с на эндпоинт /question_application/ 2.Ввести в body { "first_name": "Маша", "last_name": "Машковна", "middle_name": "Михайловна", "phone": "+79165678098", "email": "user@yandex.com", "city": "Москва", "question": "Как долго отправляются товары?", "accept_confidential_policy": true } 3. Выбрать формат json 4. Отправить запрос | H12: 405 Method Not Allowed { "detail": "Метод \"GET\" не разрешен." } | I12: 405 Method Not Allowed { "detail": "Метод \"GET\" не разрешен." } | K12: Postman | L12: Отрицательный ответ не прописан в документации swagger | M12: Ибрагимова Юлия
A13: API_qstn_pplctn_bg_2 | B13: Стандартный | C13: Низкий | D13: Отрицательный ответ 405 Method Not Allowed не прописан в в документации swagger при попытке проверки запроса с неверным HTTP-методом PUT при запросе на эндпоинт /question_application/ | F13: 1.Открыто приложение Postman 2.Ввести адрес тестового стенда: pl.rassokha.pro:8000/api/v1 3.API доступен и авторизация не требуется для PUT-запроса | G13: 1. Создать PUT-запрос с на эндпоинт /question_application/ 2.Ввести в body { "first_name": "Маша", "last_name": "Машковна", "middle_name": "Михайловна", "phone": "+79165678098", "email": "user@yandex.com", "city": "Москва", "question": "Как долго отправляются товары?", "accept_confidential_policy": true } 3. Выбрать формат json 4. Отправить запрос | H13: 405 Method Not Allowed { "detail": "Метод \"PUT\" не разрешен." } | I13: 405 Method Not Allowed { "detail": "Метод \"PUT\" не разрешен." } | K13: Postman | L13: Отрицательный ответ не прописан в документации swagger | M13: Ибрагимова Юлия
A14: API_qstn_pplctn_bg_3 | B14: Стандартный | C14: Низкий | D14: Отрицательный ответ 405 Method Not Allowed не прописан в в документации swagger при попытке проверки запроса с неверным HTTP-методом PATCH при запросе на эндпоинт /question_application/ | F14: 1.Открыто приложение Postman 2.Ввести адрес тестового стенда: pl.rassokha.pro:8000/api/v1 3.API доступен и авторизация не требуется для PATCH-запроса | G14: 1. Создать PATCH-запрос с на эндпоинт /question_application/ 2.Ввести в body { "first_name": "Маша", "last_name": "Машковна", "middle_name": "Михайловна", "phone": "+79165678098", "email": "user@yandex.com", "city": "Москва", "question": "Как долго отправляются товары?", "accept_confidential_policy": true } 3. Выбрать формат json 4. Отправить запрос | H14: 405 Method Not Allowed { "detail": "Метод \"PATCH\" не разрешен." } | I14: 405 Method Not Allowed { "detail": "Метод \"PATCH\" не разрешен." } | K14: Postman | L14: Отрицательный ответ не прописан в документации swagger | M14: Ибрагимова Юлия
A15: API_qstn_pplctn_bg_4 | B15: Стандартный | C15: Низкий | D15: Отрицательный ответ 405 Method Not Allowed не прописан в в документации swagger при попытке проверки запроса с неверным HTTP-методом DELETE при запросе на эндпоинт /question_application/ | F15: 1.Открыто приложение Postman 2.Ввести адрес тестового стенда: pl.rassokha.pro:8000/api/v1 3.API доступен и авторизация не требуется для DELETE-запроса | G15: 1. Создать DELETE-запрос с на эндпоинт /question_application/ 2.Ввести в body { "first_name": "Маша", "last_name": "Машковна", "middle_name": "Михайловна", "phone": "+79165678098", "email": "user@yandex.com", "city": "Москва", "question": "Как долго отправляются товары?", "accept_confidential_policy": true } 3. Выбрать формат json 4. Отправить запрос | H15: 405 Method Not Allowed { "detail": "Метод \"DELETE\" не разрешен." } | I15: 405 Method Not Allowed { "detail": "Метод \"DELETE\" не разрешен." } | K15: Postman | L15: Отрицательный ответ не прописан в документации swagger | M15: Ибрагимова Юлия
A16: API_qstn_pplctn_bg_5 | B16: Стандартный | C16: Средний | D16: Невозможно проверить запрос с неверным HTTP-методом HEAD при запросе на эндпоинт /question_application/ в postman | F16: 1.Открыто приложение Postman 2.Ввести адрес тестового стенда: pl.rassokha.pro:8000/api/v1 3.API доступен и авторизация не требуется для HEAD-запроса | G16: 1. Создать HEAD-запрос с на эндпоинт /question_application/ 2.Ввести в body { "first_name": "Маша", "last_name": "Машковна", "middle_name": "Михайловна", "phone": "+79165678098", "email": "user@yandex.com", "city": "Москва", "question": "Как долго отправляются товары?", "accept_confidential_policy": true } 3. Выбрать формат json 4. Отправить запрос | H16: 405 Method Not Allowed { "detail": "Метод \"HEAD\" не разрешен." } | I16: Ответа нет "Cloud Agent Error:Unable to reach the Cloud Agent. Try later or select a different agent." | J16: 2025-11-09_13-14-29.png | K16: Postman | M16: Ибрагимова Юлия
A17: API_qstn_pplctn_bg_6 | B17: Стандартный | C17: Низкий | D17: Отрицательный ответ 405 Method Not Allowed не прописан в в документации swagger при попытке проверки запроса с неверным HTTP-методом OPTIONS при запросе на эндпоинт /question_application/ | F17: 1.Открыто приложение Postman 2.Ввести адрес тестового стенда: pl.rassokha.pro:8000/api/v1 3.API доступен и авторизация не требуется для PUT-запроса | G17: 1. Создать OPTIONS-запрос с на эндпоинт /question_application/ 2.Ввести в body { "first_name": "Маша", "last_name": "Машковна", "middle_name": "Михайловна", "phone": "+79165678098", "email": "user@yandex.com", "city": "Москва", "question": "Как долго отправляются товары?", "accept_confidential_policy": true } 3. Выбрать формат json 4. Отправить запрос | H17: { "detail": "Метод \"OPTIONS\" не разрешен." } | I17: { "detail": "Метод \"OPTIONS\" не разрешен." } | K17: Postman | L17: Отрицательный ответ не прописан в документации swagger | M17: Ибрагимова Юлия
A18: API_fml_pplctns_lst_bg_3 | B18: Высокий | C18: Высокий | D18: в документации нет требований к ответу для GET /family_applications_list/cities/ | F18: ссылка на swagger: https://pl.rassokha.pro:8000/swagger/ | G18: 1) пройти по ссылке: https://pl.rassokha.pro:8000/swagger/ 2) выполнить GET запрос на эндпоинт /family_applications_list/cities/ | H18: в графе Responses указаны требования для список городов, указанных при регистрации заявки на оказание помощи в алфавитном порядке 200 ОК [ "string", "string" ] | I18: указан формат ответа для GET /family_applications_list/ 200 ОК { "count": 0, "next": "string", "previous": "string", "results": [ { "id": 0, "city": "string", "full_name": "string", "status": "new_in" } ] } | J18: API_fml_pplctns_lst_bg_3.png | K18: Swagger | M18: Раскошная Анастасия
A19: API_dntn_bg1 | B19: Высокий | C19: Высокий | D19: Запросы к эндпоинту /donation/ запрещены | E19: Отправка POST запроса возвращает 403 Forbidden. Невозможно проверить функционал | F19: 1. Открыто приложение Postman 2. Используется тестовый стенд pl.rassokha.pro:8000/api/v1 | G19: 1. Создать POST запрос на эндпоинт /donation/ 2. В тело запроса вставить: { "id": "string", "created_at": "string", "amount": { "additionalProp1": "string", "additionalProp2": "string", "additionalProp3": "string" }, "metadata": { "additionalProp1": "string", "additionalProp2": "string", "additionalProp3": "string" }, "status": "pending", "description": "string", "value": "string", "family_request": [ 0 ], "first_name": "string", "payment_method": "string" } 3.Отправить запрос | H19: Возвращается код 200 Created Возвращаются заголовки: { "Vary": "Accept, Cookie", "Allow": "POST, OPTIONS", "X-Frame-Options": "SAMEORIGIN", "Content-Length": "0", "X-Content-Type-Options": "nosniff", "Referrer-Policy": "same-origin", "Cross-Origin-Opener-Policy": "same-origin" } | I19: Возвращается код 403 Forbidden Приходит ответ с телом: <html> <head> <title>403 Forbidden</title> </head> <body> <center> <h1>403 Forbidden</h1> </center> <hr> <center>nginx</center> </body> </html> | K19: Postman | M19: Тимофей Каналин
A20: API_blg_bg1 | B20: Стандартный | C20: Средний | D20: В документации в теле ответа нет к эндпоинту /blog/ нет элемента "current" | F20: ссылка на swagger: https://pl.rassokha.pro:8000/swagger/ | G20: Отправить GET запрос на на эндпоинт /blog/ | H20: 200 ОК { "current": integer "count": integer, "next": "string", "previous": "string", "results": [ { "id": 0, "title": "string", "image": "string", "created_at": "string($date-time)", "link": "string" } ] } где "current": 1 | I20: в документации нет элемента "current" { "count": integer, "next": "string", "previous": "string", "results": [ { "id": integer, "title": "string", "image": "string", "created_at": "string($date-time)", "link": "string" } ] } | J20: API_blg_1.png | K20: Swagger | M20: Раскошная Анастасия
K21: Swagger | M21: Ибрагимова Юлия
K22: Postman | M22: Ибрагимова Юлия
K23: Postman | M23: Ибрагимова Юлия
K24: Postman | M24: Ибрагимова Юлия
K25: Postman | M25: Ибрагимова Юлия
K26: Postman | M26: Ибрагимова Юлия
K27: Postman | M27: Ибрагимова Юлия
J28: API.png | K28: Postman | M28: Гемуев Кирилл
A29: API_fml_rqst_bg1 | B29: Критический | C29: Высокий | D29: В документации не описанн POST запрос на эндпоинт family_request/{id}/comments/ | E29: В документации не описанн POST запрос на эндпоинт family_request/{id}/comments/ Поле для коментарьев присутствует на фронтенде | F29: 1. Открыто приложение Postman 2. Используется тестовый стенд pl.rassokha.pro:8000/api/v1 3.API доступен и авторизация не требуется для POST-запроса | G29: 1. Создать POST запрос на эндпоинт family_request/{id}/comments/ где {id} - существующий запрос 2. Отправить запрос | H29: 405 Method Not Allowed { "detail": "Метод \"POST\" не разрешен." } | I29: 400 Error: Bad Request { "name": [ "Обязательное поле." ], "email": [ "Обязательное поле." ], "text": [ "Обязательное поле." ], "accept_confidential_policy": [ "Обязательное поле." ] } | J29: family_request.png | K29: Postman | M29: Гемуев Кирилл
A30: API_they_nd_hlp_bg1 | B30: Стандартный | C30: Средний | D30: В документации GET /they_need_help_too/{id}/ неверный тип данных для id | E30: Тип данных id должен быть integer | F30: 1. Открыто приложение Postman 2. Используется тестовый стенд pl.rassokha.pro:8000/api/v1 | G30: 1. Создать POST запрос на эндпоинт /they_need_help_too/{id}/ где {id} - существующий идентификатор семьи 2. Отправить запрос | H30: Возвращается код 200 OK Тело ответа: [ { "id": integer, "family_name": "string", "image": "string" } ] | I30: 405 Method Not Allowed { "detail": "Метод не поддерживается." } | K30: Postman | L30: ОР и ФР относятся к функциональному багу (см QA_Pomogi_2_39_Тестовая документация) | M30: Тимофей Каналин

Sheet Баг-репорты API
A1: ID | B1: Severity | C1: Priority | D1: Название бага | E1: Описание | F1: Предусловия | G1: Шаги воспроизведения | H1: ОР | I1: ФР | J1: Скринкаст/скриншот | K1: Окружение | L1: Комментарий | M1: Автор
J2: video_report_bg1.png | K2: Postman | L2: Не действительный баг | M2: Гемуев Кирилл
J3: they_need_help_too_bg1.png | K3: Postman | M3: Гемуев Кирилл
J4: social_links_bg1.png | K4: Postman | L4: Не действительный баг | M4: Гемуев Кирилл
J5: faq_bg1.png | K5: Postman | L5: Не действительный баг | M5: Гемуев Кирилл
A6: API_fml_pplctns_lst_bg_1 | B6: Высокий | C6: Высокий | D6: 200 ОК при создании GET запроса на эндпоинт /family_applications_list/ с параметром "limit" и "offset" = дробь | F6: Base URL: pl.rassokha.pro:8000/api/v1 | G6: 1. Создать GET запрос на эндпоинт /family_applications_list/ 2. Во вкладке Params ввести: key: "limit", value: 2.2 key: "offset", value: 2.2 3. Отправить запрос | H6: 400 Bad Request | I6: Список из 10 первых оформленных заявок 200 Ок { "count": integer, "next": "string($uri)", "previous": "string($uri)", "results": [ { "id": integer, "city": "string", "full_name": "string", "status": "string" } ] } | J6: API_fml_pplctns_lst_1.png | K6: Postman | L6: в документации нет информации о формате ошибки | M6: Раскошная Анастасия
A7: API_fml_pplctns_lst_bg_2 | B7: Высокий | C7: Высокий | D7: 200 ОК при создании GET запроса на эндпоинт /family_applications_list/ с параметром "limit" и "offset" = "string" | F7: Base URL: pl.rassokha.pro:8000/api/v1 | G7: 1. Создать GET запрос на эндпоинт /family_applications_list/ 2. Во вкладке Params ввести: key: "limit", value: "5" key: "offset", value: "5" 3. Отправить запрос | H7: 400 Bad Request | I7: Список из 10 первых оформленных заявок 200 Ок { "count": integer, "next": "string($uri)", "previous": "string($uri)", "results": [ { "id": integer, "city": "string", "full_name": "string", "status": "string" } ] } | J7: API_fml_pplctns_lst_2.png | K7: Postman | L7: в документации нет информации о формате ошибки | M7: Раскошная Анастасия
A8: API | B8: Высокий | C8: Высокий | D8: Ответ 200 при запросе неверным HTTP-методом | E8: При отправке запроса на любой эдпоинт неверным HTTP-методом можно получить ответ 200, если в конце адреса не ставить "/" | F8: 1. Открыто приложение Postman 2. Используется тестовый стенд pl.rassokha.pro:8000/api/v1 3.API доступен и авторизация не требуется для POST-запроса | G8: 1. Создать GET запрос на эндпоинт/helped_online 2. Отправить запрос | H8: 405 Method Not Allowed { "detail": "Метод \"POST\" не разрешен." } | I8: 200 Ок [ { "count": integer, "description": "string" } ] | K8: Postman | M8: Гемуев Кирилл
A9: API_blg_bg2 | B9: Высокий | C9: Высокий | D9: Ответ 404 при создании GET запроса на эндпоинт /blog/ с параметром "page" = "string" | F9: Base URL: pl.rassokha.pro:8000/api/v1 | G9: 1. Создать GET запрос на эндпоинт /blog/ 2. Во вкладке Params ввести: key: "page", value: "2" 3. Отправить запрос | H9: 400 Bad Request | I9: 404 Not Found { "detail": "Неправильная страница" } | J9: API_blg_bg2.png | K9: Postman | M9: Раскошная Анастасия
A10: API_blg_bg3 | B10: Высокий | C10: Высокий | D10: Ответ 404 при создании GET запроса на эндпоинт /blog/ с параметром "page" = null | F10: Base URL: pl.rassokha.pro:8000/api/v1 | G10: 1. Создать GET запрос на эндпоинт /blog/ 2. Во вкладке Params ввести: key: "page", value: null 3. Отправить запрос | H10: Список постов в блоге: первая страница, 8 постов, начиная с последнее опубликованного. 200 ОК { "current": integer, "count": integer, "next": "string", "previous": null, "results": [ { "id": integer, "title": "string", "image": "string", "created_at": "string($date-time)", "link": "string" } ] } где "current": 1 | I10: 404 Not Found { "detail": "Неправильная страница" } | J10: API_blg_bg3.png | K10: Postman | M10: Раскошная Анастасия
A11: API_blg_bg4 | B11: Стандартный | C11: Средний | D11: В теле ответа нет времени создания блога при создании GET запроса на эндпоинт /blog/ | F11: Base URL: pl.rassokha.pro:8000/api/v1 | G11: Отправить GET запрос на эндпоинт /blog/ | H11: Список постов в блоге: первая страница, 8 постов, начиная с последнее опубликованного. 200 ОК { "current": integer, "count": integer, "next": "string", "previous": null, "results": [ { "id": integer, "title": "string", "image": "string", "created_at": "string($date-time)", "link": "string" } ] } где "current": 1, "created_at": имеет вид "2025-11-11T17:54:58.387Z" | I11: Список постов в блоге: первая страница, 8 постов, начиная с последнее опубликованного. 200 ОК { "current": integer, "count": integer, "next": "string", "previous": null, "results": [ { "id": integer, "title": "string", "image": "string", "created_at": "string($date-time)", "link": "string" } ] } где "current": 1, "created_at": имеет вид "20.06.2025" | J11: API_blg_bg4.png | K11: Postman | M11: Раскошная Анастасия
A12: API_blg_bg5 | B12: Стандартный | C12: Средний | D12: В теле ответа нет времени создания блога при создании GET запроса на эндпоинт /blog/ {id} | F12: Base URL: pl.rassokha.pro:8000/api/v1 | G12: Отправить GET запрос на эндпоинт /blog/{id}/ где id=integer, существующего блога | H12: 200 OK { "count": integer, "next": "string", "previous": "string", "results": [ { "id": integer, "title": "string", "image": "string", "created_at": "string($date-time)", "link": "string" } ] } где id соответствует заданному, "created_at": имеет вид "2025-11-11T22:17:48.433Z" | I12: 200 OK { "count": integer, "next": "string", "previous": "string", "results": [ { "id": integer, "title": "string", "image": "string", "created_at": "string($date-time)", "link": "string" } ] } где id соответствует заданному, "created_at": имеет вид "14.06.2025" | K12: Postman | M12: Раскошная Анастасия
I13: 200 OK { "count": integer, "next": "string", "previous": "string", "results": [ { "id": integer, "title": "string", "image": "string", "created_at": "string($date-time)", "link": "string" } ] } где id соответствует заданному, "created_at": имеет вид "14.06.2025" | J13: API_blg_bg6.png | K13: Postman | L13: Не действительный баг | M13: Раскошная Анастасия
A14: API_dntn_bg_1 | B14: Высокий | C14: Высокий | D14: Отправка POST запроса на эндпоинт /donation/ запрещена | F14: 1. Открыто приложение Postman 2. Используется тестовый стенд pl.rassokha.pro:8000/api/v1 | G14: 1. Создать POST запрос на эндпоинт /donation/ 2. В тело запроса вставить: { "id": "string", "created_at": "string", "amount": { "additionalProp1": "string", "additionalProp2": "string", "additionalProp3": "string" }, "metadata": { "additionalProp1": "string", "additionalProp2": "string", "additionalProp3": "string" }, "status": "pending", "description": "string", "value": "string($decimal)", "family_request": [ 0 ], "first_name": "string", "payment_method": "string" } 3.Отправить запрос | H14: Возвращается код 200 Created Возвращаются заголовки: { "Vary": "Accept, Cookie", "Allow": "POST, OPTIONS", "X-Frame-Options": "SAMEORIGIN", "Content-Length": "0", "X-Content-Type-Options": "nosniff", "Referrer-Policy": "same-origin", "Cross-Origin-Opener-Policy": "same-origin" } | I14: Возвращается код 403 Forbidden | K14: Postman | M14: Тимофей Каналин

Sheet Чек-лист САЙТ
A1: Vjlekm | B1: ID | C1: Приоритет | D1: Описание проверки | E1: Ссылка на баг-репорт | F1: Комментарий | G1: Статус проверки ОС: Разрешение: Браузер: Chrome 141.0.7390.123 | H1: Статус проверки ОС: macOS Tahoe 26.0.1 Разрешение: 3456 x 2234 Браузер: Chrome 142.0.7444.135 | I1: Статус проверки ОС: Windows 11 Разрешение: 2560х1600 Браузер: Яндекс. 25.8.5.890 | J1: Статус проверки ОС: Windows 10 Pro 22H2 Разрешение: 2560x1080 Браузер: Яндекс. 25.10.0.2474 | K1: Статус проверки ОС: Windows 10 Разрешение: 1980x1080 Браузер: Opera 123.0.5669.23 | L1: Статус проверки ОС: Windows 11 Pro Разрешение: 1920х1080 Браузер: Opera 123.0.5669.47 | M1: Статус проверки ОС: Разрешение: Браузер: Edge 142.0.3595.53 | N1: Статус проверки ОС: Windows 10 Разрешение: 1920х1080 Браузер: Edge 142.0.3595.65
A2: Главная страница | B2: hm_pg_2 | C2: Критичный | D2: На страницу "Главная" можно попасть введя ссылку в браузер https://pl.rassokha.pro:3001 | H2: Passed | I2: Passed | L2: Passed | N2: Passed
A3: Главная страница | B3: hm_pg_3 | C3: Критичный | D3: При первом посещении страницы в нижней части экрана появляется текст: «Мы используем файлы cookie для анализа трафика и улучшения вашего опыта. Некоторые cookie необходимы для работы сайта. Подробнее в нашей Политике использования cookie.». В этом сообщении есть 2 кнопки зелёного цвета: «Отклонить» и «Принять все». | H3: Passed | I3: Passed | L3: Passed | N3: Passed
A4: Главная страница | B4: hm_pg_4 | C4: Низкий | D4: Отображение блока с заголовком "Вы помогли этим детям!" в верхней левой части экрана. | H4: Passed | I4: Passed | L4: Passed | N4: Passed
A5: Главная страница | B5: hm_pg_5 | C5: Низкий | D5: Используемый цвет фона для блока "Вы помогли этим детям! " #EFB46D | F5: А разве не подложка будет с элементами на ней? В макете есть галочки в кружочка на подложке цвета #EFB46D, а фон белый уже как все страницы у блока | H5: Passed | I5: Passed | L5: Passed | N5: Passed
A6: Главная страница | B6: hm_pg_6 | C6: Средний | D6: Заголовок "Вы помогли этим детям! " расположен в левой части экрана | H6: Passed | I6: Passed | L6: Passed | N6: Passed
A7: Главная страница | B7: hm_pg_7 | C7: Низкий | D7: Заголовок блока "Вы помогли этим детям! " выделен крупным шрифтом "ХL" | H7: Passed | I7: Passed | L7: Passed | N7: Passed
A8: Главная страница | B8: hm_pg_8 | C8: Низкий | D8: Используемый шрифт текста "Вы помогли этим детям! ", "Neucha" | H8: Passed | I8: Passed | L8: Passed | N8: Passed
A9: Главная страница | B9: hm_pg_9 | C9: Низкий | D9: Используемый цвет шрифта заголовка "Вы помогли этим детям! " на макете и на сайте #FFFFFF | H9: Passed | I9: Passed | L9: Passed | N9: Passed
A10: Главная страница | B10: hm_pg_10 | C10: Низкий | D10: Под заголовком "Вы помогли этим детям! " расположены блоки "видео" | H10: Passed | I10: Passed | L10: Passed | N10: Passed
A11: Главная страница | B11: hm_pg_11 | C11: Низкий | D11: Наличие длительности в правом нижнем углу. | E11: hm_pg_bg_1 | H11: Failed | I11: Failed | L11: Failed | N11: Failed
A12: Главная страница | B12: hm_pg_12 | C12: Низкий | D12: Используемый цвет цифр длительности "видео", "0:08" #FFFFFF | E12: hm_pg_bg_1 | H12: Blocked | I12: Blocked | L12: Blocked | N12: Blocked
A13: Главная страница | B13: hm_pg_13 | C13: Низкий | D13: Форма блока (прямоугольная с закруглёнными краями). | H13: Passed | I13: Passed | L13: Passed | N13: Passed
A14: Главная страница | B14: hm_pg_14 | C14: Низкий | D14: Ниже под "видео" расположен заголовок с описанием | H14: Passed | I14: Passed | L14: Passed | N14: Passed
A15: Главная страница | B15: hm_pg_15 | C15: Низкий | D15: Размер текста : s медиум | H15: Passed | I15: Passed | L15: Passed | N15: Passed
A16: Главная страница | B16: hm_pg_16 | C16: Низкий | D16: Цвет текста: #267067 | H16: Passed | I16: Passed | L16: Passed | N16: Passed
A17: Главная страница | B17: hm_pg_17 | C17: Низкий | D17: Шрифт текста "Montserrat" | H17: Passed | I17: Passed | L17: Passed | N17: Passed
A18: Главная страница | B18: hm_pg_18 | C18: Низкий | D18: Ниже описанием подарков, расположены "просмотры" "18 просмотров • 3 месяца назад" | H18: Passed | I18: Passed | L18: Passed | N18: Passed
A19: Главная страница | B19: hm_pg_19 | C19: Низкий | D19: Заголовок текста "18 просмотров • 3 месяца назад" выделен крупным шрифтом "ххs" | H19: Passed | I19: Passed | L19: Passed | N19: Passed
A20: Главная страница | B20: hm_pg_20 | C20: Низкий | D20: Используемый цвет шрифта "18 просмотров • 3 месяца назад" # 727271 | H20: Passed | I20: Passed | L20: Passed | N20: Passed
A21: Главная страница | B21: hm_pg_21 | C21: Низкий | D21: Используемый шрифт текста "18 просмотров • 3 месяца назад" , "Montserrat" | H21: Passed | I21: Passed | L21: Passed | N21: Passed
A22: Главная страница | B22: hm_pg_22 | C22: Высокий | D22: При клике на "видео" открывается новая вкладка в браузере "Благотворительный фонд "Помоги Лично" "ВКонтакте". | H22: Passed | I22: Passed | L22: Passed | N22: Passed
A23: Главная страница | B23: hm_pg_23 | C23: Средний | D23: Проверки аналогичные для каждого последующего блока с описанием "видео" | H23: Passed | I23: Passed | L23: Passed | N23: Passed
A24: Главная страница | B24: hm_pg_24 | C24: Средний | D24: В правом верхнем углу над блоком фото "видео" расположены иконки стрелки "<", ">" | H24: Passed | I24: Passed | L24: Passed | N24: Passed
... A35: Главная страница | B35: hm_pg_38 | C35: Низкий | D35: Ниже под блоком "Вы помогли этим детям! " расположен блок с заголовком "Нужна помощь!" | H35: Passed | I35: Passed | L35: Passed | N35: Passed
A36: Главная страница | B36: hm_pg_39 | C36: Средний | D36: Блок "Нужна помощь!" состоит из следующих элементов: фон "подложка", блок из карточек "семья", фото, стрелки, лого, кнопка, заголовки текста | E36: QA_Pomogi_2_39_Тестовая документация | H36: Passed | I36: Passed | L36: Passed | N36: Failed
A37: Главная страница | B37: hm_pg_41 | C37: Низкий | D37: Заголовок блока "Нужна помощь!" выделен крупным шрифтом "ХL" | H37: Passed | I37: Passed | L37: Passed | N37: Passed
A38: Главная страница | B38: hm_pg_42 | C38: Низкий | D38: Используемый шрифт текста "Нужна помощь!", "Neucha" | H38: Passed | I38: Passed | L38: Passed | N38: Passed
A39: Главная страница | B39: hm_pg_43 | C39: Низкий | D39: Используемый цвет шрифта заголовка "Нужна помощь!" на макете и на сайте #FFFFFF | H39: Passed | I39: Passed | L39: Passed | N39: Passed
A40: Главная страница | B40: hm_pg_44 | C40: Низкий | D40: Под заголовком "Нужна помощь!" расположена карточка с фото "семья" | H40: Passed | I40: Passed | L40: Passed
A41: Главная страница | B41: hm_pg_45 | C41: Низкий | D41: Карточка имеет прямоугольную форму с закругленными краями | H41: Passed | I41: Passed | L41: Passed | N41: Passed
A42: Главная страница | B42: hm_pg_46 | C42: Низкий | D42: Карточка разделена на 2 цвета, правая часть #FFFFFF цвет левая часть #FFE0BC | H42: Passed | L42: Passed | N42: Passed
A43: Главная страница | B43: hm_pg_47 | C43: Низкий | D43: В верхнем левом углу карточки расположено фото семьи | H43: Passed | I43: Passed | L43: Passed | N43: Passed
A44: Главная страница | B44: hm_pg_48 | C44: Средний | D44: Фото кликабельно, при клике раскрывается по центру экрана (в модальном окне) | H44: Passed | I44: Passed | L44: Passed | N44: Passed
A45: Главная страница | B45: hm_pg_49 | C45: Средний | D45: Нажатие на крестик в правом верхнем углу в модальном окне закрывает фото | H45: Passed | I45: Passed | L45: Passed | N45: Passed
A46: Главная страница | B46: hm_pg_50 | C46: Низкий | D46: По центру фото "семьи" с левой и правой стороны расположены угловые стрелки | F46: Не хватает проверок на стрелки в модальном окне | H46: Passed | I46: Passed | L46: Passed | N46: Passed
A47: Главная страница | B47: hm_pg_51 | C47: Низкий | D47: Используемый цвет стрелки "<", #FFFFFF | H47: Passed | I47: Passed | L47: Passed | N47: Passed
A48: Главная страница | B48: hm_pg_52 | C48: Средний | D48: Угловая стрелка кликабельна "<" имеет 2 состояния "default", "hover" | H48: Passed | I48: Passed | L48: Passed | N48: Passed
A49: Главная страница | B49: hm_pg_53 | C49: Средний | D49: При нажатии на иконку "<" перелистывае фото "семьи" в лево | H49: Passed | I49: Passed | L49: Passed | N49: Passed
A50: Главная страница | B50: hm_pg_54 | C50: Низкий | D50: Аналогичные проверки для уловой стрелки в право ">" | H50: Passed | I50: Passed | L50: Passed | N50: Passed
A51: Главная страница | B51: hm_pg_55 | C51: Низкий | D51: В каждом фото в левом верхнем углу расположен "Лого" | H51: Passed | I51: Passed | L51: Passed | N51: Skipped
A52: Главная страница | B52: hm_pg_56 | C52: Высокий | D52: Лого имеет квадратную форму с закругленными краями, по центру расположен лого | H52: Passed | I52: Passed | L52: Passed | N52: Passed
A53: Главная страница | B53: hm_pg_57 | C53: Низкий | D53: defalt - цвет лого #FFFFFF цвет фона в лого #D89C66 | H53: Passed | I53: Passed | L53: Passed | N53: Skipped
A54: Главная страница | B54: hm_pg_58 | C54: Низкий | D54: hover - цвет лого #FFE0BC цвет фона в лого #D89C66 | E54: hm_pg_bg_2 | H54: Failed | I54: Failed | L54: Failed | N54: Skipped
A55: Главная страница | B55: hm_pg_59 | C55: Низкий | D55: Под фото семьи заголовок с текстом "Нужна помощь: многодетная мама в тяжёлой жизненной ситуации" | H55: Passed | I55: Passed | L55: Passed | N55: Passed
A56: Главная страница | B56: hm_pg_60 | C56: Высокий | D56: Заголовок текста под фото "Нужна помощь: многодетная мама в тяжёлой жизненной ситуации" выделен крупным шрифтом "М" | H56: Passed | I56: Passed | L56: Passed | N56: Passed
A57: Главная страница | B57: hm_pg_61 | C57: Низкий | D57: Используемый шрифт текста "Нужна помощь: многодетная мама в тяжёлой жизненной ситуации", "Montserrat" | H57: Passed | I57: Passed | L57: Passed | N57: Passed
A58: Главная страница | B58: hm_pg_62 | C58: Низкий | D58: Используемый цвет шрифта заголовка "Нужна помощь: многодетная мама в тяжёлой жизненной ситуации" на макете и на сайте #267067 | H58: Passed | I58: Passed | L58: Passed | N58: Passed
A59: Главная страница | B59: hm_pg_63 | C59: Высокий | D59: С правой стороны от фото по центру блока распожена лента пожертвований "Уже собрано 4 700 из 50 000 ₽" | H59: Passed | I59: Passed | L59: Passed | N59: Passed
A60: Главная страница | B60: hm_pg_64 | C60: Низкий | D60: Заголовок состоит из цифр и текста "Уже собрано 4 700 из 50 000 ₽" | H60: Passed | I60: Passed | L60: Passed | N60: Passed
A61: Главная страница | B61: hm_pg_65 | C61: Низкий | D61: Размер используемого шрифта заголовка "Уже собрано 4 700 из 50 000 ₽" медиум | H61: Passed | I61: Passed | N61: Passed
A62: Главная страница | B62: hm_pg_66 | C62: Низкий | D62: Используемый шрифт текста "Уже собрано 4 700 из 50 000 ₽", "Montserrat" | H62: Passed | I62: Passed | L62: Passed | N62: Passed
A63: Главная страница | B63: hm_pg_67 | C63: Низкий | D63: Используемый цвет шрифта заголовка "Уже собрано 4 700 из 50 000 ₽" на макете и на сайте #267067 | H63: Passed | I63: Passed | L63: Passed | N63: Passed
A64: Главная страница | B64: hm_pg_68 | C64: Низкий | D64: Используемый цвет цифр в заголовке "Уже собрано 4 700 из 50 000 ₽" #D89C66 | E64: hm_pg_bg_3 | H64: Failed | I64: Failed | L64: Failed | N64: Failed
A65: Главная страница | B65: hm_pg_69 | C65: Высокий | D65: Ниже под заголовком текста "Уже собрано 4 700 из 50 000 ₽" расположена "Шкала сбора средств" | H65: Passed | I65: Passed | L65: Passed | N65: Passed
A66: Главная страница | B66: hm_pg_70 | C66: Низкий | D66: "Шкала сбора средств" состоит из 2 цветов #EFB46D и #F2F1F1 | H66: Passed | I66: Passed | L66: Passed | N66: Passed
A67: Главная страница | B67: hm_pg_71 | C67: Низкий | D67: Под "Шкала сбора средств" расположен "divider" | H67: Passed | I67: Passed | L67: Passed | N67: Passed
A68: Главная страница | B68: hm_pg_72 | C68: Низкий | D68: "divider" имеет длинную тонкую форму | H68: Passed | I68: Passed | L68: Passed | N68: Passed
A69: Главная страница | B69: hm_pg_73 | C69: Низкий | D69: Используемый цвет "divider" #E1E1E1 | H69: Passed | I69: Passed | L69: Passed | N69: Passed
A70: Главная страница | B70: hm_pg_74 | C70: Низкий | D70: Под "divider" расположен текст "Дорогие друзья, в наш фонд" | F70: может просто текст с описанием? Не писать что внутри, так как текст разный | H70: Passed | I70: Passed | L70: Passed | N70: Passed
A71: Главная страница | B71: hm_pg_75 | C71: Низкий | D71: Размер используемого шрифта текста "Дорогие друзья, в наш фонд" "s" | H71: Passed | I71: Passed | L71: Passed | N71: Passed
A72: Главная страница | B72: hm_pg_76 | C72: Низкий | D72: Используемый шрифт текста "Дорогие друзья, в наш фонд", "Montserrat" | H72: Passed | I72: Passed | L72: Passed | N72: Passed
A73: Главная страница | B73: hm_pg_77 | C73: Низкий | D73: Используемый цвет шрифта текста "Дорогие друзья, в наш фонд"на макете и на сайте #000000 | H73: Passed | I73: Passed | L73: Passed | N73: Passed
A74: Главная страница | B74: hm_pg_78 | C74: Высокий | D74: Под текстом "Дорогие друзья, в наш фонд" по центру расположена кнопка "ПОМОЧЬ" | F74: в девтулс ссылка (не кнопка) ---- | H74: Passed | I74: Passed | L74: Passed | N74: Passed
A75: Главная страница | B75: hm_pg_79 | C75: Низкий | D75: Кнопка имеет прямоугольную вытянутую форму с закругленными краями | H75: Passed | I75: Passed | L75: Passed | N75: Passed
A76: Главная страница | B76: hm_pg_80 | C76: Низкий | D76: Используемый цвет кнопки #267067 | H76: Passed | I76: Passed | L76: Passed | N76: Passed
A77: Главная страница | B77: hm_pg_81 | C77: Низкий | D77: На кнопке по центру расположен текст "ПОМОЧЬ" | H77: Passed | I77: Passed | L77: Passed | N77: Passed
A78: Главная страница | B78: hm_pg_82 | C78: Низкий | D78: Надпись шрифта выделена жирным "ПОМОЧЬ" "s" | H78: Passed | I78: Passed | L78: Passed | N78: Passed
A79: Главная страница | B79: hm_pg_83 | C79: Низкий | D79: Используемый шрифт текста "ПОМОЧЬ", "Montserrat" | H79: Passed | I79: Passed | L79: Passed | N79: Passed
A80: Главная страница | B80: hm_pg_84 | C80: Низкий | D80: Используемый цвет шрифта "ПОМОЧЬ"на макете и на сайте #FFFFFF | H80: Passed | I80: Passed | L80: Passed | N80: Passed
A81: Главная страница | B81: hm_pg_85 | C81: Низкий | D81: Состояние кнопок
A82: Главная страница | B82: hm_pg_86 | C82: Высокий | D82: defalt - кнопка имеет цвет #267067 текст на кнопке "ПОМОЧЬ" #FFFFFF | H82: Passed | I82: Passed | L82: Passed | N82: Passed
A83: Главная страница | B83: hm_pg_87 | C83: Высокий | D83: hover- кнопка имеет цвет #267067 текст на кнопке "ПОМОЧЬ" #EFB46D | H83: Passed | I83: Passed | L83: Passed | N83: Passed
A84: Главная страница | B84: hm_pg_88 | C84: Высокий | D84: click - цвет кнопки #EFB46D текст на кнопке "ПОМОЧЬ" #FFFFFF | H84: Passed | I84: Passed | L84: Passed | N84: Skipped
A85: Главная страница | B85: hm_pg_89 | C85: Средний | D85: disable - цвет кнопки #E1E1E1 текст на кнопке ""ПОМОЧЬ"" #FFFFFF "ПОМОЧЬ" | F85: Данного состояния у ссылки нет, лишний тест | L85: Skipped | N85: Skipped
A86: Главная страница | B86: hm_pg_90 | C86: Средний | D86: Аналогичные проверки для каждого последующего блока | E86: hm_pg_bg_2 hm_pg_bg_3 | H86: Failed | I86: Failed | L86: Failed | N86: Skipped
A87: Главная страница | B87: hm_pg_91 | C87: Высокий | D87: Справой стороны от блока "Нужна помощь!" расположена карточка "Отчет о поступлениях 29.04.2024" | E87: hm_pg_bg_4 | F87: У меня ниже блока | H87: Failed | I87: Failed | L87: Failed | N87: Failed
A88: Главная страница | B88: hm_pg_92 | C88: Высокий | D88: Блок "Отчет о поступлениях 29.04.2024" содержит следующие элементы: заголовок, цифры, divider, | E88: hm_pg_bg_5 | F88: Заголовок, divider, имя благотворителя или "анонимно", сумма пожертвования, ссылка на отчеты "Посмотреть все отчеты →" | H88: Failed | I88: Failed | L88: Failed | N88: Skipped
A89: Главная страница | B89: hm_pg_93 | C89: Низкий | D89: Блок "Отчет о поступлениях 29.04.2024" имеет прямоугольную форму с закругленными краями | F89: Обнаружен баг hm_pg_bg_4 по названию блока, но форма соответствует ожидаемой | H89: Passed | I89: Passed | L89: Passed | N89: Skipped
A90: Главная страница | B90: hm_pg_94 | C90: Низкий | D90: Используемый цвет фона блока "Отчет о поступлениях 29.04.2024" #FFE0BC | H90: Passed | I90: Passed | L90: Passed | N90: Skipped
A91: Главная страница | B91: hm_pg_95 | C91: Низкий | D91: Используемый цвет заголовка текста "Отчет о поступлениях 29.04.2024" #267067 | H91: Passed | I91: Passed | L91: Passed | N91: Skipped
A92: Главная страница | B92: hm_pg_96 | C92: Низкий | D92: Используемый шрифта заголовка "Отчет о поступлениях 29.04.2024" "Montserrat" | H92: Passed | I92: Passed | L92: Passed | N92: Skipped
A93: Главная страница | B93: hm_pg_97 | C93: Низкий | D93: Используемый размер текста "Отчет о поступлениях 29.04.2024", "s" медиум | H93: Passed | I93: Passed | L93: Passed | N93: Skipped
A94: Главная страница | B94: hm_pg_98 | C94: Низкий | D94: Под заголовком текста "Отчет о поступлениях 29.04.2024" расположен divider, | H94: Passed | I94: Passed | L94: Passed | N94: Skipped
A95: Главная страница | B95: hm_pg_99 | C95: Низкий | D95: "divider" имеет длинную тонкую форму | H95: Passed | I95: Passed | L95: Passed | N95: Skipped
A96: Главная страница | B96: hm_pg_100 | C96: Низкий | D96: Используемый цвет "divider" #267067 | H96: Passed | I96: Passed | L96: Passed | N96: Skipped
A97: Главная страница | B97: hm_pg_101 | C97: Низкий | D97: Под divider расположен вертикальный список пожертвований, где каждая строка содержит имя отправителя слева и сумму в ₽ справа. | H97: Passed | I97: Passed | L97: Passed | N97: Skipped
A98: Главная страница | B98: hm_pg_102 | C98: Высокий | D98: Используемый цвет списка #000000 | H98: Passed | I98: Passed | L98: Passed | N98: Skipped
A99: Главная страница | B99: hm_pg_103 | C99: Низкий | D99: Используемый шрифта списка "Montserrat" | H99: Passed | I99: Passed | L99: Passed | N99: Skipped
A100: Главная страница | B100: hm_pg_104 | C100: Высокий | D100: Под списком расположена ссылка "Посмотреть все отчеты →" | E100: hm_pg_bg_5 | H100: Failed | I100: Failed | L100: Failed | N100: Failed
A101: Главная страница | B101: hm_pg_105 | C101: Низкий | D101: Цвет сылки "Посмотреть все отчеты →" #000000 | E101: hm_pg_bg_5 | H101: Blocked | I101: Blocked | L101: Blocked | N101: Blocked
A102: Главная страница | B102: hm_pg_106 | C102: Низкий | D102: Размет шрифта ссылки "Посмотреть все отчеты →" "s" ссылка | E102: hm_pg_bg_5 | H102: Blocked | I102: Blocked | L102: Blocked | N102: Blocked
A103: Главная страница | B103: hm_pg_107 | C103: Низкий | D103: Шрифт ссылки"Посмотреть все отчеты →" "Montserrat" | E103: hm_pg_bg_5 | H103: Blocked | I103: Blocked | L103: Blocked | N103: Blocked
A104: Главная страница | B104: hm_pg_109 | C104: Низкий | D104: При наведении на ссылку "Посмотреть все отчеты →" курсором мыши появляется hover-эффект (подчеркивание) | E104: hm_pg_bg_5 | H104: Blocked | I104: Blocked | L104: Blocked | N104: Blocked
A105: Главная страница | B105: hm_pg_110 | C105: Низкий | D105: Ниже под блоком "Отчет о поступлениях 29.04.2024" расположен блок "ПОМОЧЬ ОЧЕНЬ ПРОСТО" | H105: Passed | I105: Passed | L105: Passed | N105: Passed
A106: Главная страница | B106: hm_pg_111 | C106: Высокий | D106: Блок "ПОМОЧЬ ОЧЕНЬ ПРОСТО" включает в себя следующие элементы: заголовок текста Благотворитель, поле ввода с плейсхолдером "Анонимно", заголовок "Сумма в рублях" блок из кнопок с суммами: 250 ₽, 500 ₽, 1000 ₽, ссылка "Указать свою", заголовок "Назначение платежа", поле ввода с плейсхолдером "Пожертвование", заголовок "Email для квитанции ", поле ввода с плейсхолдером "Указать email", чекбокс, заголовок "Я принимаю условия публичной оферты и даю согласие на обработку персональных данных", кнопка с текстом "ПОМОЧЬ С КАРТЫ" | E106: hm_pg_bg_6 | H106: Failed | I106: Failed | L106: Failed | N106: Failed
A107: Главная страница | B107: hm_pg_112 | C107: Высокий | D107: Используемый цвет фона блока "ПОМОЧЬ ОЧЕНЬ ПРОСТО" #FFE0BC | H107: Passed | I107: Passed | L107: Passed | N107: Passed
A108: Главная страница | B108: hm_pg_113 | C108: Низкий | D108: Блок "ПОМОЧЬ ОЧЕНЬ ПРОСТО" имеет прямоугольную форму с закругленными краями | H108: Passed | I108: Passed | L108: Passed | N108: Passed
A109: Главная страница | B109: hm_pg_114 | C109: Низкий | D109: Цвет "ПОМОЧЬ ОЧЕНЬ ПРОСТО" #267067 | H109: Passed | I109: Passed | L109: Passed | N109: Passed
A110: Главная страница | B110: hm_pg_115 | C110: Низкий | D110: Шрифт "ПОМОЧЬ ОЧЕНЬ ПРОСТО" "Neucha" | H110: Passed | I110: Passed | L110: Passed | N110: Passed
...

Sheet Баг-репорты САЙТ
A1: ID | B1: Severity | C1: Priority | D1: Название бага | E1: Описание | F1: Предусловия | G1: Шаги воспроизведения | H1: ОР | I1: ФР | J1: Скринкаст/скриншот | K1: Окружение | L1: Комментарий
A2: hm_pg_bg_1 | B2: Желательный | C2: Низкий | D2: Отсутствие отображения длительности видео в правом нижнем углу блока "Вы помогли этим детям!" на главной странице | E2: На макете указана длительность видео, но на тестовом стенде она не отображается | F2: Открыта главная страница сайта: https://pl.rassokha.pro:3001 | G2: Найти блок "Вы помогли этим детям!" с видео | H2: В правом нижнем углу видео отображается его длительность | I2: В правом нижнем углу видео длительность НЕ отображается | J2: hm_pg_bg_1.png | K2: macOS Tahoe 26.0.1 Разрешение: 3456 x 2234 Браузер: Chrome 142.0.7444.135 Разрешение: 1920х1080 Браузер: Opera 123.0.5669.47 ОС: Windows 11 Разрешение: 2560х1600 Браузер: Яндекс. 25.8.5.890 Edge Windows 10 Версия 142.0.3595.65 Разрешение 1920х1080 | L2: Ошибка влияет только на UI и не мешает основной функциональности
A3: hm_pg_bg_2 | B3: Желательный | C3: Низкий | D3: Логотип на карточке с фото в блоке "Нужна помощь!" на главной странице не соответствует состоянию hover | E3: По макетам лого должно менять цвет при наведении (hover) | F3: Открыта главная страница сайта: https://pl.rassokha.pro:3001 | G3: 1. Найти блок "Нужна помощь!" 2. Навести курсор на логотип в верхнем левом углу карточки | H3: При наведении на лого, оно должно менять цвет на #FFE0BC | I3: Логотип не меняет цвета при наведении | K3: macOS Tahoe 26.0.1 Разрешение: 3456 x 2234 Браузер: Chrome 142.0.7444.135 ОС: Windows 11 Разрешение: 2560х1600 Браузер: Яндекс. 25.8.5.890 OC: Windows 11 24H2 Разрешение: 1920х1080 Браузер: Opera 123.0.5669.47 Edge Windows 10 Версия 142.0.3595.65 Разрешение 1920х1080 | L3: Возможно, ошибка связана с некорректным применением стилей CSS для состояния hover.
A4: hm_pg_bg_3 | B4: Желательный | C4: Низкий | D4: Несоответствие цвета цифр в заголовке на карточке в блоке "Нужна помощь" на главной странице | E4: На макете для цвета цифр в заголовке указан #D89C66, но в DevTools отображается #efb46d | F4: Открыта главная страница сайта: https://pl.rassokha.pro:3001 | G4: Найти заголовок на карточке с сбором средств | H4: Цвет цифр в заголовке должен быть #D89C66 | I4: В DevTools отображается #efb46d | K4: macOS Tahoe 26.0.1 Разрешение: 3456 x 2234 Браузер: Chrome 142.0.7444.135 Разрешение: 1920х1080 Браузер: Opera 123.0.5669.47 ОС: Windows 11 Разрешение: 2560х1600 Браузер: Яндекс. 25.8.5.890 Edge Windows 10 Версия 142.0.3595.65 Разрешение 1920х1080 | L4: В DevTools неверно применен цвет для элемента
A5: hm_pg_bg_4 | B5: Желательный | C5: Низкий | D5: Вместо "Отчет о поступлениях (дата формирования отчета)" указана "Лента пожертвований" на главной странице в блоке "Нужна помощь" справа от карточки семьи | F5: Открыта главная страница сайта: https://pl.rassokha.pro:3001 | G5: 1. Найти блок "Нужна помощь" 2. Справа от карточки семьи блок с отчетом | H5: Наименование: "Отчет о поступлениях" и справа дата отчета | I5: Наименование: "Лента пожертвований" без даты | J5: hm_pg_bg_4.png | K5: OC: Windows 11 24H2 Разрешение: 1920х1080 Браузер: Opera 123.0.5669.47 macOS Tahoe 26.0.1 Разрешение: 3456 x 2234 Браузер: Chrome 142.0.7444.135 ОС: Windows 11 Разрешение: 2560х1600 Браузер: Яндекс. 25.8.5.890 Edge Windows 10 Версия 142.0.3595.65 Разрешение 1920х1080 | M5: Раскошная Анастасия
A6: hm_pg_bg_5 | B6: Высокий | C6: Высокий | D6: В блоке "Отчет о поступлениях" нет ссылки на все отчеты | F6: Открыта главная страница сайта: https://pl.rassokha.pro:3001 | G6: 1. Найти блок "Нужна помощь" 2. Справа от карточки семьи блок с отчетом | H6: Под списком благотворителей и суммами пожертвований есть ссылка на все отчеты "Посмотреть все отчеты →" | I6: Ссылки нет | J6: hm_pg_bg_5.png | K6: OC: Windows 11 24H2 Разрешение: 1920х1080 Браузер: Opera 123.0.5669.47 macOS Tahoe 26.0.1 Разрешение: 3456 x 2234 Браузер: Chrome 142.0.7444.135 ОС: Windows 11 Разрешение: 2560х1600 Браузер: Яндекс. 25.8.5.890 Edge Windows 10 Версия 142.0.3595.65 Разрешение 1920х1080 | M6: Раскошная Анастасия
A7: hm_pg_bg_6 | B7: Желательный | C7: Низкий | D7: В блоке "Помочь очень просто!" в графе "Email для квитанций" не указан плейсхолдер "Указать email" | F7: Открыта главная страница сайта: https://pl.rassokha.pro:3001 | G7: 1. Найти блок "Нужна помощь" 2. Справа от карточки семьи и ниже блока с отчетом | H7: В графе "Email для квитанций" указан плейсхолдер "Указать email" | I7: В графе "Email для квитанций" указан плейсхолдер "email" | J7: hm_pg_bg_6.png | K7: OC: Windows 11 24H2 Разрешение: 1920х1080 Браузер: Opera 123.0.5669.47 macOS Tahoe 26.0.1 Разрешение: 3456 x 2234 Браузер: Chrome 142.0.7444.135 ОС: Windows 11 Разрешение: 2560х1600 Браузер: Яндекс. 25.8.5.890 Edge Windows 10 Версия 142.0.3595.65 Разрешение 1920х1080 | M7: Раскошная Анастасия
A8: hm_pg_bg_7 | B8: Высокий | C8: Высокий | D8: На главной странице в блоке "Нужна помощь" под карточками семьи нет пагинации | F8: Открыта главная страница сайта: https://pl.rassokha.pro:3001 | G8: 1. Найти блок "Нужна помощь" 2. Под карточками семьи | H8: Под карточками семьи есть пагинация | I8: Под карточками семьи нет пагинации | J8: hm_pg_bg_7.png | K8: OC: Windows 11 24H2 Разрешение: 1920х1080 Браузер: Opera 123.0.5669.47 ОС: Windows 11 Разрешение: 2560х1600 Браузер: Яндекс. 25.8.5.890 macOS Tahoe 26.0.1 Разрешение: 3456 x 2234 Браузер: Chrome 142.0.7444.135 Edge Windows 10 Версия 142.0.3595.65 Разрешение 1920х1080 | M8: Раскошная Анастасия
A9: bt_fndtn_bg_1 | B9: Желательный | C9: Низкий | D9: На странице "О фонде" в блоке "Наша команда" у карточек "Директор", "Бухгалтер" и "Волонтер" не меняют режим при наведении курсора | F9: Открыта странице "О фонде" https://pl.rassokha.pro:3001/about | G9: 1, Найти блок "Наша команда" 2. Навести курсор на карточку "Директор", "Бухгалтер" или "Волонтер" | H9: Карточки имеют 2 состояния при наведении курсора "defaut, hover" | I9: Карточки не активны | K9: OC: Windows 11 24H2 Разрешение: 1920х1080 Браузер: Opera 123.0.5669.47 ОС: Windows 11 Разрешение: 2560х1600 Браузер: Яндекс. 25.8.5.890 Edge Windows 10 Версия 142.0.3595.65 Разрешение 1920х1080 | M9: Раскошная Анастасия
A10: bt_fndtn_bg_2 | B10: Желательный | C10: Низкий | D10: На странице "О фонде" в блоке "Наша команда" у карточки "Директор" задвоилась рамка вокруг фото | F10: Открыта странице "О фонде" https://pl.rassokha.pro:3001/about | G10: 1, Найти блок "Наша команда" 2. Обратить внимание на карточку "Директор" | H10: Фото в одинарной белой рамке | I10: Фото в двойной белой рамке | J10: bt_fndtn_bg_2.png | K10: OC: Windows 11 24H2 Разрешение: 1920х1080 Браузер: Opera 123.0.5669.47 ОС: Windows 11 Разрешение: 2560х1600 Браузер: Яндекс. 25.8.5.890 Edge Windows 10 Версия 142.0.3595.65 Разрешение 1920х1080 Edge Windows 10 Версия 142.0.3595.65 Разрешение 1920х1080 | M10: Раскошная Анастасия
A11: bt_fndtn_bg_3 | B11: Критический | C11: Высокий | D11: На странице "О фонде" нет блока "Учредительные документы" | F11: Открыта странице "О фонде" https://pl.rassokha.pro:3001/about | G11: 1. Найти блок "Нас поддерживают" | H11: Под блоком "Нас поддерживают" размещен блок "Учредтельные документы" | I11: Под блоком "Нас поддерживают" размещен сразу футер | J11: bt_fndtn_bg_3.png | K11: OC: Windows 11 24H2 Разрешение: 1920х1080 Браузер: Opera 123.0.5669.47 ОС: Windows 11 Разрешение: 2560х1600 Браузер: Яндекс. 25.8.5.890 Edge Windows 10 Версия 142.0.3595.65 Разрешение 1920х1080 | M11: Раскошная Анастасия
A12: gt_hlp_bg_1 | B12: Критический | C12: Высокий | D12: На странице "Получить помощь" поле ввода "Город" не имеет раскрывающегося списка | E12: По макету поле имеет раскрывающийся список | F12: Открыта страница "Получить помощь" https://pl.rassokha.pro:3001/get-help | G12: 1. Найти блок "Вам нужна помощь?" 2. Найти поле "Город" | H12: Поле "Город" имеет раскрывающийся список | I12: Поле "Город" не имеет раскрывающийся список | J12: gt_hlp_bg_1.png | K12: ОС: Windows 11 Разрешение: 2560х1600 Браузер: Яндекс. 25.8.5.890 OC: Windows 11 24H2 Разрешение: 1920х1080 Браузер: Opera 123.0.5669.47 Edge Windows 10 Версия 142.0.3595.65 Разрешение 1920х1080 | M12: Попов Денис
A13: gt_hlp_bg_2 | B13: Критический | C13: Высокий | D13: На странице "Получить помощь" в блоке "Список заявок" при выборе в поле "Город" любого города отображаются заявки из всех городов | F13: Открыта страница "Получить помощь" https://pl.rassokha.pro:3001/get-help | G13: 1. Найти блок "Список заявок" 2. В поле "Город" раскрыть выпадающий список 3. В списке выбрать любой город | H13: В блоке "Список заявок" при выборе в поле "Город" любого города отображаются заявки из этого города | I13: В блоке "Список заявок" при выборе в поле "Город" любого города отображаются заявки из всех городов | J13: gt_hlp_bg_2.png | K13: ОС: Windows 11 Разрешение: 2560х1600 Браузер: Яндекс. 25.8.5.890 OC: Windows 11 24H2 Разрешение: 1920х1080 Браузер: Opera 123.0.5669.47 Edge Windows 10 Версия 142.0.3595.65 Разрешение 1920х1080 | M13: Попов Денис
A14: gt_hlp_bg_3 | B14: Высокий | C14: Средний | D14: На странице "Получить помощь" в блоке "Список заявок" в поле "Город" в раскрывающемся списке нет пустого поля (сверху спсика) для сброса выбранного поля | F14: Открыта страница "Получить помощь" https://pl.rassokha.pro:3001/get-help | G14: 1. Найти блок "Список заявок" 2. В поле "Город" раскрыть выпадающий список | H14: В блоке "Список заявок" при выборе в поле "Город" в раскрывающемся списке есть пустое поле (сверху спсика) для сброса выбранного поля | I14: В блоке "Список заявок" при выборе в поле "Город" в раскрывающемся списке нет пустого поля (сверху спсика) для сброса выбранного поля | J14: gt_hlp_bg_3.png | K14: ОС: Windows 11 Разрешение: 2560х1600 Браузер: Яндекс. 25.8.5.890 OC: Windows 11 24H2 Разрешение: 1920х1080 Браузер: Opera 123.0.5669.47 Edge Windows 10 Версия 142.0.3595.65 Разрешение 1920х1080 | M14: Попов Денис
A15: gt_hlp_bg_4 | B15: Стандартный | C15: Низкий | D15: На странице "Получить помощь" в блоке "Список заявок" текст на кнопке - "ПОКАЗАТЬ ЕЩЕ" | F15: Открыта страница "Получить помощь" https://pl.rassokha.pro:3001/get-help | G15: 1. Найти блок "Список заявок" 2. Найти кнопку "Показать еще" | H15: В блоке "Список заявок" текст на кнопке - "ПОКАЗАТЬ ЕЩЕ" | I15: В блоке "Список заявок" текст на кнопке - "Показать еще" | J15: gt_hlp_bg_4.png | K15: ОС: Windows 11 Разрешение: 2560х1600 Браузер: Яндекс. 25.8.5.890 OC: Windows 11 24H2 Разрешение: 1920х1080 Браузер: Opera 123.0.5669.47 Edge Windows 10 Версия 142.0.3595.65 Разрешение 1920х1080 | M15: Попов Денис
A16: gt_hlp_bg_5 | B16: Стандартный | C16: Низкий | D16: На странице "Получить помощь" в блоке "Часто задаваемые вопросы" при раскрытии вопроса внутри ответов нет кликабельных ссылок | F16: Открыта страница "Получить помощь" https://pl.rassokha.pro:3001/get-help | G16: 1. Найти блок "Часто задаваемые вопросы" 2. Кликнуть на вопрос | H16: При раскрытии вопроса внутри ответов есть кликабельные ссылки | I16: При раскрытии вопроса внутри ответов нет кликабельных ссылок | J16: gt_hlp_bg_5.png | K16: ОС: Windows 11 Разрешение: 2560х1600 Браузер: Яндекс. 25.8.5.890 Edge Windows 10 Версия 142.0.3595.65 Разрешение 1920х1080 | M16: Попов Денис
A17: vlntr_bg_1 | B17: Критический | C17: Высокий | D17: На странице "Стать волонтером" в блоке "Анкета волонтера" поле ввода "Город" не имеет раскрывающегося списка | E17: По макету поле имеет раскрывающийся список | F17: Открыта страница "Стать волонтером" https://pl.rassokha.pro:3001/volunteer-applications | G17: 1. Найти блок "Анкета волонтера" 2. Найти поле "Город" | H17: Поле "Город" имеет раскрывающийся список | I17: Поле "Город" не имеет раскрывающийся список | J17: vlntr_bg_1.pgn | K17: ОС: Windows 11 Разрешение: 2560х1600 Браузер: Яндекс. 25.8.5.890 OC: Windows 11 24H2 Разрешение: 1920х1080 Браузер: Opera 123.0.5669.47 Edge Windows 10 Версия 142.0.3595.65 Разрешение 1920х1080 | M17: Попов Денис
A18: vlntr_bg_2 | B18: Стандартный | C18: Низкий | D18: На странице "Стать волонтером" в блоке "Часто задаваемые вопросы" при раскрытии вопроса внутри ответов нет кликабельных ссылок | F18: Открыта страница "Стать волонтером" https://pl.rassokha.pro:3001/volunteer-applications | G18: 1. Найти блок "Часто задаваемые вопросы" 2. Кликнуть на вопрос | H18: При раскрытии вопроса внутри ответов есть кликабельные ссылки | I18: При раскрытии вопроса внутри ответов нет кликабельных ссылок | J18: vlntr_bg_2.png | K18: ОС: Windows 11 Разрешение: 2560х1600 Браузер: Яндекс. 25.8.5.890 Edge Windows 10 Версия 142.0.3595.65 Разрешение 1920х1080 | M18: Попов Денис
A19: dcmnts_bg_1 | B19: Желательный | C19: Низкий | D19: Некорректный порядок документов в галерее под заголовком "Документы" на странице документов | E19: По макету документы фонда должны отображаться слева направо в порядке: 1) Свидетельство о государственной регистрации коммерческих организаций, 2) Свидетельство о постановке на учет в налоговом органе, 3) Лист записи ЕГРЮЛ. Фактически порядок другой: первым отображается Лист записи ЕГРЮЛ, затем остальные документы | F19: Открыта страница "Документы" https://pl.rassokha.pro:3001/documents | G19: Проверить порядок документов в галерее | H19: Документы отображаются в соответствии с макетом в Figma: слева направо в порядке: 1) Свидетельство о государственной регистрации коммерческих организаций, 2) Свидетельство о постановке на учет в налоговом органе, 3) Лист записи ЕГРЮЛ | I19: Документы отображаются : слева направо в порядке: 1) Лист записи ЕГРЮЛ, 2) Свидетельство о государственной регистрации коммерческих организаций, 3) Свидетельство о постановке на учет в налоговом органе | J19: dcmnts_bg_1.png | K19: macOS Tahoe 26.0.1 Разрешение: 3456 x 2234 Браузер: Chrome 142.0.7444.135 OC: Windows 11 24H2 Разрешение: 1920х1080 Браузер: Opera 123.0.5669.47 Edge Windows 10 Версия 142.0.3595.65 Разрешение 1920х1080 | L19: Вероятно, в данных нарушена сортировка или порядок вывода элементов. Функциональность не нарушена, проблема только в соответствии макету
A20: hdr_bg_1 | B20: Стандартный | C20: Средний | D20: Некорректный переход по ссылке «Кому помочь» в хедере | E20: При клике по пункту меню «Кому помочь» происходит переход на главную страницу, но пользователь попадает в блок «Нужна помощь!». | F20: Открыта страница сайта "О фонде" https://pl.rassokha.pro:3001/about | G20: В верхнем меню нажать на ссылку «Кому помочь» | H20: При клике на раздел "Кому помочь" переход на главную страницу в раздел "Нужна помощь!" | I20: При клике на раздел "Кому помочь" переход на главную страницу в раздел "Вы помогли этим детям" | J20: hdr_bg_1.mov | K20: macOS Tahoe 26.0.1 Разрешение: 3456 x 2234 Браузер: Chrome 142.0.7444.135 OC: Windows 11 24H2 Разрешение: 1920х1080 Браузер: Opera 123.0.5669.47 Edge Windows 10 Версия 142.0.3595.65 Разрешение 1920х1080 | L20: У ссылки прописан неверный якорь, либо скрипт прокрутки работает некорректно; Требуется проверка ссылок и обработчиков навигации
A21: pbl_blg_bg_1 | B21: Стандартный | C21: Средний | D21: На странице "Публикации блога" под заголовком блока на правом краю блока справа от даты нет ссылки на мессенджер Вайбер | F21: Открыта страница "Публикация блога" https://pl.rassokha.pro:3001/blog/5 | G21: Справа от названия блока найти ссылки на мессенджеры | H21: На странице "Публикация блога" имеется ссылки на мессенджеры ТГ, ВК и WA | I21: На странице "Публикации блога" нет ссылки на мессенджер Вайбер | J21: pbl_blg_bg_1.png | K21: ОС: Windows 11 Разрешение: 2560х1600 Браузер: Яндекс. 25.8.5.890 macOS Tahoe 26.0.1 Разрешение: 3456 x 2234 Браузер: Chrome 142.0.7444.135 OC: Windows 11 24H2 Разрешение: 1920х1080 Браузер: Opera 123.0.5669.47 Edge Windows 10 Версия 142.0.3595.65 Разрешение 1920х1080 | M21: Попов Денис
A22: ftr_bg_1 | B22: Стандартный | C22: Средний | D22: Отсутствие ссылок на "Telegram" и "YouTube" в футере | F22: Открыт футер на любой странице сайта | G22: Найти блок с иконками соцсетей в правой части футера | H22: Все 4 ссылки на соцсети отображаются: Telegram, YouTube, Вконтакте, Одноклассники | I22: Ссылки на Telegram и YouTube отсутствуют | J22: ftr_bg_1.png | K22: macOS Tahoe 26.0.1 Разрешение: 3456 x 2234 Браузер: Chrome 142.0.7444.135 OC: Windows 11 24H2 Разрешение: 1920х1080 Браузер: Opera 123.0.5669.47 | L22: Возможно устарел макет и ссылки на телеграмм и ютуб не требуются (ютуб запрещен в РФ)
A23: ftr_bg_2 | B23: Высокий | C23: Высокий | D23: Отсутствует раздел «Обратная связь» в футере | F23: Открыт футер на любой странице сайта | G23: Найти раздел "Обратная связь" | H23: Раздел "Обратная связь" отображается в футере | I23: Раздел полностью отсутствует | J23: ftr_bg_2.png | K23: macOS Tahoe 26.0.1 Разрешение: 3456 x 2234 Браузер: Chrome 142.0.7444.135 OC: Windows 11 24H2 Разрешение: 1920х1080 Браузер: Opera 123.0.5669.47
A24: dtls_bg_1 | B24: Желательный | C24: Низкий | D24: На странице "Реквизиты" заголовок блока с текстом "Реквизиты благотворительного фонда "Помоги Лично"" расположен посередине страницы | F24: Открыть страницу "Реквизиты" https://pl.rassokha.pro:3001/requisites | G24: Найти заголовок "Реквизиты благотворительного фонда "Помоги Лично" | H24: Заголовок блока с текстом "Реквизиты благотворительного фонда "Помоги Лично"" расположен слева над областью с реквизитами | I24: Заголовок блока с текстом "Реквизиты благотворительного фонда "Помоги Лично"" расположен посередине страницы над областью с реквизитами | J24: dtls_bg_1.png | K24: ОС: Windows 11 Разрешение: 2560х1600 Браузер: Яндекс. 25.8.5.890 | M24: Попов Денис
A25: dtls_bg_2 | B25: Стандартный | C25: Средний | D25: На странице "Реквизиты" под ссылкой "Скачать реквизиты благотворительного фонда "Помоги Лично"" отсутствуют ссылки на "Telegram" и "YouTube" | F25: Открыть страницу "Реквизиты" https://pl.rassokha.pro:3001/requisites | G25: Найти блок со ссылками на мессенджеры | H25: Все 4 ссылки на соцсети отображаются: Telegram, YouTube, Вконтакте, Одноклассники | I25: Ссылки на Telegram и YouTube отсутствуют | J25: dtls_bg_2.png | K25: ОС: Windows 11 Разрешение: 2560х1600 Браузер: Яндекс. 25.8.5.890 OC: Windows 11 24H2 Разрешение: 1920х1080 Браузер: Opera 123.0.5669.47 | M25: Попов Денис
A26: fml_pg_bttn_bg_1 | B26: Стандартный | C26: Средний | D26: На странице "Семья (кнопка помочь)" карточка "Быстрый способ помочь" расположена под блоком "Фамилия семьи" | F26: Открыть страницу "Семья (кнопка помочь)" https://pl.rassokha.pro:3001/family_request | G26: Найти карточку "Быстрый способ помочь" | H26: Справой стороны от блока "Фамилия семьи" расположена карточка "Быстрый способ помочь" | I26: Карточка "Быстрый способ помочь" расположена под блоком "Фамилия семьи" | J26: fml_pg_bttn_bg_1.png | K26: ОС: Windows 11 Разрешение: 2560х1600 Браузер: Яндекс. 25.8.5.890 | M26: Попов Денис
A27: fml_pg_bttn_bg_2 | B27: Высокий | C27: Средний | D27: На странице "Семья (кнопка помочь)" справа от заголовка "Помочь ребенку!" расположены три кнопки "Онлайн, Реквизиты, Помочь лично" | F27: Открыть страницу "Семья (кнопка помочь)" https://pl.rassokha.pro:3001/family_request | G27: Найти блок "Помочь ребенку!" | H27: Справа от заголовка "Помочь ребенку!" расположены две кнопки "Онлайн, Реквизиты" | I27: Справа от заголовка "Помочь ребенку!" расположены три кнопки "Онлайн, Реквизиты, Помочь лично" | J27: fml_pg_bttn_bg_2.png | K27: ОС: Windows 11 Разрешение: 2560х1600 Браузер: Яндекс. 25.8.5.890 | M27: Попов Денис
A28: fml_pg_bttn_bg_3 | B28: Желательный | C28: Низкий | D28: На странице "Семья (кнопка помочь)" в блоке "Помочь ребенку!" под 2 radio buttom "Хочу помогать ОДНОКРАТНО" "Хочу помогать ЕЖЕМЕСЯЧНО" расположен заголовок "3. Ваши данные" | F28: Открыть страницу "Семья (кнопка помочь)" https://pl.rassokha.pro:3001/family_request | G28: Найти блок "Помочь ребенку!" | H28: Под 2 radio buttom "Хочу помогать ОДНОКРАТНО" "Хочу помогать ЕЖЕМЕСЯЧНО" расположен заголовок "3. Ваш комментарий (отражается в ленте пожертвований)" | I28: Под 2 radio buttom "Хочу помогать ОДНОКРАТНО" "Хочу помогать ЕЖЕМЕСЯЧНО" расположен заголовок "3. Ваши данные" | J28: fml_pg_bttn_bg_3.png | K28: ОС: Windows 11 Разрешение: 2560х1600 Браузер: Яндекс. 25.8.5.890 OC: Windows 11 24H2 Разрешение: 1920х1080 Браузер: Opera 123.0.5669.47 | M28: Попов Денис
A29: fml_pg_bttn_bg_4 | B29: Высокий | C29: Средний | D29: На странице "Семья (кнопка помочь)" в блоке "Помочь ребенку!" под заголовком "3. Ваши данные" расположено два поля ввода "Имя, Email" | F29: Открыть страницу "Семья (кнопка помочь)" https://pl.rassokha.pro:3001/family_request | G29: Найти блок "Помочь ребенку!" | H29: Под заголовком "3. Ваш комментарий (отражается в ленте пожертвований)" расположено три поля ввода "Ваше имя, Email, Ваши комментарии и пожелания" | I29: Под заголовком "3. Ваши данные" расположено два поля ввода "Имя, Email" | J29: fml_pg_bttn_bg_4.png | K29: ОС: Windows 11 Разрешение: 2560х1600 Браузер: Яндекс. 25.8.5.890 OC: Windows 11 24H2 Разрешение: 1920х1080 Браузер: Opera 123.0.5669.47 | M29: Попов Денис
A30: fml_pg_bttn_bg_5 | B30: Желательный | C30: Низкий | D30: На странице "Семья (кнопка помочь)" в блоке "Помочь ребенку!" под заголовком "3. Ваши данные" первое поле ввода имеет плейсхолдер "Имя" | F30: Открыть страницу "Семья (кнопка помочь)" https://pl.rassokha.pro:3001/family_request | G30: Найти блок "Помочь ребенку!" | H30: Под заголовком "3. Ваш комментарий (отражается в ленте пожертвований)" расположено три поля ввода "Ваше имя, Email, Ваши комментарии и пожелания" | I30: Под заголовком "3. Ваши данные" первое поле ввода имеет плейсхолдер "Имя" | J30: fml_pg_bttn_bg_5.png | K30: ОС: Windows 11 Разрешение: 2560х1600 Браузер: Яндекс. 25.8.5.890 OC: Windows 11 24H2 Разрешение: 1920х1080 Браузер: Opera 123.0.5669.47 | M30: Попов Денис
A31: fml_pg_bttn_bg_6 | B31: Желательный | C31: Низкий | D31: На странице "Семья (кнопка помочь)" в блоке "Помочь ребенку!" под полями ввода "Имя" и "Email" расположен заголовок "Итоговая сумма: 2500 ₽" | F31: Открыть страницу "Семья (кнопка помочь)" https://pl.rassokha.pro:3001/family_request | G31: Найти блок "Помочь ребенку!" | H31: Под полем ввода "Ваши комментарии и пожелания" расположен заголовок "Итоговая сумма пожертвования: 2500 ₽" | I31: Под полями ввода "Имя" и "Email" расположен заголовок "Итоговая сумма: 2500 ₽" | J31: fml_pg_bttn_bg_6.png | K31: ОС: Windows 11 Разрешение: 2560х1600 Браузер: Яндекс. 25.8.5.890 OC: Windows 11 24H2 Разрешение: 1920х1080 Браузер: Opera 123.0.5669.47 | M31: Попов Денис
A32: fml_pg_ bttn_bg_7 | B32: Желательный | C32: Низкий | D32: Используемый цвет цифр в заголовке собранных средств на странице семьи #efb46d вместо #D89C66 | F32: Открыть страницу "Семья (кнопка помочь)" https://pl.rassokha.pro:3001/family_request | G32: 1. Найти заголовок шкалы сбора средств 2. В девтулс проверить код цвета элемента | H32: Используемый цвет цифр в заголовке собранных средств на странице семьи #D89C66 | I32: Используемый цвет цифр в заголовке собранных средств на странице семьи #efb46d | K32: macOS Tahoe 26.0.1 Разрешение: 3456 x 2234 Браузер: Chrome 142.0.7444.135
A33: fml_pg_ bttn_bg_8 | B33: Высокий | C33: Высокий | D33: На странице "Семья (кнопка помочь)" в блоке "Помочь ребенку!" под заголовком "Итоговая сумма: 2500 ₽" расположена одна кнопка "Пожертвовать" | F33: Открыть страницу "Семья (кнопка помочь)" https://pl.rassokha.pro:3001/family_request | G33: Найти блок "Помочь ребенку!" | H33: Под заголовком "Итоговая сумма: 2500 ₽" расположены две кнопки "Пожертвовать" и "Счет для юр. лиц" | I33: Под заголовком "Итоговая сумма: 2500 ₽" расположена одна кнопка "Пожертвовать" | J33: fml_pg_ bttn_bg_8.png | K33: ОС: Windows 11 Разрешение: 2560х1600 Браузер: Яндекс. 25.8.5.890 | M33: Попов Денис
A34: fml_pg_ bttn_bg_9 | B34: Желательный | C34: Низкий | D34: На странице "Семья (кнопка помочь)" в блоке "Помочь ребенку!" при нажатой кнопке "Реквизиты" под заголовком "1. Реквизиты для перевода" вертикально расположены названия реквизитов "Организация, ИНН, КПП, ОГРН/ОГРНИП, Расчётный счёт, БИК, Банк, Корр. счёт, Назначение платежа" | F34: Открыть страницу "Семья (кнопка помочь)" https://pl.rassokha.pro:3001/family_request | G34: 1. Найти блок "Помочь ребенку!" 2. Нажать кнопку "Реквизиты" | H34: Под заголовком "1. Реквизиты для перевода" вертикально расположены названия реквизитов "Банк, БИК, Кор. счет, Получатель, Расчетный счет, ИНН, КПП, Назначение платежа" | I34: Под заголовком "1. Реквизиты для перевода" вертикально расположены названия реквизитов "Организация, ИНН, КПП, ОГРН/ОГРНИП, Расчётный счёт, БИК, Банк, Корр. счёт, Назначение платежа" | J34: fml_pg_ bttn_bg_9.png | K34: ОС: Windows 11 Разрешение: 2560х1600 Браузер: Яндекс. 25.8.5.890 | M34: Попов Денис
A35: fml_pg_ bttn_bg_10 | B35: Высокий | C35: Высокий | D35: Отсутствуют радиокнопки выбора банка/способа оплаты в карточке "Быстрый способ помочь" | E35: В карточке "Быстрый способ помочь" по макету должны отображаться радиокнопки с выбором банков и способов оплаты | F35: Открыть страницу "Семья (кнопка помочь)" https://pl.rassokha.pro:3001/family_request | G35: Найти карточку "Быстрый способ помочь" | H35: Радиокнопки с выбором банков и способов оплаты отображаются над зоголовком карточки | I35: Радиокнопки отсутствуют | J35: fml_pg_ bttn_bg_10.png | K35: macOS Tahoe 26.0.1 Разрешение: 3456 x 2234 Браузер: Chrome 142.0.7444.135
A36: fml_pg_ bttn_bg_11 | B36: Высокий | C36: Высокий | D36: На странице "Семья (кнопка помочь)" в блоке "Помочь ребенку!" при нажатой кнопке "Реквизиты" справа от реквизитов расположена одна кнопка "скачать реквизиты" | F36: Открыть страницу "Семья (кнопка помочь)" https://pl.rassokha.pro:3001/family_request | G36: 1. Найти блок "Помочь ребенку!" 2. Нажать кнопку "Реквизиты" | H36: Справа от реквизитов расположены две кнопки "Скачать реквизиты" и "Счет для юр. лиц" | I36: Справа от реквизитов расположена одна кнопка "Скачать реквизиты" | J36: fml_pg_ bttn_bg_11.png | K36: ОС: Windows 11 Разрешение: 2560х1600 Браузер: Яндекс. 25.8.5.890 OC: Windows 11 24H2 Разрешение: 1920х1080 Браузер: Opera 123.0.5669.47 | M36: Попов Денис
A37: fml_pg_ bttn_bg_12 | B37: Высокий | C37: Средний | D37: На странице "Семья (кнопка помочь)" карточка "Им тоже нужна помощь" расположена над блоком "Помочь ребенку" | F37: Открыть страницу "Семья (кнопка помочь)" https://pl.rassokha.pro:3001/family_request | G37: Найти карточку "Им тоже нужна помощь" | H37: Карточка "Им тоже нужна помощь" расположена справа от блока "Помочь ребенку" | I37: Карточка "Им тоже нужна помощь" расположена над блоком "Помочь ребенку" | J37: fml_pg_ bttn_bg_12.png | K37: ОС: Windows 11 Разрешение: 2560х1600 Браузер: Яндекс. 25.8.5.890 | M37: Попов Денис
A38: fml_pg_ bttn_bg_13 | B38: Высокий | C38: Высокий | D38: На странице "Семья (кнопка помочь)" под блоком "Помочь ребенку!" расположен блок с заголовком "История" | F38: Открыть страницу "Семья (кнопка помочь)" https://pl.rassokha.pro:3001/family_request | G38: Найти блок "История" | H38: Под блоком "Помочь ребенку!" расположены три блока с заголовками "История", "Документы", "Новости" | I38: Под блоком "Помочь ребенку!" расположен один блок с заголовком "История" | J38: fml_pg_ bttn_bg_13.png | K38: ОС: Windows 11 Разрешение: 2560х1600 Браузер: Яндекс. 25.8.5.890 OC: Windows 11 24H2 Разрешение: 1920х1080 Браузер: Opera 123.0.5669.47 | M38: Попов Денис
A39: fml_pg_ bttn_bg_14 | B39: Стандартный | C39: Средний | D39: На странице "Семья (кнопка помочь)" справа от блока "История" в списке ссылок на мессенджеры отсутсвует ссылка на Вайбер | F39: Открыть страницу "Семья (кнопка помочь)" https://pl.rassokha.pro:3001/family_request | G39: Найти блок "История" | H39: Справа от блока "История" расположены ссылки на мессенджеры ТГ, ВК и WA | I39: Справа от блока "История" в списке ссылок на мессенджеры отсутсвует ссылка на Вайбер | J39: fml_pg_ bttn_bg_14.png | K39: ОС: Windows 11 Разрешение: 2560х1600 Браузер: Яндекс. 25.8.5.890 OC: Windows 11 24H2 Разрешение: 1920х1080 Браузер: Opera 123.0.5669.47 | M39: Попов Денис
A40: fml_pg_ bttn_bg_15 | B40: Высокий | C40: Высокий | D40: На странице "Семья (кнопка помочь)", под блоком "История" находится блок для оставления комментария "Ваш комментарий или пожелания" | F40: Открыть страницу "Семья (кнопка помочь)" https://pl.rassokha.pro:3001/family_request | G40: Найти блок "История" | H40: Под блоком "История" находится блок "Нуждаются в помощи" | I40: Под блоком "История" находится блок для оставления комментария "Ваш комментарий или пожелания" | J40: fml_pg_ bttn_bg_15.png | K40: ОС: Windows 11 Разрешение: 2560х1600 Браузер: Яндекс. 25.8.5.890 OC: Windows 11 24H2 Разрешение: 1920х1080 Браузер: Opera 123.0.5669.47 | M40: Попов Денис
A41: fml_pg_ bttn_bg_16 | B41: Желательный | C41: Низкий | D41: На странице "Семья (кнопка помочь)", под блоком "История" находится блок для оставления комментария "Ваш комментарий или пожелания" | F41: Открыть страницу "Семья (кнопка помочь)" https://pl.rassokha.pro:3001/family_request | G41: Найти блок "История" | H41: Под блоком "История" находится блок "Ваш комментарий или пожелания (отражается в карточке ребенка)" | I41: Под блоком "История" находится блок для оставления комментария "Ваш комментарий или пожелания" | J41: fml_pg_ bttn_bg_16.png | K41: ОС: Windows 11 Разрешение: 2560х1600 Браузер: Яндекс. 25.8.5.890 OC: Windows 11 24H2 Разрешение: 1920х1080 Браузер: Opera 123.0.5669.47 | M41: Попов Денис
A42: cntcts_bg_1 | B42: Стандартный | C42: Средний | D42: На странице "Контакты" не активна иконка "наш адрес" | F42: Открыта страница "Контакты" https://pl.rassokha.pro:3001/contacts | G42: Найти блок с иконками контактов | H42: 1. При клике на иконку "Наш адрес" на карте появляется иконка "наш адрес". 2. Иконка имет 2 состояния "default", "hover". 3. При наведении курсора на иконку меняется цвет векторного рисунка с белого в зеленый | I42: 1. При клике на иконку "Наш адрес" ничего не происходит. 2. Иконка не имеет 2 состояния "default", "hover". 3. При наведении курсора на иконку цвет не меняется | K42: OC: Windows 11 24H2 Разрешение: 1920х1080 Браузер: Opera 123.0.5669.47 | M42: Раскошная Анастасия
A43: wh_hlpd_bg_1 | B43: Стандартный | C43: Средний | D43: На странице "Кому помогли" под блоком карточек "Получатель помощи" нет пагинации | F43: Открыта страница "Кому помогли" https://pl.rassokha.pro:3001/whom-we-helped | G43: Найти блок карточек "Получатель помощи" | H43: Под блоком карточек "Получатель помощи" расположен блок пагинации "Навигация страницы" | I43: Под блоком карточек "Получатель помощи" нет блока пагинации "Навигация страницы" | K43: OC: Windows 11 24H2 Разрешение: 1920х1080 Браузер: Opera 123.0.5669.47 | M43: Раскошная Анастасия
A44: fml_pg_ bttn_bg_17 | B44: Желательный | C44: Низкий | D44: На странице "Семья (кнопка помочь)", под блоком "История" в блоке для оставления комментария "Ваш комментарий или пожелания" третье поле ввода имеет плейсхолдер "Ваши комментарии" | F44: Открыть страницу "Семья (кнопка помочь)" https://pl.rassokha.pro:3001/family_request | G44: Найти блок "Ваш комментарий или пожелания" | H44: В блоке для оставления комментария "Ваш комментарий или пожелания" третье поле ввода имеет плейсхолдер "Ваши комментарии и пожелания" | I44: В блоке для оставления комментария "Ваш комментарий или пожелания" третье поле ввода имеет плейсхолдер "Ваши комментарии" | J44: fml_pg_ bttn_bg_17.png | K44: ОС: Windows 11 Разрешение: 2560х1600 Браузер: Яндекс. 25.8.5.890 OC: Windows 11 24H2 Разрешение: 1920х1080 Браузер: Opera 123.0.5669.47 | M44: Попов Денис
A45: sk_qstn_bg_1 | B45: Высокий | C45: Высокий | D45: Кнопка "Задать вопрос" не работает при некорректно заполненных полях на странице "Получить помощь" | E45: На странице "Получить помощь" кнопка "Задать вопрос" должна работать независимо от корректности заполнения формы, так как не связана с обработкой этих полей. | F45: Открыта страница "Получить помощь" https://pl.rassokha.pro:3001/get-help | G45: 1. В поля формы "Вам нужна помощь?" ввести некорректные данные 2. Нажать кнопку "Задать вопрос" в блоке "Часто задаваемые вопросы" | H45: Кнопка "Задать вопрос" работает всегда, независимо от состояния полей формы | I45: Кнопка не работает | J45: sk_qstn_bg_1.mov | K45: macOS Tahoe 26.0.1 Разрешение: 3456 x 2234 Браузер: Chrome 142.0.7444.135 OC: Windows 11 24H2 Разрешение: 1920х1080 Браузер: Opera 123.0.5669.47
A46: gt_hlp_bg_6 | B46: Стандартный | C46: Средний | D46: На странице "Получить помощь" в блоке "Список заявок" столбец города с большим количеством смволов (более 30) сдвигает вправо остальные столбцы | F46: Открыта страница "Получить помощь" https://pl.rassokha.pro:3001/get-help | G46: 1. найти блок "Список заявок" 2. нажимать на кнопку "показать еще" пока не откроется 71 -я заявка с городом "ПетровПетровПетровПетровПетровПетровПетровПетровПетровПетровПетровПетровПетровПетровПетровПетровПетр" | H46: Во втором столбце "ГОРОД" при поступлении длинного наименования города текст не выходит за границы ячейки, не обрезается и не сдвигает остальные столбцы | I46: Столбец "Город" сдвигает столбцы | J46: gt_hlp_bg_6.png | K46: OC: Windows 11 24H2 Разрешение: 1920х1080 Браузер: Opera 123.0.5669.47 | M46: Раскошная Анастасия
A47: sk_qstn_bg_2 | B47: Стандартный | C47: Средний | D47: Отсутствует кнопка закрытия ("крестик") в форме "Задать вопрос" | F47: Открыта страница с формой "Задать вопрос" https://pl.rassokha.pro:3001/frequent-questions | G47: Найти форму "Задать вопрос" | H47: В форме отображается иконка закрытия ("крестик") | I47: Иконка закрытия отсутствует | J47: sk_qstn_bg_2.png | K47: macOS Tahoe 26.0.1 Разрешение: 3456 x 2234 Браузер: Chrome 142.0.7444.135 OC: Windows 11 24H2 Разрешение: 1920х1080 Браузер: Opera 123.0.5669.47
A48: sk_qstn_bg_3 | B48: Желательный | C48: Низкий | D48: Некорректное название поля ввода сообщения в форме "Задать вопрос" | F48: Открыта страница с формой "Задать вопрос" https://pl.rassokha.pro:3001/frequent-questions | G48: 1. Найти форму "Задать вопрос" 2. Проверить наименование поля ввода сообщения | H48: Название поля ввода "Оставьте сообщение" | I48: Название поля ввода "Оставьте вопрос" | J48: sk_qstn_bg_3.png | K48: macOS Tahoe 26.0.1 Разрешение: 3456 x 2234 Браузер: Chrome 142.0.7444.135 OC: Windows 11 24H2 Разрешение: 1920х1080 Браузер: Opera 123.0.5669.47
A49: gt_hlp_bg_7 | B49: Критический | C49: Высокий | D49: На странице "Получить помощь" в блоке "Список заявок" при повторном нажатии активной кнопки "Получено" фильтр не сбрасывается | F49: Открыта страница "Получить помощь" https://pl.rassokha.pro:3001/get-help | G49: 1. найти блок "Список заявок" 2. кликнуть на "Получено" 3. после того, как список сформируется, кликнуть повторно на "Получено" | H49: При повторном нажатии на активную кнопку "ПОЛУЧЕНО" статус фильтра в таблице сбрасывается | I49: фильтр остался тот же | K49: OC: Windows 11 24H2 Разрешение: 1920х1080 Браузер: Opera 123.0.5669.47 | M49: Раскошная Анастасия
A50: gt_hlp_bg_8 | B50: Критический | C50: Высокий | D50: На странице "Получить помощь" в блоке "Список заявок" при повторном нажатии активной кнопки "Обработано" фильтр не сбрасывается | F50: Открыта страница "Получить помощь" https://pl.rassokha.pro:3001/get-help | G50: 1. найти блок "Список заявок" 2. кликнуть на "Обработано" 3. после того, как список сформируется, кликнуть повторно на "Обработано" | H50: При повторном нажатии на активную кнопку "Обработано" статус фильтра в таблице сбрасывается | I50: фильтр остался тот же | K50: OC: Windows 11 24H2 Разрешение: 1920х1080 Браузер: Opera 123.0.5669.47 | M50: Раскошная Анастасия
A51: gt_hlp_bg_9 | B51: Критический | C51: Высокий | D51: На странице "Получить помощь" в блоке "Список заявок" при выборе "Получено" и выборе "Города" не срабатывает фильтрация по городу | F51: Открыта страница "Получить помощь" https://pl.rassokha.pro:3001/get-help | G51: 1. найти блок "Список заявок" 2. кликнуть на "Получено" 3. кликнуть на "Город" и выбрать город | H51: При одновременно активных кнопках "Получено" и "Город" таблица отображает только заявки из выбранного города с статусом "В обработке" | I51: фильтр по городам срабатывает только, если сначала выбрать город затем кликнуть "Получено" | K51: OC: Windows 11 24H2 Разрешение: 1920х1080 Браузер: Opera 123.0.5669.47
A52: gt_hlp_bg_10 | B52: Критический | C52: Высокий | D52: На странице "Получить помощь" в блоке "Список заявок" при выборе "Обработано" и выборе "Города" не срабатывает фильтрация по городу | F52: Открыта страница "Получить помощь" https://pl.rassokha.pro:3001/get-help | G52: Логотип на карточке с фото в блоке "Нужна помощь!" на главной странице не соответствует состоянию hover | H52: По макетам лого должно менять цвет при наведении (hover) | I52: Открыта главная страница сайта: https://pl.rassokha.pro:3001 | K52: OC: Windows 11 24H2 Разрешение: 1920х1080 Браузер: Opera 123.0.5669.47
A53: vlntr_bg_3 | B53: Желательный | C53: Низкий | D53: На странице "Стать волонтером" в блоке "Анкета волонтера" в поле для фото нет плейсхолдера "Ссылка на вашу фотографию" | F53: Открыта страница "Стать волонтером" https://pl.rassokha.pro:3001/volunteer-applications | G53: Несоответствие цвета цифр в заголовке на карточке в блоке "Нужна помощь" на главной странице | H53: На макете для цвета цифр в заголовке указан #D89C66, но в DevTools отображается #efb46d | I53: Открыта главная страница сайта: https://pl.rassokha.pro:3001 | K53: OC: Windows 11 24H2 Разрешение: 1920х1080 Браузер: Opera 123.0.5669.47
A54: ftr_bg_3 | B54: Желательный | C54: Низкий | D54: В футере названием раздела указан "Отчеты" вместо "Отчет Фонда" | F54: Открыта главная страница сайта: https://pl.rassokha.pro:3001 | G54: Вместо "Отчет о поступлениях (дата формирования отчета)" указана "Лента пожертвований" на главной странице в блоке "Нужна помощь" справа от карточки семьи | I54: Открыта главная страница сайта: https://pl.rassokha.pro:3001 | J54: ftr_bg_3.png | K54: OC: Windows 11 24H2 Разрешение: 1920х1080 Браузер: Opera 123.0.5669.47
A55: sk_qstn_bg_4 | B55: Желательный | C55: Низкий | D55: В блоке "Задать вопрос" графа для заполнения номера телефона названа "Телефон" вместо "Номер телефона" | F55: Открыта страница "Задать вопрос" https://pl.rassokha.pro:3001/frequent-questions | G55: В блоке "Отчет о поступлениях" нет ссылки на все отчеты | I55: Открыта главная страница сайта: https://pl.rassokha.pro:3001 | J55: sk_qstn_bg_4.png | K55: OC: Windows 11 24H2 Разрешение: 1920х1080 Браузер: Opera 123.0.5669.47
A56: sk_qstn_bg_5 | B56: Критический | C56: Высокий | D56: В блоке "Задать вопрос" нет выпадающего списка в графе "Город" | F56: Открыта страница "Задать вопрос" https://pl.rassokha.pro:3001/frequent-questions | G56: В блоке "Помочь очень просто!" в графе "Email для квитанций" не указан плейсхолдер "Указать email" | I56: Открыта главная страница сайта: https://pl.rassokha.pro:3001 | J56: sk_qstn_bg_4.png | K56: OC: Windows 11 24H2 Разрешение: 1920х1080 Браузер: Opera 123.0.5669.47
A57: fml_pg_ bttn_bg_18 | B57: Желательный | C57: Низкий | D57: В блоке "Быстрый способ помочь" вместо фразы "Внимание!!! Помочь можно из приложений Сбербанк в строке поиска наберите «ПОДАРИ ШАНС»." указана фраза "Внимание!!! Помочь можно из приложений Сбербанк в строке поиска наберите «помоги лично»." | F57: Открыта страница семьи, оформившей заявку на получение помощи https://pl.rassokha.pro:3001/family_request/18 | G57: На главной странице в блоке "Нужна помощь" под карточками семьи нет пагинации | I57: Открыта главная страница сайта: https://pl.rassokha.pro:3001 | J57: fml_pg_ bttn_bg_18.png | K57: OC: Windows 11 24H2 Разрешение: 1920х1080 Браузер: Opera 123.0.5669.47
A58: fml_pg_ bttn_bg_19 | B58: Желательный | C58: Низкий | D58: В блоке "Помочь ребенку" в указанных суммах пожертвования нет разделения между тысячами и сотнями | F58: Открыта страница семьи, оформившей заявку на получение помощи https://pl.rassokha.pro:3001/family_request/18 | G58: На странице "О фонде" в блоке "Наша команда" у карточек "Директор", "Бухгалтер" и "Волонтер" не меняют режим при наведении курсора | I58: Открыта странице "О фонде" https://pl.rassokha.pro:3001/about | J58: fml_pg_ bttn_bg_19.png | K58: OC: Windows 11 24H2 Разрешение: 1920х1080 Браузер: Opera 123.0.5669.47
A59: fml_pg_ bttn_bg_20 | B59: Критический | C59: Высокий | D59: В блоке "Помочь лично" в графе "Город" нет выпадающего списка | F59: Открыта страница семьи, оформившей заявку на получение помощи https://pl.rassokha.pro:3001/family_request/18 | G59: На странице "О фонде" в блоке "Наша команда" у карточки "Директор" задвоилась рамка вокруг фото | I59: Открыта странице "О фонде" https://pl.rassokha.pro:3001/about | K59: OC: Windows 11 24H2 Разрешение: 1920х1080 Браузер: Opera 123.0.5669.47
A60: fml_pg_ bttn_bg_21 | B60: Критический | C60: Высокий | D60: В блоке "Им тоже нужна помощь" только 3 информ блока (оставленных заявок гораздо больше) | F60: Открыта страница семьи, оформившей заявку на получение помощи https://pl.rassokha.pro:3001/family_request/18 | G60: На странице "О фонде" нет блока "Учредительные документы" | I60: Открыта странице "О фонде" https://pl.rassokha.pro:3001/about | J60: fml_pg_ bttn_bg_21.png | K60: OC: Windows 11 24H2 Разрешение: 1920х1080 Браузер: Opera 123.0.5669.47
A61: fml_pg_ bttn_bg_22 | B61: Желательный | C61: Низкий | D61: В блоке "Помочь очень просто!" плейсхолдер графы "Email для квитанции" указан "Email" | F61: Открыта страница семьи, оформившей заявку на получение помощи https://pl.rassokha.pro:3001/family_request/18 | G61: На странице "Получить помощь" поле ввода "Город" не имеет раскрывающегося списка | H61: По макету поле имеет раскрывающийся список | I61: Открыта страница "Получить помощь" https://pl.rassokha.pro:3001/get-help | K61: OC: Windows 11 24H2 Разрешение: 1920х1080 Браузер: Opera 123.0.5669.47
A62: vlntr_bg_4 | B62: Высокий | C62: Высокий | D62: На старнице "Стать волонтером" после нажатия кнопки "задать вопрос" блоки "Чтать волонтером" и "анкета волонтера" пропадают | F62: Открыта страница сайта "Стать волонтером" https://pl.rassokha.pro:3001/volunteer-applications | G62: На странице "Получить помощь" в блоке "Список заявок" при выборе в поле "Город" любого города отображаются заявки из всех городов | I62: Открыта страница "Получить помощь" https://pl.rassokha.pro:3001/get-help | J62: Помоги лично и еще 2 страницы — Личный_ Microsoft​ Edge 2025-11-18 21-53-09.mp4 | K62: Edge Windows 10 Версия 142.0.3595.65 Разрешение 1920х1080
A63: hm_pg_bg_8 | B63: Желательный | C63: Средний | D63: На главной странице при масштабировании блока "Нужна помощь!" разъезжается верстка | F63: Открыта Главная страница сайта https://pl.rassokha.pro:3001/ | G63: На странице "Получить помощь" в блоке "Список заявок" в поле "Город" в раскрывающемся списке нет пустого поля (сверху спсика) для сброса выбранного поля | I63: Открыта страница "Получить помощь" https://pl.rassokha.pro:3001/get-help | J63: Помоги лично — Личный_ Microsoft​ Edge 2025-11-18 22-18-24.mp4 | K63: Edge Windows 10 Версия 142.0.3595.65 Разрешение 1920х1080 | L63: https://drive.google.com/file/d/1d3QEuCJRnphABN6aAwm8JU2eoSOPI62P/view?usp=drive_link
A64: ke_gz_bg_1 | B64: Желательный | C64: Низкий | D64: Некорректная валидация полей Имя, Фамилия, Отчество, Город, Район, Комментарий, Адрес при заполнении формы "Получить помощь". При введении 1 символа возникает ошибка длины. | F64: Открыта страница "Получить помощь" https://pl.rassokha.pro:3001/get-help | G64: На странице "Получить помощь" в блоке "Список заявок" текст на кнопке - "ПОКАЗАТЬ ЕЩЕ" | I64: Открыта страница "Получить помощь" https://pl.rassokha.pro:3001/get-help | K64: Статус проверки ОС: Windows 10 Pro 22H2 Разрешение: 1920x1080 Браузер: Chrome 142.0.7444.135 | L64: Аналогичная ситуация для: "Кнопка ПОМОЧЬ" "Стать Волонтером"
A65: ke_gz_bg_2 | B65: Желательный | C65: Низкий | D65: Некорректная валидация поля Телефон при заполнении формы "Получить помощь". При введении 1 символа возникает ошибка длины. | F65: Открыта страница "Получить помощь" https://pl.rassokha.pro:3001/get-help | G65: На странице "Получить помощь" в блоке "Часто задаваемые вопросы" при раскрытии вопроса внутри ответов нет кликабельных ссылок | I65: Открыта страница "Получить помощь" https://pl.rassokha.pro:3001/get-help | K65: Статус проверки ОС: Windows 10 Pro 22H2 Разрешение: 1920x1080 Браузер: Chrome 142.0.7444.135 | L65: Аналогичная ситуация для: "Кнопка ПОМОЧЬ" "Стать Волонтером"
A66: ke_gz_bg_3 | B66: Желательный | C66: Низкий | D66: Некорректная валидация поля Телефон при заполнении формы "Получить помощь". При введении 2-7 символов возникает ошибка длины. | F66: Открыта страница "Получить помощь" https://pl.rassokha.pro:3001/get-help | G66: На странице "Стать волонтером" в блоке "Анкета волонтера" поле ввода "Город" не имеет раскрывающегося списка | H66: По макету поле имеет раскрывающийся список | I66: Открыта страница "Стать волонтером" https://pl.rassokha.pro:3001/volunteer-applications | K66: Статус проверки ОС: Windows 10 Pro 22H2 Разрешение: 1920x1080 Браузер: Chrome 142.0.7444.135 | L66: Аналогичная ситуация для: "Кнопка ПОМОЧЬ" "Стать Волонтером"
A67: ke_gz_bg_4 | B67: Желательный | C67: Низкий | D67: Некорректная валидация поля Телефон при заполнении формы "Получить помощь". Отсутствует проверка отдельных зон номера. | F67: Открыта страница "Получить помощь" https://pl.rassokha.pro:3001/get-help | G67: На странице "Стать волонтером" в блоке "Часто задаваемые вопросы" при раскрытии вопроса внутри ответов нет кликабельных ссылок | I67: Открыта страница "Стать волонтером" https://pl.rassokha.pro:3001/volunteer-applications | K67: Статус проверки ОС: Windows 10 Pro 22H2 Разрешение: 1920x1080 Браузер: Chrome 142.0.7444.135 | L67: Аналогичная ситуация для: "Кнопка ПОМОЧЬ" "Стать Волонтером"
A68: ke_gz_bg_5 | B68: Желательный | C68: Низкий | D68: Некорректная валидация поля Телефон при заполнении формы "Получить помощь". Отсутствует проверка на нулевой номер. | F68: Открыта страница "Получить помощь" https://pl.rassokha.pro:3001/get-help | G68: Некорректный порядок документов в галерее под заголовком "Документы" на странице документов | H68: По макету документы фонда должны отображаться слева направо в порядке: 1) Свидетельство о государственной регистрации коммерческих организаций, 2) Свидетельство о постановке на учет в налоговом органе, 3) Лист записи ЕГРЮЛ. Фактически порядок другой: первым отображается Лист записи ЕГРЮЛ, затем остальные документы | I68: Открыта страница "Документы" https://pl.rassokha.pro:3001/documents | K68: Статус проверки ОС: Windows 10 Pro 22H2 Разрешение: 1920x1080 Браузер: Chrome 142.0.7444.135 | L68: Аналогичная ситуация для: "Кнопка ПОМОЧЬ" "Стать Волонтером"
A69: ke_gz_bg_6 | B69: Желательный | C69: Низкий | D69: Некорректная валидация поля Email при заполнении формы "Получить помощь". Отсутствует проверка на длину локальной части. | F69: Открыта страница "Получить помощь" https://pl.rassokha.pro:3001/get-help | G69: Некорректный переход по ссылке «Кому помочь» в хедере | H69: При клике по пункту меню «Кому помочь» происходит переход на главную страницу, но пользователь попадает в блок «Нужна помощь!». | I69: Открыта страница сайта "О фонде" https://pl.rassokha.pro:3001/about | K69: Статус проверки ОС: Windows 10 Pro 22H2 Разрешение: 1920x1080 Браузер: Chrome 142.0.7444.135 | L69: Аналогичная ситуация для: "Публикация блога" "Кнопка ПОМОЧЬ" "Стать Волонтером"
A70: ke_gz_bg_7 | B70: Желательный | C70: Низкий | D70: Некорректная валидация поля Адрес при заполнении формы "Получить помощь". Длина не может превышать 200 символов. | F70: Открыта страница "Получить помощь" https://pl.rassokha.pro:3001/get-help | G70: На странице "Публикации блога" под заголовком блока на правом краю блока справа от даты нет ссылки на мессенджер Вайбер | I70: Открыта страница "Публикация блога" https://pl.rassokha.pro:3001/blog/5 | K70: Статус проверки ОС: Windows 10 Pro 22H2 Разрешение: 1920x1080 Браузер: Chrome 142.0.7444.135
A71: ke_gz_bg_8 | B71: Стандартный | C71: Низкий | D71: Некорректная валидация поля Комментарий при заполнении формы "Получить помощь". Не допускается ввод ?- 4000 символов. | F71: Открыта страница "Получить помощь" https://pl.rassokha.pro:3001/get-help | G71: Отсутствие ссылок на "Telegram" и "YouTube" в футере | I71: Открыт футер на любой странице сайта | K71: Статус проверки ОС: Windows 10 Pro 22H2 Разрешение: 1920x1080 Браузер: Chrome 142.0.7444.135 | L71: Аналогичная ситуация для: "Кнопка ПОМОЧЬ"
A72: ke_gz_bg_9 | B72: Стандартный | C72: Низкий | D72: Некорректная валидация поля Ваше при заполнении формы "Стать волонтером". Можно прикрепить пустой файл | F72: Открыта страница "Получить помощь" https://pl.rassokha.pro:3001/volunteer-applications | G72: Отсутствует раздел «Обратная связь» в футере | I72: Открыт футер на любой странице сайта | K72: Статус проверки ОС: Windows 10 Pro 22H2 Разрешение: 1920x1080 Браузер: Chrome 142.0.7444.135
A73: ke_gz_bg_10 | B73: Стандартный | C73: Низкий | D73: Некорректная валидация поля Ваше при заполнении формы "Стать волонтером". Можно прикрепить поврежденный файл | F73: Открыта страница "Получить помощь" https://pl.rassokha.pro:3001/volunteer-applications | G73: На странице "Реквизиты" заголовок блока с текстом "Реквизиты благотворительного фонда "Помоги Лично"" расположен посередине страницы | I73: Открыть страницу "Реквизиты" https://pl.rassokha.pro:3001/requisites | K73: Статус проверки ОС: Windows 10 Pro 22H2 Разрешение: 1920x1080 Браузер: Chrome 142.0.7444.135

Sheet Баг-репорты САЙТ (копия)
A1: ID | B1: Severity | C1: Priority | D1: Название бага | E1: Описание | F1: Предусловия | G1: Шаги воспроизведения | H1: ОР | I1: ФР | J1: Скринкаст/скриншот | K1: Окружение | L1: Комментарий
A2: hm_pg_bg_1 | B2: Желательный | C2: Низкий | D2: Отсутствие отображения длительности видео в правом нижнем углу блока "Вы помогли этим детям!" на главной странице | E2: На макете указана длительность видео, но на тестовом стенде она не отображается | F2: Открыта главная страница сайта: https://pl.rassokha.pro:3001 | G2: Найти блок "Вы помогли этим детям!" с видео | H2: В правом нижнем углу видео отображается его длительность | I2: В правом нижнем углу видео длительность НЕ отображается | J2: hm_pg_bg_1.png | K2: macOS Tahoe 26.0.1 Разрешение: 3456 x 2234 Браузер: Chrome 142.0.7444.135 Разрешение: 1920х1080 Браузер: Opera 123.0.5669.47 ОС: Windows 11 Разрешение: 2560х1600 Браузер: Яндекс. 25.8.5.890 | L2: Ошибка влияет только на UI и не мешает основной функциональности
A3: hm_pg_bg_2 | B3: Желательный | C3: Низкий | D3: Логотип на карточке с фото в блоке "Нужна помощь!" на главной странице не соответствует состоянию hover | E3: По макетам лого должно менять цвет при наведении (hover) | F3: Открыта главная страница сайта: https://pl.rassokha.pro:3001 | G3: 1. Найти блок "Нужна помощь!" 2. Навести курсор на логотип в верхнем левом углу карточки | H3: При наведении на лого, оно должно менять цвет на #FFE0BC | I3: Логотип не меняет цвета при наведении | K3: macOS Tahoe 26.0.1 Разрешение: 3456 x 2234 Браузер: Chrome 142.0.7444.135 ОС: Windows 11 Разрешение: 2560х1600 Браузер: Яндекс. 25.8.5.890 | L3: Возможно, ошибка связана с некорректным применением стилей CSS для состояния hover.
A4: hm_pg_bg_3 | B4: Желательный | C4: Низкий | D4: Несоответствие цвета цифр в заголовке на карточке в блоке "Нужна помощь" на главной странице | E4: На макете для цвета цифр в заголовке указан #D89C66, но в DevTools отображается #efb46d | F4: Открыта главная страница сайта: https://pl.rassokha.pro:3001 | G4: Найти заголовок на карточке с сбором средств | H4: Цвет цифр в заголовке должен быть #D89C66 | I4: В DevTools отображается #efb46d | K4: macOS Tahoe 26.0.1 Разрешение: 3456 x 2234 Браузер: Chrome 142.0.7444.135 Разрешение: 1920х1080 Браузер: Opera 123.0.5669.47 ОС: Windows 11 Разрешение: 2560х1600 Браузер: Яндекс. 25.8.5.890 | L4: В DevTools неверно применен цвет для элемента
A5: hm_pg_bg_4 | B5: Желательный | C5: Низкий | D5: Вместо "Отчет о поступлениях (дата формирования отчета)" указана "Лента пожертвований" на главной странице в блоке "Нужна помощь" справа от карточки семьи | F5: Открыта главная страница сайта: https://pl.rassokha.pro:3001 | G5: 1. Найти блок "Нужна помощь" 2. Справа от карточки семьи блок с отчетом | H5: Наименование: "Отчет о поступлениях" и справа дата отчета | I5: Наименование: "Лента пожертвований" без даты | J5: hm_pg_bg_4.png | K5: OC: Windows 11 24H2 Разрешение: 1920х1080 Браузер: Opera 123.0.5669.47 macOS Tahoe 26.0.1 Разрешение: 3456 x 2234 Браузер: Chrome 142.0.7444.135 ОС: Windows 11 Разрешение: 2560х1600 Браузер: Яндекс. 25.8.5.890
A6: hm_pg_bg_5 | B6: Высокий | C6: Высокий | D6: В блоке "Отчет о поступлениях" нет ссылки на все отчеты | F6: Открыта главная страница сайта: https://pl.rassokha.pro:3001 | G6: 1. Найти блок "Нужна помощь" 2. Справа от карточки семьи блок с отчетом | H6: Под списком благотворителей и суммами пожертвований есть ссылка на все отчеты "Посмотреть все отчеты →" | I6: Ссылки нет | J6: hm_pg_bg_5.png | K6: OC: Windows 11 24H2 Разрешение: 1920х1080 Браузер: Opera 123.0.5669.47 macOS Tahoe 26.0.1 Разрешение: 3456 x 2234 Браузер: Chrome 142.0.7444.135 ОС: Windows 11 Разрешение: 2560х1600 Браузер: Яндекс. 25.8.5.890
A7: hm_pg_bg_6 | B7: Желательный | C7: Низкий | D7: В блоке "Помочь очень просто!" в графе "Email для квитанций" не указан плейсхолдер "Указать email" | F7: Открыта главная страница сайта: https://pl.rassokha.pro:3001 | G7: 1. Найти блок "Нужна помощь" 2. Справа от карточки семьи и ниже блока с отчетом | H7: В графе "Email для квитанций" указан плейсхолдер "Указать email" | I7: В графе "Email для квитанций" указан плейсхолдер "email" | J7: hm_pg_bg_6.png | K7: OC: Windows 11 24H2 Разрешение: 1920х1080 Браузер: Opera 123.0.5669.47 macOS Tahoe 26.0.1 Разрешение: 3456 x 2234 Браузер: Chrome 142.0.7444.135 ОС: Windows 11 Разрешение: 2560х1600 Браузер: Яндекс. 25.8.5.890
A8: hm_pg_bg_7 | B8: Высокий | C8: Высокий | D8: На главной странице в блоке "Нужна помощь" под карточками семьи нет пагинации | F8: Открыта главная страница сайта: https://pl.rassokha.pro:3001 | G8: 1. Найти блок "Нужна помощь" 2. Под карточками семьи | H8: Под карточками семьи есть пагинация | I8: Под карточками семьи нет пагинации | J8: hm_pg_bg_7.png | K8: OC: Windows 11 24H2 Разрешение: 1920х1080 Браузер: Opera 123.0.5669.47 ОС: Windows 11 Разрешение: 2560х1600 Браузер: Яндекс. 25.8.5.890 macOS Tahoe 26.0.1 Разрешение: 3456 x 2234 Браузер: Chrome 142.0.7444.135
A9: bt_fndtn_bg_1 | B9: Желательный | C9: Низкий | D9: На странице "О фонде" в блоке "Наша команда" у карточек "Директор", "Бухгалтер" и "Волонтер" не меняют режим при наведении курсора | F9: Открыта странице "О фонде" https://pl.rassokha.pro:3001/about | G9: 1, Найти блок "Наша команда" 2. Навести курсор на карточку "Директор", "Бухгалтер" или "Волонтер" | H9: Карточки имеют 2 состояния при наведении курсора "defaut, hover" | I9: Карточки не активны | K9: OC: Windows 11 24H2 Разрешение: 1920х1080 Браузер: Opera 123.0.5669.47 ОС: Windows 11 Разрешение: 2560х1600 Браузер: Яндекс. 25.8.5.890
A10: bt_fndtn_bg_2 | B10: Желательный | C10: Низкий | D10: На странице "О фонде" в блоке "Наша команда" у карточки "Директор" задвоилась рамка вокруг фото | F10: Открыта странице "О фонде" https://pl.rassokha.pro:3001/about | G10: 1, Найти блок "Наша команда" 2. Обратить внимание на карточку "Директор" | H10: Фото в одинарной белой рамке | I10: Фото в двойной белой рамке | J10: bt_fndtn_bg_2.png | K10: OC: Windows 11 24H2 Разрешение: 1920х1080 Браузер: Opera 123.0.5669.47 ОС: Windows 11 Разрешение: 2560х1600 Браузер: Яндекс. 25.8.5.890
A11: bt_fndtn_bg_3 | B11: Критический | C11: Высокий | D11: На странице "О фонде" нет блока "Учредительные документы" | F11: Открыта странице "О фонде" https://pl.rassokha.pro:3001/about | G11: 1. Найти блок "Нас поддерживают" | H11: Под блоком "Нас поддерживают" размещен блок "Учредтельные документы" | I11: Под блоком "Нас поддерживают" размещен сразу футер | J11: bt_fndtn_bg_3.png | K11: OC: Windows 11 24H2 Разрешение: 1920х1080 Браузер: Opera 123.0.5669.47 ОС: Windows 11 Разрешение: 2560х1600 Браузер: Яндекс. 25.8.5.890
A12: gt_hlp_bg_1 | B12: Критический | C12: Высокий | D12: На странице "Получить помощь" поле ввода "Город" не имеет раскрывающегося списка | E12: По макету поле имеет раскрывающийся список | F12: Открыта страница "Получить помощь" https://pl.rassokha.pro:3001/get-help | G12: 1. Найти блок "Вам нужна помощь?" 2. Найти поле "Город" | H12: Поле "Город" имеет раскрывающийся список | I12: Поле "Город" не имеет раскрывающийся список | J12: gt_hlp_bg_1.png | K12: ОС: Windows 11 Разрешение: 2560х1600 Браузер: Яндекс. 25.8.5.890 OC: Windows 11 24H2 Разрешение: 1920х1080 Браузер: Opera 123.0.5669.47
A13: gt_hlp_bg_2 | B13: Критический | C13: Высокий | D13: На странице "Получить помощь" в блоке "Список заявок" при выборе в поле "Город" любого города отображаются заявки из всех городов | F13: Открыта страница "Получить помощь" https://pl.rassokha.pro:3001/get-help | G13: 1. Найти блок "Список заявок" 2. В поле "Город" раскрыть выпадающий список 3. В списке выбрать любой город | H13: В блоке "Список заявок" при выборе в поле "Город" любого города отображаются заявки из этого города | I13: В блоке "Список заявок" при выборе в поле "Город" любого города отображаются заявки из всех городов | J13: gt_hlp_bg_2.png | K13: ОС: Windows 11 Разрешение: 2560х1600 Браузер: Яндекс. 25.8.5.890 OC: Windows 11 24H2 Разрешение: 1920х1080 Браузер: Opera 123.0.5669.47
A14: gt_hlp_bg_3 | B14: Высокий | C14: Средний | D14: На странице "Получить помощь" в блоке "Список заявок" в поле "Город" в раскрывающемся списке нет пустого поля (сверху спсика) для сброса выбранного поля | F14: Открыта страница "Получить помощь" https://pl.rassokha.pro:3001/get-help | G14: 1. Найти блок "Список заявок" 2. В поле "Город" раскрыть выпадающий список | H14: В блоке "Список заявок" при выборе в поле "Город" в раскрывающемся списке есть пустое поле (сверху спсика) для сброса выбранного поля | I14: В блоке "Список заявок" при выборе в поле "Город" в раскрывающемся списке нет пустого поля (сверху спсика) для сброса выбранного поля | J14: gt_hlp_bg_3.png | K14: ОС: Windows 11 Разрешение: 2560х1600 Браузер: Яндекс. 25.8.5.890 OC: Windows 11 24H2 Разрешение: 1920х1080 Браузер: Opera 123.0.5669.47
A15: gt_hlp_bg_4 | B15: Стандартный | C15: Низкий | D15: На странице "Получить помощь" в блоке "Список заявок" текст на кнопке - "ПОКАЗАТЬ ЕЩЕ" | F15: Открыта страница "Получить помощь" https://pl.rassokha.pro:3001/get-help | G15: 1. Найти блок "Список заявок" 2. Найти кнопку "Показать еще" | H15: В блоке "Список заявок" текст на кнопке - "ПОКАЗАТЬ ЕЩЕ" | I15: В блоке "Список заявок" текст на кнопке - "Показать еще" | J15: gt_hlp_bg_4.png | K15: ОС: Windows 11 Разрешение: 2560х1600 Браузер: Яндекс. 25.8.5.890 OC: Windows 11 24H2 Разрешение: 1920х1080 Браузер: Opera 123.0.5669.47
A16: gt_hlp_bg_5 | B16: Стандартный | C16: Низкий | D16: На странице "Получить помощь" в блоке "Часто задаваемые вопросы" при раскрытии вопроса внутри ответов нет кликабельных ссылок | F16: Открыта страница "Получить помощь" https://pl.rassokha.pro:3001/get-help | G16: 1. Найти блок "Часто задаваемые вопросы" 2. Кликнуть на вопрос | H16: При раскрытии вопроса внутри ответов есть кликабельные ссылки | I16: При раскрытии вопроса внутри ответов нет кликабельных ссылок | J16: gt_hlp_bg_5.png | K16: ОС: Windows 11 Разрешение: 2560х1600 Браузер: Яндекс. 25.8.5.890
A17: vlntr_bg_1 | B17: Критический | C17: Высокий | D17: На странице "Стать волонтером" в блоке "Анкета волонтера" поле ввода "Город" не имеет раскрывающегося списка | E17: По макету поле имеет раскрывающийся список | F17: Открыта страница "Стать волонтером" https://pl.rassokha.pro:3001/volunteer-applications | G17: 1. Найти блок "Анкета волонтера" 2. Найти поле "Город" | H17: Поле "Город" имеет раскрывающийся список | I17: Поле "Город" не имеет раскрывающийся список | J17: vlntr_bg_1.pgn | K17: ОС: Windows 11 Разрешение: 2560х1600 Браузер: Яндекс. 25.8.5.890
A18: vlntr_bg_2 | B18: Стандартный | C18: Низкий | D18: На странице "Стать волонтером" в блоке "Часто задаваемые вопросы" при раскрытии вопроса внутри ответов нет кликабельных ссылок | F18: Открыта страница "Стать волонтером" https://pl.rassokha.pro:3001/volunteer-applications | G18: 1. Найти блок "Часто задаваемые вопросы" 2. Кликнуть на вопрос | H18: При раскрытии вопроса внутри ответов есть кликабельные ссылки | I18: При раскрытии вопроса внутри ответов нет кликабельных ссылок | J18: vlntr_bg_2.png | K18: ОС: Windows 11 Разрешение: 2560х1600 Браузер: Яндекс. 25.8.5.890
A19: dcmnts_bg_1 | B19: Желательный | C19: Низкий | D19: Некорректный порядок документов в галерее под заголовком "Документы" на странице документов | E19: По макету документы фонда должны отображаться слева направо в порядке: 1) Свидетельство о государственной регистрации коммерческих организаций, 2) Свидетельство о постановке на учет в налоговом органе, 3) Лист записи ЕГРЮЛ. Фактически порядок другой: первым отображается Лист записи ЕГРЮЛ, затем остальные документы | F19: Открыта страница "Документы" https://pl.rassokha.pro:3001/documents | G19: Проверить порядок документов в галерее | H19: Документы отображаются в соответствии с макетом в Figma: слева направо в порядке: 1) Свидетельство о государственной регистрации коммерческих организаций, 2) Свидетельство о постановке на учет в налоговом органе, 3) Лист записи ЕГРЮЛ | I19: Документы отображаются : слева направо в порядке: 1) Лист записи ЕГРЮЛ, 2) Свидетельство о государственной регистрации коммерческих организаций, 3) Свидетельство о постановке на учет в налоговом органе | J19: dcmnts_bg_1.png | K19: macOS Tahoe 26.0.1 Разрешение: 3456 x 2234 Браузер: Chrome 142.0.7444.135 | L19: Вероятно, в данных нарушена сортировка или порядок вывода элементов. Функциональность не нарушена, проблема только в соответствии макету
A20: hdr_bg_1 | B20: Стандартный | C20: Средний | D20: Некорректный переход по ссылке «Кому помочь» в хедере | E20: При клике по пункту меню «Кому помочь» происходит переход на главную страницу, но пользователь попадает в блок «Нужна помощь!». | F20: Открыта страница сайта "О фонде" https://pl.rassokha.pro:3001/about | G20: В верхнем меню нажать на ссылку «Кому помочь» | H20: При клике на раздел "Кому помочь" переход на главную страницу в раздел "Нужна помощь!" | I20: При клике на раздел "Кому помочь" переход на главную страницу в раздел "Вы помогли этим детям" | J20: hdr_bg_1.mov | K20: macOS Tahoe 26.0.1 Разрешение: 3456 x 2234 Браузер: Chrome 142.0.7444.135 | L20: У ссылки прописан неверный якорь, либо скрипт прокрутки работает некорректно; Требуется проверка ссылок и обработчиков навигации
A21: pbl_blg_bg_1 | B21: Стандартный | C21: Средний | D21: На странице "Публикации блога" под заголовком блока на правом краю блока справа от даты нет ссылки на мессенджер Вайбер | F21: Открыта страница "Публикация блога" https://pl.rassokha.pro:3001/blog/5 | G21: Справа от названия блока найти ссылки на мессенджеры | H21: На странице "Публикация блога" имеется ссылки на мессенджеры ТГ, ВК и WA | I21: На странице "Публикации блога" нет ссылки на мессенджер Вайбер | J21: pbl_blg_bg_1.png | K21: ОС: Windows 11 Разрешение: 2560х1600 Браузер: Яндекс. 25.8.5.890 macOS Tahoe 26.0.1 Разрешение: 3456 x 2234 Браузер: Chrome 142.0.7444.135
A22: ftr_bg_1 | B22: Стандартный | C22: Средний | D22: Отсутствие ссылок на "Telegram" и "YouTube" в футере | F22: Открыт футер на любой странице сайта | G22: Найти блок с иконками соцсетей в правой части футера | H22: Все 4 ссылки на соцсети отображаются: Telegram, YouTube, Вконтакте, Одноклассники | I22: Ссылки на Telegram и YouTube отсутствуют | J22: ftr_bg_1.png | K22: macOS Tahoe 26.0.1 Разрешение: 3456 x 2234 Браузер: Chrome 142.0.7444.135 | L22: Возможно устарел макет и ссылки на телеграмм и ютуб не требуются (ютуб запрещен в РФ)
A23: ftr_bg_2 | B23: Высокий | C23: Высокий | D23: Отсутствует раздел «Обратная связь» в футере | F23: Открыт футер на любой странице сайта | G23: Найти раздел "Обратная связь" | H23: Раздел "Обратная связь" отображается в футере | I23: Раздел полностью отсутствует | J23: ftr_bg_2.png | K23: macOS Tahoe 26.0.1 Разрешение: 3456 x 2234 Браузер: Chrome 142.0.7444.135
A24: dtls_bg_1 | B24: Желательный | C24: Низкий | D24: На странице "Реквизиты" заголовок блока с текстом "Реквизиты благотворительного фонда "Помоги Лично"" расположен посередине страницы | F24: Открыть страницу "Реквизиты" https://pl.rassokha.pro:3001/requisites | G24: Найти заголовок "Реквизиты благотворительного фонда "Помоги Лично" | H24: Заголовок блока с текстом "Реквизиты благотворительного фонда "Помоги Лично"" расположен слева над областью с реквизитами | I24: Заголовок блока с текстом "Реквизиты благотворительного фонда "Помоги Лично"" расположен посередине страницы над областью с реквизитами | J24: dtls_bg_1.png | K24: ОС: Windows 11 Разрешение: 2560х1600 Браузер: Яндекс. 25.8.5.890
A25: dtls_bg_2 | B25: Стандартный | C25: Средний | D25: На странице "Реквизиты" под ссылкой "Скачать реквизиты благотворительного фонда "Помоги Лично"" отсутствуют ссылки на "Telegram" и "YouTube" | F25: Открыть страницу "Реквизиты" https://pl.rassokha.pro:3001/requisites | G25: Найти блок со ссылками на мессенджеры | H25: Все 4 ссылки на соцсети отображаются: Telegram, YouTube, Вконтакте, Одноклассники | I25: Ссылки на Telegram и YouTube отсутствуют | J25: dtls_bg_2.png | K25: ОС: Windows 11 Разрешение: 2560х1600 Браузер: Яндекс. 25.8.5.890
A26: fml_pg_bttn_bg_1 | B26: Стандартный | C26: Средний | D26: На странице "Семья (кнопка помочь)" карточка "Быстрый способ помочь" расположена под блоком "Фамилия семьи" | F26: Открыть страницу "Семья (кнопка помочь)" https://pl.rassokha.pro:3001/family_request | G26: Найти карточку "Быстрый способ помочь" | H26: Справой стороны от блока "Фамилия семьи" расположена карточка "Быстрый способ помочь" | I26: Карточка "Быстрый способ помочь" расположена под блоком "Фамилия семьи" | J26: fml_pg_bttn_bg_1.png | K26: ОС: Windows 11 Разрешение: 2560х1600 Браузер: Яндекс. 25.8.5.890
A27: fml_pg_bttn_bg_2 | B27: Высокий | C27: Средний | D27: На странице "Семья (кнопка помочь)" справа от заголовка "Помочь ребенку!" расположены три кнопки "Онлайн, Реквизиты, Помочь лично" | F27: Открыть страницу "Семья (кнопка помочь)" https://pl.rassokha.pro:3001/family_request | G27: Найти блок "Помочь ребенку!" | H27: Справа от заголовка "Помочь ребенку!" расположены две кнопки "Онлайн, Реквизиты" | I27: Справа от заголовка "Помочь ребенку!" расположены три кнопки "Онлайн, Реквизиты, Помочь лично" | J27: fml_pg_bttn_bg_2.png | K27: ОС: Windows 11 Разрешение: 2560х1600 Браузер: Яндекс. 25.8.5.890
A28: fml_pg_bttn_bg_3 | B28: Желательный | C28: Низкий | D28: На странице "Семья (кнопка помочь)" в блоке "Помочь ребенку!" под 2 radio buttom "Хочу помогать ОДНОКРАТНО" "Хочу помогать ЕЖЕМЕСЯЧНО" расположен заголовок "3. Ваши данные" | F28: Открыть страницу "Семья (кнопка помочь)" https://pl.rassokha.pro:3001/family_request | G28: Найти блок "Помочь ребенку!" | H28: Под 2 radio buttom "Хочу помогать ОДНОКРАТНО" "Хочу помогать ЕЖЕМЕСЯЧНО" расположен заголовок "3. Ваш комментарий (отражается в ленте пожертвований)" | I28: Под 2 radio buttom "Хочу помогать ОДНОКРАТНО" "Хочу помогать ЕЖЕМЕСЯЧНО" расположен заголовок "3. Ваши данные" | J28: fml_pg_bttn_bg_3.png | K28: ОС: Windows 11 Разрешение: 2560х1600 Браузер: Яндекс. 25.8.5.890
A29: fml_pg_bttn_bg_4 | B29: Высокий | C29: Средний | D29: На странице "Семья (кнопка помочь)" в блоке "Помочь ребенку!" под заголовком "3. Ваши данные" расположено два поля ввода "Имя, Email" | F29: Открыть страницу "Семья (кнопка помочь)" https://pl.rassokha.pro:3001/family_request | G29: Найти блок "Помочь ребенку!" | H29: Под заголовком "3. Ваш комментарий (отражается в ленте пожертвований)" расположено три поля ввода "Ваше имя, Email, Ваши комментарии и пожелания" | I29: Под заголовком "3. Ваши данные" расположено два поля ввода "Имя, Email" | J29: fml_pg_bttn_bg_4.png | K29: ОС: Windows 11 Разрешение: 2560х1600 Браузер: Яндекс. 25.8.5.890
A30: fml_pg_bttn_bg_5 | B30: Желательный | C30: Низкий | D30: На странице "Семья (кнопка помочь)" в блоке "Помочь ребенку!" под заголовком "3. Ваши данные" первое поле ввода имеет плейсхолдер "Имя" | F30: Открыть страницу "Семья (кнопка помочь)" https://pl.rassokha.pro:3001/family_request | G30: Найти блок "Помочь ребенку!" | H30: Под заголовком "3. Ваш комментарий (отражается в ленте пожертвований)" расположено три поля ввода "Ваше имя, Email, Ваши комментарии и пожелания" | I30: Под заголовком "3. Ваши данные" первое поле ввода имеет плейсхолдер "Имя" | J30: fml_pg_bttn_bg_5.png | K30: ОС: Windows 11 Разрешение: 2560х1600 Браузер: Яндекс. 25.8.5.890
A31: fml_pg_bttn_bg_6 | B31: Желательный | C31: Низкий | D31: На странице "Семья (кнопка помочь)" в блоке "Помочь ребенку!" под полями ввода "Имя" и "Email" расположен заголовок "Итоговая сумма: 2500 ₽" | F31: Открыть страницу "Семья (кнопка помочь)" https://pl.rassokha.pro:3001/family_request | G31: Найти блок "Помочь ребенку!" | H31: Под полем ввода "Ваши комментарии и пожелания" расположен заголовок "Итоговая сумма пожертвования: 2500 ₽" | I31: Под полями ввода "Имя" и "Email" расположен заголовок "Итоговая сумма: 2500 ₽" | J31: fml_pg_bttn_bg_6.png | K31: ОС: Windows 11 Разрешение: 2560х1600 Браузер: Яндекс. 25.8.5.890
A32: fml_pg_ bttn_bg_7 | B32: Желательный | C32: Низкий | D32: Используемый цвет цифр в заголовке собранных средств на странице семьи #efb46d вместо #D89C66 | F32: Открыть страницу "Семья (кнопка помочь)" https://pl.rassokha.pro:3001/family_request | G32: 1. Найти заголовок шкалы сбора средств 2. В девтулс проверить код цвета элемента | H32: Используемый цвет цифр в заголовке собранных средств на странице семьи #D89C66 | I32: Используемый цвет цифр в заголовке собранных средств на странице семьи #efb46d | K32: macOS Tahoe 26.0.1 Разрешение: 3456 x 2234 Браузер: Chrome 142.0.7444.135
A33: fml_pg_ bttn_bg_8 | B33: Высокий | C33: Высокий | D33: На странице "Семья (кнопка помочь)" в блоке "Помочь ребенку!" под заголовком "Итоговая сумма: 2500 ₽" расположена одна кнопка "Пожертвовать" | F33: Открыть страницу "Семья (кнопка помочь)" https://pl.rassokha.pro:3001/family_request | G33: Найти блок "Помочь ребенку!" | H33: Под заголовком "Итоговая сумма: 2500 ₽" расположены две кнопки "Пожертвовать" и "Счет для юр. лиц" | I33: Под заголовком "Итоговая сумма: 2500 ₽" расположена одна кнопка "Пожертвовать" | J33: fml_pg_ bttn_bg_8.png | K33: ОС: Windows 11 Разрешение: 2560х1600 Браузер: Яндекс. 25.8.5.890
A34: fml_pg_ bttn_bg_9 | B34: Желательный | C34: Низкий | D34: На странице "Семья (кнопка помочь)" в блоке "Помочь ребенку!" при нажатой кнопке "Реквизиты" под заголовком "1. Реквизиты для перевода" вертикально расположены названия реквизитов "Организация, ИНН, КПП, ОГРН/ОГРНИП, Расчётный счёт, БИК, Банк, Корр. счёт, Назначение платежа" | F34: Открыть страницу "Семья (кнопка помочь)" https://pl.rassokha.pro:3001/family_request | G34: 1. Найти блок "Помочь ребенку!" 2. Нажать кнопку "Реквизиты" | H34: Под заголовком "1. Реквизиты для перевода" вертикально расположены названия реквизитов "Банк, БИК, Кор. счет, Получатель, Расчетный счет, ИНН, КПП, Назначение платежа" | I34: Под заголовком "1. Реквизиты для перевода" вертикально расположены названия реквизитов "Организация, ИНН, КПП, ОГРН/ОГРНИП, Расчётный счёт, БИК, Банк, Корр. счёт, Назначение платежа" | J34: fml_pg_ bttn_bg_9.png | K34: ОС: Windows 11 Разрешение: 2560х1600 Браузер: Яндекс. 25.8.5.890
A35: fml_pg_ bttn_bg_10 | B35: Высокий | C35: Высокий | D35: Отсутствуют радиокнопки выбора банка/способа оплаты в карточке "Быстрый способ помочь" | E35: В карточке "Быстрый способ помочь" по макету должны отображаться радиокнопки с выбором банков и способов оплаты | F35: Открыть страницу "Семья (кнопка помочь)" https://pl.rassokha.pro:3001/family_request | G35: Найти карточку "Быстрый способ помочь" | H35: Радиокнопки с выбором банков и способов оплаты отображаются над зоголовком карточки | I35: Радиокнопки отсутствуют | J35: fml_pg_ bttn_bg_10.png | K35: macOS Tahoe 26.0.1 Разрешение: 3456 x 2234 Браузер: Chrome 142.0.7444.135
A36: fml_pg_ bttn_bg_11 | B36: Высокий | C36: Высокий | D36: На странице "Семья (кнопка помочь)" в блоке "Помочь ребенку!" при нажатой кнопке "Реквизиты" справа от реквизитов расположена одна кнопка "скачать реквизиты" | F36: Открыть страницу "Семья (кнопка помочь)" https://pl.rassokha.pro:3001/family_request | G36: 1. Найти блок "Помочь ребенку!" 2. Нажать кнопку "Реквизиты" | H36: Справа от реквизитов расположены две кнопки "Скачать реквизиты" и "Счет для юр. лиц" | I36: Справа от реквизитов расположена одна кнопка "Скачать реквизиты" | J36: fml_pg_ bttn_bg_11.png | K36: ОС: Windows 11 Разрешение: 2560х1600 Браузер: Яндекс. 25.8.5.890
A37: fml_pg_ bttn_bg_12 | B37: Высокий | C37: Средний | D37: На странице "Семья (кнопка помочь)" карточка "Им тоже нужна помощь" расположена над блоком "Помочь ребенку" | F37: Открыть страницу "Семья (кнопка помочь)" https://pl.rassokha.pro:3001/family_request | G37: Найти карточку "Им тоже нужна помощь" | H37: Карточка "Им тоже нужна помощь" расположена справа от блока "Помочь ребенку" | I37: Карточка "Им тоже нужна помощь" расположена над блоком "Помочь ребенку" | J37: fml_pg_ bttn_bg_12.png | K37: ОС: Windows 11 Разрешение: 2560х1600 Браузер: Яндекс. 25.8.5.890
A38: fml_pg_ bttn_bg_13 | B38: Высокий | C38: Высокий | D38: На странице "Семья (кнопка помочь)" под блоком "Помочь ребенку!" расположен блок с заголовком "История" | F38: Открыть страницу "Семья (кнопка помочь)" https://pl.rassokha.pro:3001/family_request | G38: Найти блок "История" | H38: Под блоком "Помочь ребенку!" расположены три блока с заголовками "История", "Документы", "Новости" | I38: Под блоком "Помочь ребенку!" расположен один блок с заголовком "История" | J38: fml_pg_ bttn_bg_13.png | K38: ОС: Windows 11 Разрешение: 2560х1600 Браузер: Яндекс. 25.8.5.890
A39: fml_pg_ bttn_bg_14 | B39: Стандартный | C39: Средний | D39: На странице "Семья (кнопка помочь)" справа от блока "История" в списке ссылок на мессенджеры отсутсвует ссылка на Вайбер | F39: Открыть страницу "Семья (кнопка помочь)" https://pl.rassokha.pro:3001/family_request | G39: Найти блок "История" | H39: Справа от блока "История" расположены ссылки на мессенджеры ТГ, ВК и WA | I39: Справа от блока "История" в списке ссылок на мессенджеры отсутсвует ссылка на Вайбер | J39: fml_pg_ bttn_bg_14.png | K39: ОС: Windows 11 Разрешение: 2560х1600 Браузер: Яндекс. 25.8.5.890
A40: fml_pg_ bttn_bg_15 | B40: Высокий | C40: Высокий | D40: На странице "Семья (кнопка помочь)", под блоком "История" находится блок для оставления комментария "Ваш комментарий или пожелания" | F40: Открыть страницу "Семья (кнопка помочь)" https://pl.rassokha.pro:3001/family_request | G40: Найти блок "История" | H40: Под блоком "История" находится блок "Нуждаются в помощи" | I40: Под блоком "История" находится блок для оставления комментария "Ваш комментарий или пожелания" | J40: fml_pg_ bttn_bg_15.png | K40: ОС: Windows 11 Разрешение: 2560х1600 Браузер: Яндекс. 25.8.5.890
A41: fml_pg_ bttn_bg_16 | B41: Желательный | C41: Низкий | D41: На странице "Семья (кнопка помочь)", под блоком "История" находится блок для оставления комментария "Ваш комментарий или пожелания" | F41: Открыть страницу "Семья (кнопка помочь)" https://pl.rassokha.pro:3001/family_request | G41: Найти блок "История" | H41: Под блоком "История" находится блок "Ваш комментарий или пожелания (отражается в карточке ребенка)" | I41: Под блоком "История" находится блок для оставления комментария "Ваш комментарий или пожелания" | J41: fml_pg_ bttn_bg_16.png | K41: ОС: Windows 11 Разрешение: 2560х1600 Браузер: Яндекс. 25.8.5.890
A42: cntcts_bg_1 | B42: Стандартный | C42: Средний | D42: На странице "Контакты" не активна иконка "наш адрес" | F42: Открыта страница "Контакты" https://pl.rassokha.pro:3001/contacts | G42: Найти блок с иконками контактов | H42: 1. При клике на иконку "Наш адрес" на карте появляется иконка "наш адрес". 2. Иконка имет 2 состояния "default", "hover". 3. При наведении курсора на иконку меняется цвет векторного рисунка с белого в зеленый | I42: 1. При клике на иконку "Наш адрес" ничего не происходит. 2. Иконка не имеет 2 состояния "default", "hover". 3. При наведении курсора на иконку цвет не меняется | K42: OC: Windows 11 24H2 Разрешение: 1920х1080 Браузер: Opera 123.0.5669.47
A43: wh_hlpd_bg_1 | B43: Стандартный | C43: Средний | D43: На странице "Кому помогли" под блоком карточек "Получатель помощи" нет пагинации | F43: Открыта страница "Кому помогли" https://pl.rassokha.pro:3001/whom-we-helped | G43: Найти блок карточек "Получатель помощи" | H43: Под блоком карточек "Получатель помощи" расположен блок пагинации "Навигация страницы" | I43: Под блоком карточек "Получатель помощи" нет блока пагинации "Навигация страницы" | K43: OC: Windows 11 24H2 Разрешение: 1920х1080 Браузер: Opera 123.0.5669.47
A44: fml_pg_ bttn_bg_17 | B44: Желательный | C44: Низкий | D44: На странице "Семья (кнопка помочь)", под блоком "История" в блоке для оставления комментария "Ваш комментарий или пожелания" третье поле ввода имеет плейсхолдер "Ваши комментарии" | F44: Открыть страницу "Семья (кнопка помочь)" https://pl.rassokha.pro:3001/family_request | G44: Найти блок "Ваш комментарий или пожелания" | H44: В блоке для оставления комментария "Ваш комментарий или пожелания" третье поле ввода имеет плейсхолдер "Ваши комментарии и пожелания" | I44: В блоке для оставления комментария "Ваш комментарий или пожелания" третье поле ввода имеет плейсхолдер "Ваши комментарии" | J44: fml_pg_ bttn_bg_17.png | K44: ОС: Windows 11 Разрешение: 2560х1600 Браузер: Яндекс. 25.8.5.890
A45: sk_qstn_bg_1 | B45: Высокий | C45: Высокий | D45: Кнопка "Задать вопрос" не работает при некорректно заполненных полях на странице "Получить помощь" | E45: На странице "Получить помощь" кнопка "Задать вопрос" должна работать независимо от корректности заполнения формы, так как не связана с обработкой этих полей. | F45: Открыта страница "Получить помощь" https://pl.rassokha.pro:3001/get-help | G45: 1. В поля формы "Вам нужна помощь?" ввести некорректные данные 2. Нажать кнопку "Задать вопрос" в блоке "Часто задаваемые вопросы" | H45: Кнопка "Задать вопрос" работает всегда, независимо от состояния полей формы | I45: Кнопка не работает | K45: ОС: Windows 11 Разрешение: 2560х1600 Браузер: Яндекс. 25.8.5.890

Sheet Чек-лист МВ.  
A1: Модуль | B1: ID | C1: Приоритет | D1: Описание проверки | E1: Ссылка на баг-репорт | F1: Комментарий | G1: Статус проверки ОС: android One UI версия: 13 Разрешение: 2400 × 1080 Браузер: Chrome версия 142.0.7444.138
D2: Раздел "Главная"
A3: Хидер | B3: hdr_1 | C3: Критичный | D3: На страницу "Главная" можно попасть, введя ссылку в браузере: https://pl.rassokha.pro:3001. | G3: Passed
A4: Хидер | B4: hdr_2 | C4: Критичный | D4: При первом посещении страницы в нижней части экрана появляется текст: "Мы используем файлы cookie для анализа трафика и улучшения вашего опыта. Некоторые cookie необходимы для работы сайта. Подробнее в нашей Политике использования cookie." | G4: Passed
A5: Хидер | B5: hdr_3 | C5: Критичный | D5: В текстовом сообщении две кнопки зеленого цвета: "Отклонить", "Принять все". | G5: Passed
A6: Хидер | B6: hdr_4 | C6: Критичный | D6: Логотип фонда в левом верхнем углу экрана отображается полностью, не обрезан. | G6: Passed
A7: Хидер | B7: hdr_5 | C7: Средний | D7: Используемый цвет шрифта в заголовке "БЛАГОТВОРИТЕЛЬНЫЙ ФОНД" на макете и на сайте: #267067. | G7: Passed
A8: Хидер | B8: hdr_6 | C8: Средний | D8: По центру блока расположена кнопка с текстом "Помочь". | E8: QA_Pomogi_2_39_Тестовая документация | G8: Failed
A9: Хидер | B9: hdr_7 | C9: Низкий | D9: Кнопка имеет прямоугольную форму с закругленными краями и "бордер". Название написано по центру кнопки. | G9: Passed
A10: Хидер | B10: hdr_8 | C10: Низкий | D10: Используемый цвет бордера: #267067. | G10: Passed
A11: Хидер | B11: hdr_9 | C11: Низкий | D11: Используемый цвет кнопки: #FFFFFF. | G11: Passed
A12: Хидер | B12: hdr_10 | C12: Низкий | D12: Используемый шрифт текста "Помочь": Montserrat. | G12: Passed
A13: Хидер | B13: hdr_11 | C13: Средний | D13: Под логотипом с лево расположен заголовок "ПОМОГИ ЛИЧНО", написанный жирными заглавными буквами. | G13: Passed
A14: Хидер | B14: hdr_12 | C14: Низкий | D14: Используемый цвет шрифта заголовка "ПОМОГИ ЛИЧНО" на макете и на сайте: #FFFFFF. | G14: Passed
A15: Хидер | B15: hdr_13 | C15: Низкий | D15: Под логотипом компании расположена "акцентная рамка". Используемый цвет акцентной рамки: #267067. | G15: Passed
A16: Хидер | B16: hdr_14 | C16: Низкий | D16: С правой стороны от кнопки расположена иконка (☰) Burger menu. Используемый цвет иконки: #267067. | G16: Passed
A17: Хидер | B17: hdr_15 | C17: Критичный | D17: Открытие по тапу на бургер-иконку. | G17: Passed
A18: Хидер | B18: hdr_16 | C18: Низкий | D18: Закрытие по тапу на крестик/бургер. | G18: Passed
A19: Хидер | B19: hdr_17 | C19: Низкий | D19: Закрытие по тапу вне области меню. | G19: Passed
A20: Хидер | B20: hdr_18 | C20: Высокий | D20: Меню занимает всю ширину экрана. | G20: Passed
... A44: Главная страница | B44: hm_pg_7 | C44: Низкий | D44: Под заголовком "Вы помогли этим детям!" по центру экрана расположен блок видео | G44: Passed
A45: Главная страница | B45: hm_pg_8 | C45: Низкий | D45: В блоке видео указано время, расположенное в правом нижнем углу. | E45: QA_Pomogi_2_39_Тестовая документация | G45: Failed
A46: Главная страница | B46: hm_pg_9 | C46: Низкий | D46: Блок времени состоит из прямоугольника с закруглёнными краями и цифрами по центру. | G46: Failed
A47: Главная страница | B47: hm_pg_10 | C47: Низкий | D47: Используемый цвет цифр на видео ("0:08") — #FFFFFF. | G47: Failed
A48: Главная страница | B48: hm_pg_11 | C48: Низкий | D48: Используемый цвет прямоугольника "время" — #000000. | G48: Failed
A49: Главная страница | B49: hm_pg_12 | C49: Низкий | D49: В блоке видео указано время, расположенное в правом нижнем углу. | G49: Failed
A50: Главная страница | B50: hm_pg_14 | C50: Низкий | D50: Используемый цвет шрифта "Подарки для Дарьи" — #267067. | G50: Passed
A51: Главная страница | B51: hm_pg_15 | C51: Низкий | D51: Используемый шрифт текста "Подарки для Дарьи" — "Montserrat". | G51: Passed
A52: Главная страница | B52: hm_pg_16 | C52: Низкий | D52: Ниже под заголовком с левого края "Подарки для Дарьи" расположены "Просмотры" 18 просмотров • 3 месяца назад". | G52: Passed
A53: Главная страница | B53: hm_pg_17 | C53: Низкий | D53: (Шрифт: Montserrat, цвет: #727271, размер: mob_XXS) | G53: Passed
A54: Главная страница | B54: hm_pg_18 | C54: Высокий | D54: Нажатии на блок видео , ведет на страницу Благотваворительный фонд "Помоги лично" | G54: Passed
A55: Главная страница | B55: hm_pg_19 | C55: Низкий | D55: Проверки аналогичны для каждого последующего блока. | G55: Passed
A56: Главная страница | B56: hm_pg_20 | C56: Низкий | D56: По центру видео, с левой и правой стороны, расположены стрелки навигации | G56: Passed
A57: Главная страница | B57: hm_pg_21 | C57: Средний | D57: Угловая стрелка кликабельна "<", ">" и имеет состояния: default ,hover, click,disable | G57: Passed
B58: hm_pg_22 | C58: Средний | D58: (<) при клике прокручивает карусель сфото влево (к началу списка). | E58: QA_Pomogi_2_39_Тестовая документация | G58: Passed
B59: hm_pg_23 | C59: Средний | D59: (>): При клике прокручивает карусель с фото вправо (к концу списка). | E59: QA_Pomogi_2_39_Тестовая документация | G59: Passed
A60: Главная страница | B60: hm_pg_24 | C60: Средний | D60: Свайп влево/вправо для просмотра блока с видео. | G60: Passed
A61: Главная страница | B61: hm_pg_25 | C61: Низкий | D61: В нижнем левом углу под блоком видео расположена сылка "Все дети →". | G61: Passed
A62: Главная страница | B62: hm_pg_26 | C62: Низкий | D62: Размер используемого шрифтассылки "Все дети →": mob_S ссылка. | G62: Passed
A63: Главная страница | B63: hm_pg_27 | C63: Низкий | D63: Используемый шрифт ссылки "Все дети →": Montserrat. | G63: Passed
A64: Главная страница | B64: hm_pg_28 | C64: Низкий | D64: Используемый цвет ссылки "Все дети →" на макете и на сайте: #267067. | G64: Passed
A65: Главная страница | B65: hm_pg_29 | C65: Низкий | D65: При нажатие на ссылку "Все дети →" появляется подцеркивани | G65: Passed
A66: Главная страница | B66: hm_pg_30 | C66: Высокий | D66: При клике на ссылку "Все дети →" открывается новое окно в браузере — на Благотваворительный фонд "Помоги лично" | G66: Passed
A67: Главная страница | B67: hm_pg_31 | C67: Низкий | D67: Под блоком видео "Вы помогли этим детям!" расположен блок "Нужна помощь! | G67: Passed
A68: Главная страница | B68: hm_pg_32 | C68: Низкий | D68: Шрифт: Neucha, | G68: Passed
A69: Главная страница | B69: hm_pg_33 | C69: Низкий | D69: Цвет: #FFFFFF | G69: Passed
A70: Главная страница | B70: hm_pg_34 | C70: Низкий | D70: Размер: mob_XL. | G70: Passed
A71: Главная страница | B71: hm_pg_35 | C71: Низкий | D71: Цвет "Подложка" - "Вы помогли этим детям!" — #EFB46D. | G71: Passed
... A81: Главная страница | B81: hm_pg_45 | C81: Средний | D81: Для обеих кнопок реализованы состояния default (по умолчанию) и hover(при нажатии). | G81: Passed
A82: Главная страница | B82: hm_pg_46 | C82: Средний | D82: При нажатие «Назад» (<) при клике прокручивает карусель сфото влево (к началу списка). | E82: QA_Pomogi_2_39_Тестовая документация | G82: Failed
A83: Главная страница | B83: hm_pg_47 | C83: Средний | D83: (>): При клике прокручивает карусель с фото вправо (к концу списка). | E83: QA_Pomogi_2_39_Тестовая документация | G83: Failed
A84: Главная страница | B84: hm_pg_48 | C84: Низкий | D84: Ниже под блоком фото расположен счетчик пожертвований, "Уже собрано 4 700 из 50 000 ₽" | G84: Passed
A85: Главная страница | B85: hm_pg_49 | C85: Низкий | D85: Шрифт:Montserrat | G85: Passed
A86: Главная страница | B86: hm_pg_50 | C86: Низкий | D86: Цвет: #267067 | G86: Passed
A87: Главная страница | B87: hm_pg_51 | C87: Низкий | D87: Размер: mob_XS медиум | G87: Passed
A88: Главная страница | B88: hm_pg_52 | C88: Низкий | D88: Под счетчиком средств расположен текст: "Дорогие друзья, в наш фонд". | G88: Passed
A89: Главная страница | B89: hm_pg_53 | C89: Низкий | D89: Размер шрифта: "mob_S", "Montserrat". | G89: Passed
A90: Главная страница | B90: hm_pg_54 | C90: Низкий | D90: Цвет шрифта: #000000. | G90: Passed
A91: Главная страница | B91: hm_pg_55 | C91: Критичный | D91: Под заголовком "Дорогие друзья, в наш фонд" по центру блока расположена кнопка "ПОМОЧЬ". | G91: Passed
